Workbook
Name \A: '[1]result-mi'!#REF!
Name \X: #REF!
Name \Y: #REF!
Name _1: #REF!
Name _2: '[1]result-mi'!#REF!
Name _3: #REF!
Name _4: '[1]result-mi'!#REF!
Name _5: '[1]result-mi'!#REF!
Name _DAT2: #REF!
Name aaaaaaaa: #N/A
Name asds: '[1]result-mi'!#REF!
Name Atualizacao_Variacao: #N/A
Name base: #REF!
Name Base_Precos: #REF!
Name Base_Rendimento: #REF!
Name Cad_Fam: #REF!
Name Carambei: [11]base!$CH$3:$CL$560
Name cbi: #REF!
Name cpz: #REF!
Name devers2: [12]MêsBase!$A$2:$Q$64
Name Divers: [13]MêsBase!$A$2:$Q$64
Name dsdsd: '[1]result-mi'!#REF!
Name dsfdsdsfg: '[1]result-mi'!#REF!
Name f: #N/A
Name frfsd: '[1]result-mi'!#REF!
Name Imprime_corrigido: #N/A
Name IMPRIME2: #N/A
Name Junho: '[1]result-mi'!#REF!
Name Local_Plan_ME: #N/A
Name MENU: '[1]result-mi'!#REF!
Name Módulo1.Local_Plan_ME: #N/A
Name Módulo1.Ocultar: #N/A
Name mrua: #REF!
Name mrus: #REF!
Name NvsASD: "V2001-12-31"
Name NvsAutoDrillOk: "VN"
Name NvsInstSpec: "%,FBU_FILIAL,TENTIDADES,NTMA"
Name NvsLayoutType: "M3"
Name NvsPanelEffdt: "V1990-01-01"
Name NvsPanelSetid: "VMODEL"
Name NvsReqBU: "VTEL"
Name NvsReqBUOnly: "VN"
Name NvsTransLed: "VN"
Name NvsTreeASD: "V2050-01-01"
Name NvsValTbl.BUSINESS_UNIT: "BUS_UNIT_TBL_GL"
Name Ocultar: #N/A
Name preço: [11]base!$A$3:$F$4003
Name RESACUM: #REF!
Name RESMES: #REF!
Name rre: '[1]result-mi'!#REF!
Name rveA: #REF!
Name rveS: #REF!
Name Sispec: [15]Sispec!$A$1:$M$65536
Name Sispec99: [16]Sispec99!$A$1:$M$65536
Name SispecPSAP: [17]SispecPSAP!$A$1:$M$65536
Name TabEmp: [16]Tabelas!$A$1:$C$74
Name TFRIG: '[1]result-mi'!#REF!
Name TNFRIG: '[1]result-mi'!#REF!
Name TNPIN: '[1]result-mi'!#REF!
Name TPIN: '[1]result-mi'!#REF!

Sheet COLAR PLANO
A1: CÓD. ITEM | C1: NOME DO ITEM | D1: Plano Mensal Alterado | E1: =SUBTOTAL(9,D2:D1204) -> 2160000 | F1: ='BD VOLUME'!F3 -> 2160000 | G1: =E1-F1 -> 0 | I1: =30/130 -> 0.23076923
A2: 985996 | C2: FRANGO CARC S/ MIUDOS CG | D2: =G2*1000 -> 0 | E2: =VLOOKUP(A2,'BD VOLUME'!A:F,6,0) -> 0 | G2: 0
A3: 797901 | C3: FRANGO INTEIRO CG PCT | D3: =G3*1000 -> 0 | E3: =VLOOKUP(A3,'BD VOLUME'!A:F,6,0) -> 0 | G3: 0
A4: 18244 | C4: COXINHA ASA CG ALM SE | D4: =G4*1000 -> 73324.8 | E4: =VLOOKUP(A4,'BD VOLUME'!A:F,6,0) -> 73324.8 | G4: 73.3248
A5: 990397 | C5: COXINHA DA ASA BDJ RF PRM | D5: =G5*1000 -> 1094.4 | E5: =VLOOKUP(A5,'BD VOLUME'!A:F,6,0) -> 1094.4 | G5: 1.0944
A6: 14290 | C6: MEIO ASA CG ALM | D6: =G6*1000 -> 56908.8 | E6: =VLOOKUP(A6,'BD VOLUME'!A:F,6,0) -> 56908.8 | G6: 56.9088
A7: 14133 | C7: ASA INT CG ITF SE | D7: =G7*1000 -> 87552 | E7: =VLOOKUP(A7,'BD VOLUME'!A:F,6,0) -> 87552 | G7: 87.552
A8: 997653 | C8: CARNE MS AVES CG CST MP ZG | D8: =G8*1000 -> 317088 | E8: =VLOOKUP(A8,'BD VOLUME'!A:F,6,0) -> 317088 | G8: 317.088
A9: 18163 | C9: CORACAO FGO CG ALM SE | D9: =G9*1000 -> 12096 | E9: =VLOOKUP(A9,'BD VOLUME'!A:F,6,0) -> 12096 | G9: 12.096
A10: 209669 | C10: FIGADO FG CG PCT | D10: =G10*1000 -> 42336 | E10: =VLOOKUP(A10,'BD VOLUME'!A:F,6,0) -> 42336 | G10: 42.336
A11: 14567 | C11: FILEZINHO PEITO CG BL SE | D11: =G11*1000 -> 120657.6 | E11: =VLOOKUP(A11,'BD VOLUME'!A:F,6,0) -> 120657.6 | G11: 120.6576
A12: 990389 | C12: FILEZINHO FG BDJ RF PRM 700G | D12: =G12*1000 -> 302.4 | E12: =VLOOKUP(A12,'BD VOLUME'!A:F,6,0) -> 302.4 | G12: 0.3024
A13: 18228 | C13: MOELA FRANGO CG ALM SE | D13: =G13*1000 -> 35712 | E13: =VLOOKUP(A13,'BD VOLUME'!A:F,6,0) -> 35712 | G13: 35.712
... A28: 55364 | C28: REC PEITO FGO CO MPL MP | D28: =G28*1000 -> 11232 | E28: =VLOOKUP(A28,'BD VOLUME'!A:F,6,0) -> 11232 | G28: 11.232
E29: =VLOOKUP(A29,'BD VOLUME'!A:F,6,0) -> #N/A
E30: =VLOOKUP(A30,'BD VOLUME'!A:F,6,0) -> #N/A
E31: =VLOOKUP(A31,'BD VOLUME'!A:F,6,0) -> #N/A
E32: =VLOOKUP(A32,'BD VOLUME'!A:F,6,0) -> #N/A
E33: =VLOOKUP(A33,'BD VOLUME'!A:F,6,0) -> #N/A
E34: =VLOOKUP(A34,'BD VOLUME'!A:F,6,0) -> #N/A
E35: =VLOOKUP(A35,'BD VOLUME'!A:F,6,0) -> #N/A
E36: =VLOOKUP(A36,'BD VOLUME'!A:F,6,0) -> #N/A
E37: =VLOOKUP(A37,'BD VOLUME'!A:F,6,0) -> #N/A
E38: =VLOOKUP(A38,'BD VOLUME'!A:F,6,0) -> #N/A
E39: =VLOOKUP(A39,'BD VOLUME'!A:F,6,0) -> #N/A
E40: =VLOOKUP(A40,'BD VOLUME'!A:F,6,0) -> #N/A
... E431: =VLOOKUP(A431,'BD VOLUME'!A:F,6,0) -> #N/A

Sheet BD VOLUME
B2: VELOCIDADE PADRÃO (FR/HORA) | C2: HORAS TRABALHADAS | D2: PESO MÉDIO FRANGO (KG) | E2: DIAS TRABALHADOS | F2: TOTAL PLANO DO SIMULADOR | G2: TOTAL PLANO DE PRODUÇÃO
A3: Grande | B3: =(SUM(Preencher!$I$13:$K$13)/(SUM(Preencher!$I$15:$K$16))) -> 4699.7389 | C3: =SUM(Preencher!$I$15:$K$16) -> 9.575 | D3: =Preencher!$I$23 -> 3 | E3: =Preencher!$I$11 -> 22 | F3: =SUBTOTAL(9,F8:F777) -> 2160000 | G3: ='COLAR PLANO'!E1 -> 2160000
A4: Pequeno | B4: =(SUM(Preencher!$I$14:$K$14)/(SUM(Preencher!$I$15:$K$16))) -> 0 | C4: =SUM(Preencher!$I$15:$K$16) -> 9.575 | D4: =Preencher!$I$24 -> 0 | E4: =Preencher!$I$11 -> 22
A6: Item | B6: Sigla | C6: Nm Item | D6: Família | E6: Sub Família | F6: Plano de Produção (kg/mês) | G6: Plano de produção (kg/hora) | H6: Rend. Prod. acabado | I6: Frangos/h | J6: % frangos desviados | K6: Peso pacote | L6: Nº pct/cx | M6: Peso Caxia | N6: pct/hr | O6: cx/hr Manual | P6: cx/hr Autom. | Q6: Bloc/hr CG | R6: Cx/hr RF | S6: Bloc/hr RF | T6: Lacr/hr | W6: MQ.TUNEL DE CG (CONTINUO) | X6: MQ.TUNEL DE CG (CONTINUO) (1) | Y6: MQ.TUNEL DE CG (CONTINUO) (2) | Z6: MQ.TUNEL DE CG (CONTINUO) (3) | AA6: MQ.TUNEL DE CG (ESTATICO) | AB6: MQ.TUNEL DE CG (ESTATICO) (1) | AC6: MQ.TUNEL DE CG (ESTATICO) (2) | AD6: Capacidade Tunel | AE6: Horas de tunel | AF6: MQ.GIROFREEZER | AG6: MQ.GIROFREEZER (1) | AH6: MQ.GIROFREEZER (2) | AI6: MQ.GIROFREEZER REV04 | AJ6: MQ.GIROFREEZER (3) | AK6: Capacidade Giro | AL6: Horas de giro
A7: MIUDOS | B7: =B3+B4 -> 4699.7389 | D7: =((B3*D3)+(B4*D4))/(B3+B4) -> 3 | AD7: =LARGE(AD8:AD1203,1) -> 0 | AE7: =SUBTOTAL(9,AE8:AE1203) -> 0 | AK7: =LARGE(AK8:AK1203,1) -> 0 | AL7: =SUBTOTAL(9,AL8:AL1203) -> 0
A8: 964310 | B8: 964310 | C8: MOELA FG CG PCT | D8: MIUDOS | E8: MOELA PACOTE 1 KG | F8: =SUMIF('COLAR PLANO'!$A:$A,A8,'COLAR PLANO'!$D:$D) -> 0 | G8: =IFERROR(F8/($E$3*$C$3),0) -> 0 | H8: 0.0106 | I8: =IFERROR(G8/$D$7/H8,0) -> 0 | J8: =IFERROR(I8/$B$7,0) -> 0 | K8: 1 | L8: 12 | M8: 12 | N8: =IFERROR(G8/K8,"-") -> 0 | P8: =IFERROR(G8/M8,"-") -> 0 | U8: - | V8: FRG | W8: =Preencher!$B$3&U8&V8&A8&$W$6 -> JARINU-FRG964310MQ.TUNEL DE CG (CONTINUO) | X8: =Preencher!$B$3&U8&V8&A8&$X$6 -> JARINU-FRG964310MQ.TUNEL DE CG (CONTINUO) (1) | Y8: =Preencher!$B$3&U8&V8&A8&$Y$6 -> JARINU-FRG964310MQ.TUNEL DE CG (CONTINUO) (2) | Z8: =Preencher!$B$3&U8&V8&A8&$Z$6 -> JARINU-FRG964310MQ.TUNEL DE CG (CONTINUO) (3) | AA8: =Preencher!$B$3&U8&V8&A8&$AA$6 -> JARINU-FRG964310MQ.TUNEL DE CG (ESTATICO) | AB8: =Preencher!$B$3&U8&V8&A8&$AB$6 -> JARINU-FRG964310MQ.TUNEL DE CG (ESTATICO) (1) | AC8: =Preencher!$B$3&U8&V8&A8&$AC$6 -> JARINU-FRG964310MQ.TUNEL DE CG (ESTATICO) (2) | AD8: =IFERROR(SUMIF('BD Otimix'!A:A,'BD VOLUME'!X8,'BD Otimix'!O:O)+SUMIF('BD Otimix'!A:A,'BD VOLUME'!Y8,'BD Otimix'!O:O)+SUMIF('BD Otimix'!A:A,'BD VOLUME'!Z8,'BD Otimix'!O:O)+SUMIF('BD Otimix'!A:A,'BD VOLUME'!AA8,'BD Otimix'!O:O)+SUMIF('BD Otimix'!A:A,'BD VOLUME'!AB8,'BD Otimix'!O:O)+SUMIF('BD Otimix'!A:A,'BD VOLUME'!AC8,'BD Otimix'!O:O)+SUMIF('BD Otimix'!A:A,'BD VOLUME'!W8,'BD Otimix'!O:O),0) -> 0 | AE8: =IFERROR(F8/$E$3/1000/AD8,0) -> 0 | AF8: =Preencher!$B$3&$U$8&$V$8&A8&$AF$6 -> JARINU-FRG964310MQ.GIROFREEZER | AG8: =Preencher!$B$3&$U$8&$V$8&A8&$AG$6 -> JARINU-FRG964310MQ.GIROFREEZER (1) | AH8: =Preencher!$B$3&$U$8&$V$8&A8&$AH$6 -> JARINU-FRG964310MQ.GIROFREEZER (2) | AI8: =Preencher!$B$3&$U$8&$V$8&A8&$AI$6 -> JARINU-FRG964310MQ.GIROFREEZER REV04 | AJ8: =Preencher!$B$3&$U$8&$V$8&A8&$AJ$6 -> JARINU-FRG964310MQ.GIROFREEZER (3) | AK8: =IFERROR(SUMIF('BD Otimix'!A:A,'BD VOLUME'!AG8,'BD Otimix'!O:O)+SUMIF('BD Otimix'!A:A,'BD VOLUME'!AH8,'BD Otimix'!O:O)+SUMIF('BD Otimix'!A:A,'BD VOLUME'!AI8,'BD Otimix'!O:O)+SUMIF('BD Otimix'!A:A,'BD VOLUME'!AJ8,'BD Otimix'!O:O)+SUMIF('BD Otimix'!A:A,'BD VOLUME'!AF8,'BD Otimix'!O:O),0) -> 0 | AL8: =IFERROR(F8/$E$3/1000/AK8,0) -> 0
A9: 40843 | B9: GI-32 | C9: MOELA FG PB | D9: MIUDOS | E9: MOELA PACOTE 1 KG | F9: =SUMIF('COLAR PLANO'!$A:$A,A9,'COLAR PLANO'!$D:$D) -> 0 | G9: =IFERROR(F9/($E$3*$C$3),0) -> 0 | H9: 0.0106 | I9: =IFERROR(G9/$D$7/H9,0) -> 0 | J9: =IFERROR(I9/$B$7,0) -> 0 | K9: 1 | L9: 12 | M9: 12 | N9: =IFERROR(G9/K9,"-") -> 0 | P9: =IFERROR(G9/M9,"-") -> 0 | U9: - | V9: FRG | W9: =Preencher!$B$3&U9&V9&A9&$W$6 -> JARINU-FRG40843MQ.TUNEL DE CG (CONTINUO) | X9: =Preencher!$B$3&U9&V9&A9&$X$6 -> JARINU-FRG40843MQ.TUNEL DE CG (CONTINUO) (1) | Y9: =Preencher!$B$3&U9&V9&A9&$Y$6 -> JARINU-FRG40843MQ.TUNEL DE CG (CONTINUO) (2) | Z9: =Preencher!$B$3&U9&V9&A9&$Z$6 -> JARINU-FRG40843MQ.TUNEL DE CG (CONTINUO) (3) | AA9: =Preencher!$B$3&U9&V9&A9&$AA$6 -> JARINU-FRG40843MQ.TUNEL DE CG (ESTATICO) | AB9: =Preencher!$B$3&U9&V9&A9&$AB$6 -> JARINU-FRG40843MQ.TUNEL DE CG (ESTATICO) (1) | AC9: =Preencher!$B$3&U9&V9&A9&$AC$6 -> JARINU-FRG40843MQ.TUNEL DE CG (ESTATICO) (2) | AD9: =IFERROR(SUMIF('BD Otimix'!A:A,'BD VOLUME'!X9,'BD Otimix'!O:O)+SUMIF('BD Otimix'!A:A,'BD VOLUME'!Y9,'BD Otimix'!O:O)+SUMIF('BD Otimix'!A:A,'BD VOLUME'!Z9,'BD Otimix'!O:O)+SUMIF('BD Otimix'!A:A,'BD VOLUME'!AA9,'BD Otimix'!O:O)+SUMIF('BD Otimix'!A:A,'BD VOLUME'!AB9,'BD Otimix'!O:O)+SUMIF('BD Otimix'!A:A,'BD VOLUME'!AC9,'BD Otimix'!O:O)+SUMIF('BD Otimix'!A:A,'BD VOLUME'!W9,'BD Otimix'!O:O),0) -> 0 | AE9: =IFERROR(F9/$E$3/1000/AD9,0) -> 0 | AF9: =Preencher!$B$3&$U$8&$V$8&A9&$AF$6 -> JARINU-FRG40843MQ.GIROFREEZER | AG9: =Preencher!$B$3&$U$8&$V$8&A9&$AG$6 -> JARINU-FRG40843MQ.GIROFREEZER (1) | AH9: =Preencher!$B$3&$U$8&$V$8&A9&$AH$6 -> JARINU-FRG40843MQ.GIROFREEZER (2) | AI9: =Preencher!$B$3&$U$8&$V$8&A9&$AI$6 -> JARINU-FRG40843MQ.GIROFREEZER REV04 | AJ9: =Preencher!$B$3&$U$8&$V$8&A9&$AJ$6 -> JARINU-FRG40843MQ.GIROFREEZER (3) | AK9: =IFERROR(SUMIF('BD Otimix'!A:A,'BD VOLUME'!AG9,'BD Otimix'!O:O)+SUMIF('BD Otimix'!A:A,'BD VOLUME'!AH9,'BD Otimix'!O:O)+SUMIF('BD Otimix'!A:A,'BD VOLUME'!AI9,'BD Otimix'!O:O)+SUMIF('BD Otimix'!A:A,'BD VOLUME'!AJ9,'BD Otimix'!O:O)+SUMIF('BD Otimix'!A:A,'BD VOLUME'!AF9,'BD Otimix'!O:O),0) -> 0 | AL9: =IFERROR(F9/$E$3/1000/AK9,0) -> 0
A10: 1039 | B10: GI-105 | C10: MOELA FG PB | D10: MIUDOS | E10: MOELA PACOTE 1 KG | F10: =SUMIF('COLAR PLANO'!$A:$A,A10,'COLAR PLANO'!$D:$D) -> 0 | G10: =IFERROR(F10/($E$3*$C$3),0) -> 0 | H10: 0.0106 | I10: =IFERROR(G10/$D$7/H10,0) -> 0 | J10: =IFERROR(I10/$B$7,0) -> 0 | K10: 1 | L10: 12 | M10: 12 | N10: =IFERROR(G10/K10,"-") -> 0 | P10: =IFERROR(G10/M10,"-") -> 0 | U10: - | V10: FRG | W10: =Preencher!$B$3&U10&V10&A10&$W$6 -> JARINU-FRG1039MQ.TUNEL DE CG (CONTINUO) | X10: =Preencher!$B$3&U10&V10&A10&$X$6 -> JARINU-FRG1039MQ.TUNEL DE CG (CONTINUO) (1) | Y10: =Preencher!$B$3&U10&V10&A10&$Y$6 -> JARINU-FRG1039MQ.TUNEL DE CG (CONTINUO) (2) | Z10: =Preencher!$B$3&U10&V10&A10&$Z$6 -> JARINU-FRG1039MQ.TUNEL DE CG (CONTINUO) (3) | AA10: =Preencher!$B$3&U10&V10&A10&$AA$6 -> JARINU-FRG1039MQ.TUNEL DE CG (ESTATICO) | AB10: =Preencher!$B$3&U10&V10&A10&$AB$6 -> JARINU-FRG1039MQ.TUNEL DE CG (ESTATICO) (1) | AC10: =Preencher!$B$3&U10&V10&A10&$AC$6 -> JARINU-FRG1039MQ.TUNEL DE CG (ESTATICO) (2) | AD10: =IFERROR(SUMIF('BD Otimix'!A:A,'BD VOLUME'!X10,'BD Otimix'!O:O)+SUMIF('BD Otimix'!A:A,'BD VOLUME'!Y10,'BD Otimix'!O:O)+SUMIF('BD Otimix'!A:A,'BD VOLUME'!Z10,'BD Otimix'!O:O)+SUMIF('BD Otimix'!A:A,'BD VOLUME'!AA10,'BD Otimix'!O:O)+SUMIF('BD Otimix'!A:A,'BD VOLUME'!AB10,'BD Otimix'!O:O)+SUMIF('BD Otimix'!A:A,'BD VOLUME'!AC10,'BD Otimix'!O:O)+SUMIF('BD Otimix'!A:A,'BD VOLUME'!W10,'BD Otimix'!O:O),0) -> 0 | AE10: =IFERROR(F10/$E$3/1000/AD10,0) -> 0 | AF10: =Preencher!$B$3&$U$8&$V$8&A10&$AF$6 -> JARINU-FRG1039MQ.GIROFREEZER | AG10: =Preencher!$B$3&$U$8&$V$8&A10&$AG$6 -> JARINU-FRG1039MQ.GIROFREEZER (1) | AH10: =Preencher!$B$3&$U$8&$V$8&A10&$AH$6 -> JARINU-FRG1039MQ.GIROFREEZER (2) | AI10: =Preencher!$B$3&$U$8&$V$8&A10&$AI$6 -> JARINU-FRG1039MQ.GIROFREEZER REV04 | AJ10: =Preencher!$B$3&$U$8&$V$8&A10&$AJ$6 -> JARINU-FRG1039MQ.GIROFREEZER (3) | AK10: =IFERROR(SUMIF('BD Otimix'!A:A,'BD VOLUME'!AG10,'BD Otimix'!O:O)+SUMIF('BD Otimix'!A:A,'BD VOLUME'!AH10,'BD Otimix'!O:O)+SUMIF('BD Otimix'!A:A,'BD VOLUME'!AI10,'BD Otimix'!O:O)+SUMIF('BD Otimix'!A:A,'BD VOLUME'!AJ10,'BD Otimix'!O:O)+SUMIF('BD Otimix'!A:A,'BD VOLUME'!AF10,'BD Otimix'!O:O),0) -> 0 | AL10: =IFERROR(F10/$E$3/1000/AK10,0) -> 0
A11: 44903 | B11: GI-13 | C11: MOELA FG PB | D11: MIUDOS | E11: MOELA PACOTE 1 KG | F11: =SUMIF('COLAR PLANO'!$A:$A,A11,'COLAR PLANO'!$D:$D) -> 0 | G11: =IFERROR(F11/($E$3*$C$3),0) -> 0 | H11: 0.0106 | I11: =IFERROR(G11/$D$7/H11,0) -> 0 | J11: =IFERROR(I11/$B$7,0) -> 0 | K11: 1 | L11: 16 | M11: 16 | N11: =IFERROR(G11/K11,"-") -> 0 | P11: =IFERROR(G11/M11,"-") -> 0 | U11: - | V11: FRG | W11: =Preencher!$B$3&U11&V11&A11&$W$6 -> JARINU-FRG44903MQ.TUNEL DE CG (CONTINUO) | X11: =Preencher!$B$3&U11&V11&A11&$X$6 -> JARINU-FRG44903MQ.TUNEL DE CG (CONTINUO) (1) | Y11: =Preencher!$B$3&U11&V11&A11&$Y$6 -> JARINU-FRG44903MQ.TUNEL DE CG (CONTINUO) (2) | Z11: =Preencher!$B$3&U11&V11&A11&$Z$6 -> JARINU-FRG44903MQ.TUNEL DE CG (CONTINUO) (3) | AA11: =Preencher!$B$3&U11&V11&A11&$AA$6 -> JARINU-FRG44903MQ.TUNEL DE CG (ESTATICO) | AB11: =Preencher!$B$3&U11&V11&A11&$AB$6 -> JARINU-FRG44903MQ.TUNEL DE CG (ESTATICO) (1) | AC11: =Preencher!$B$3&U11&V11&A11&$AC$6 -> JARINU-FRG44903MQ.TUNEL DE CG (ESTATICO) (2) | AD11: =IFERROR(SUMIF('BD Otimix'!A:A,'BD VOLUME'!X11,'BD Otimix'!O:O)+SUMIF('BD Otimix'!A:A,'BD VOLUME'!Y11,'BD Otimix'!O:O)+SUMIF('BD Otimix'!A:A,'BD VOLUME'!Z11,'BD Otimix'!O:O)+SUMIF('BD Otimix'!A:A,'BD VOLUME'!AA11,'BD Otimix'!O:O)+SUMIF('BD Otimix'!A:A,'BD VOLUME'!AB11,'BD Otimix'!O:O)+SUMIF('BD Otimix'!A:A,'BD VOLUME'!AC11,'BD Otimix'!O:O)+SUMIF('BD Otimix'!A:A,'BD VOLUME'!W11,'BD Otimix'!O:O),0) -> 0 | AE11: =IFERROR(F11/$E$3/1000/AD11,0) -> 0 | AF11: =Preencher!$B$3&$U$8&$V$8&A11&$AF$6 -> JARINU-FRG44903MQ.GIROFREEZER | AG11: =Preencher!$B$3&$U$8&$V$8&A11&$AG$6 -> JARINU-FRG44903MQ.GIROFREEZER (1) | AH11: =Preencher!$B$3&$U$8&$V$8&A11&$AH$6 -> JARINU-FRG44903MQ.GIROFREEZER (2) | AI11: =Preencher!$B$3&$U$8&$V$8&A11&$AI$6 -> JARINU-FRG44903MQ.GIROFREEZER REV04 | AJ11: =Preencher!$B$3&$U$8&$V$8&A11&$AJ$6 -> JARINU-FRG44903MQ.GIROFREEZER (3) | AK11: =IFERROR(SUMIF('BD Otimix'!A:A,'BD VOLUME'!AG11,'BD Otimix'!O:O)+SUMIF('BD Otimix'!A:A,'BD VOLUME'!AH11,'BD Otimix'!O:O)+SUMIF('BD Otimix'!A:A,'BD VOLUME'!AI11,'BD Otimix'!O:O)+SUMIF('BD Otimix'!A:A,'BD VOLUME'!AJ11,'BD Otimix'!O:O)+SUMIF('BD Otimix'!A:A,'BD VOLUME'!AF11,'BD Otimix'!O:O),0) -> 0 | AL11: =IFERROR(F11/$E$3/1000/AK11,0) -> 0
A12: 18228 | B12: MOE PC | C12: MOELA FRANGO CG ALM SE | D12: MIUDOS | E12: MOELA PACOTE 1 KG | F12: =SUMIF('COLAR PLANO'!$A:$A,A12,'COLAR PLANO'!$D:$D) -> 35712 | G12: =IFERROR(F12/($E$3*$C$3),0) -> 169.5324 | H12: 0.0106 | I12: =IFERROR(G12/$D$7/H12,0) -> 5331.2075 | J12: =IFERROR(I12/$B$7,0) -> 1.1343625 | K12: 1 | L12: 18 | M12: 18 | N12: =IFERROR(G12/K12,"-") -> 169.5324 | P12: =IFERROR(G12/M12,"-") -> 9.4184667 | U12: - | V12: FRG | W12: =Preencher!$B$3&U12&V12&A12&$W$6 -> JARINU-FRG18228MQ.TUNEL DE CG (CONTINUO) | X12: =Preencher!$B$3&U12&V12&A12&$X$6 -> JARINU-FRG18228MQ.TUNEL DE CG (CONTINUO) (1) | Y12: =Preencher!$B$3&U12&V12&A12&$Y$6 -> JARINU-FRG18228MQ.TUNEL DE CG (CONTINUO) (2) | Z12: =Preencher!$B$3&U12&V12&A12&$Z$6 -> JARINU-FRG18228MQ.TUNEL DE CG (CONTINUO) (3) | AA12: =Preencher!$B$3&U12&V12&A12&$AA$6 -> JARINU-FRG18228MQ.TUNEL DE CG (ESTATICO) | AB12: =Preencher!$B$3&U12&V12&A12&$AB$6 -> JARINU-FRG18228MQ.TUNEL DE CG (ESTATICO) (1) | AC12: =Preencher!$B$3&U12&V12&A12&$AC$6 -> JARINU-FRG18228MQ.TUNEL DE CG (ESTATICO) (2) | AD12: =IFERROR(SUMIF('BD Otimix'!A:A,'BD VOLUME'!X12,'BD Otimix'!O:O)+SUMIF('BD Otimix'!A:A,'BD VOLUME'!Y12,'BD Otimix'!O:O)+SUMIF('BD Otimix'!A:A,'BD VOLUME'!Z12,'BD Otimix'!O:O)+SUMIF('BD Otimix'!A:A,'BD VOLUME'!AA12,'BD Otimix'!O:O)+SUMIF('BD Otimix'!A:A,'BD VOLUME'!AB12,'BD Otimix'!O:O)+SUMIF('BD Otimix'!A:A,'BD VOLUME'!AC12,'BD Otimix'!O:O)+SUMIF('BD Otimix'!A:A,'BD VOLUME'!W12,'BD Otimix'!O:O),0) -> 0 | AE12: =IFERROR(F12/$E$3/1000/AD12,0) -> 0 | AF12: =Preencher!$B$3&$U$8&$V$8&A12&$AF$6 -> JARINU-FRG18228MQ.GIROFREEZER | AG12: =Preencher!$B$3&$U$8&$V$8&A12&$AG$6 -> JARINU-FRG18228MQ.GIROFREEZER (1) | AH12: =Preencher!$B$3&$U$8&$V$8&A12&$AH$6 -> JARINU-FRG18228MQ.GIROFREEZER (2) | AI12: =Preencher!$B$3&$U$8&$V$8&A12&$AI$6 -> JARINU-FRG18228MQ.GIROFREEZER REV04 | AJ12: =Preencher!$B$3&$U$8&$V$8&A12&$AJ$6 -> JARINU-FRG18228MQ.GIROFREEZER (3) | AK12: =IFERROR(SUMIF('BD Otimix'!A:A,'BD VOLUME'!AG12,'BD Otimix'!O:O)+SUMIF('BD Otimix'!A:A,'BD VOLUME'!AH12,'BD Otimix'!O:O)+SUMIF('BD Otimix'!A:A,'BD VOLUME'!AI12,'BD Otimix'!O:O)+SUMIF('BD Otimix'!A:A,'BD VOLUME'!AJ12,'BD Otimix'!O:O)+SUMIF('BD Otimix'!A:A,'BD VOLUME'!AF12,'BD Otimix'!O:O),0) -> 0 | AL12: =IFERROR(F12/$E$3/1000/AK12,0) -> 0
A13: 236769 | C13: MOELA FG BDJ GF | D13: MIUDOS | E13: MOELA BDJ CG | F13: =SUMIF('COLAR PLANO'!$A:$A,A13,'COLAR PLANO'!$D:$D) -> 0 | G13: =IFERROR(F13/($E$3*$C$3),0) -> 0 | H13: 0.0106 | I13: =IFERROR(G13/$D$7/H13,0) -> 0 | J13: =IFERROR(I13/$B$7,0) -> 0 | K13: 0.45 | L13: 16 | M13: 9 | N13: =IFERROR(G13/K13,"-") -> 0 | P13: =IFERROR(G13/M13,"-") -> 0 | U13: - | V13: FRG | W13: =Preencher!$B$3&U13&V13&A13&$W$6 -> JARINU-FRG236769MQ.TUNEL DE CG (CONTINUO) | X13: =Preencher!$B$3&U13&V13&A13&$X$6 -> JARINU-FRG236769MQ.TUNEL DE CG (CONTINUO) (1) | Y13: =Preencher!$B$3&U13&V13&A13&$Y$6 -> JARINU-FRG236769MQ.TUNEL DE CG (CONTINUO) (2) | Z13: =Preencher!$B$3&U13&V13&A13&$Z$6 -> JARINU-FRG236769MQ.TUNEL DE CG (CONTINUO) (3) | AA13: =Preencher!$B$3&U13&V13&A13&$AA$6 -> JARINU-FRG236769MQ.TUNEL DE CG (ESTATICO) | AB13: =Preencher!$B$3&U13&V13&A13&$AB$6 -> JARINU-FRG236769MQ.TUNEL DE CG (ESTATICO) (1) | AC13: =Preencher!$B$3&U13&V13&A13&$AC$6 -> JARINU-FRG236769MQ.TUNEL DE CG (ESTATICO) (2) | AD13: =IFERROR(SUMIF('BD Otimix'!A:A,'BD VOLUME'!X13,'BD Otimix'!O:O)+SUMIF('BD Otimix'!A:A,'BD VOLUME'!Y13,'BD Otimix'!O:O)+SUMIF('BD Otimix'!A:A,'BD VOLUME'!Z13,'BD Otimix'!O:O)+SUMIF('BD Otimix'!A:A,'BD VOLUME'!AA13,'BD Otimix'!O:O)+SUMIF('BD Otimix'!A:A,'BD VOLUME'!AB13,'BD Otimix'!O:O)+SUMIF('BD Otimix'!A:A,'BD VOLUME'!AC13,'BD Otimix'!O:O)+SUMIF('BD Otimix'!A:A,'BD VOLUME'!W13,'BD Otimix'!O:O),0) -> 0 | AE13: =IFERROR(F13/$E$3/1000/AD13,0) -> 0 | AF13: =Preencher!$B$3&$U$8&$V$8&A13&$AF$6 -> JARINU-FRG236769MQ.GIROFREEZER | AG13: =Preencher!$B$3&$U$8&$V$8&A13&$AG$6 -> JARINU-FRG236769MQ.GIROFREEZER (1) | AH13: =Preencher!$B$3&$U$8&$V$8&A13&$AH$6 -> JARINU-FRG236769MQ.GIROFREEZER (2) | AI13: =Preencher!$B$3&$U$8&$V$8&A13&$AI$6 -> JARINU-FRG236769MQ.GIROFREEZER REV04 | AJ13: =Preencher!$B$3&$U$8&$V$8&A13&$AJ$6 -> JARINU-FRG236769MQ.GIROFREEZER (3) | AK13: =IFERROR(SUMIF('BD Otimix'!A:A,'BD VOLUME'!AG13,'BD Otimix'!O:O)+SUMIF('BD Otimix'!A:A,'BD VOLUME'!AH13,'BD Otimix'!O:O)+SUMIF('BD Otimix'!A:A,'BD VOLUME'!AI13,'BD Otimix'!O:O)+SUMIF('BD Otimix'!A:A,'BD VOLUME'!AJ13,'BD Otimix'!O:O)+SUMIF('BD Otimix'!A:A,'BD VOLUME'!AF13,'BD Otimix'!O:O),0) -> 0 | AL13: =IFERROR(F13/$E$3/1000/AK13,0) -> 0
A14: 227909 | C14: MOELA FG BDJ NGF | D14: MIUDOS | E14: MOELA BDJ CG | F14: =SUMIF('COLAR PLANO'!$A:$A,A14,'COLAR PLANO'!$D:$D) -> 0 | G14: =IFERROR(F14/($E$3*$C$3),0) -> 0 | H14: 0.0106 | I14: =IFERROR(G14/$D$7/H14,0) -> 0 | J14: =IFERROR(I14/$B$7,0) -> 0 | K14: 1 | L14: 12 | M14: 12 | N14: =IFERROR(G14/K14,"-") -> 0 | P14: =IFERROR(G14/M14,"-") -> 0 | U14: - | V14: FRG | W14: =Preencher!$B$3&U14&V14&A14&$W$6 -> JARINU-FRG227909MQ.TUNEL DE CG (CONTINUO) | X14: =Preencher!$B$3&U14&V14&A14&$X$6 -> JARINU-FRG227909MQ.TUNEL DE CG (CONTINUO) (1) | Y14: =Preencher!$B$3&U14&V14&A14&$Y$6 -> JARINU-FRG227909MQ.TUNEL DE CG (CONTINUO) (2) | Z14: =Preencher!$B$3&U14&V14&A14&$Z$6 -> JARINU-FRG227909MQ.TUNEL DE CG (CONTINUO) (3) | AA14: =Preencher!$B$3&U14&V14&A14&$AA$6 -> JARINU-FRG227909MQ.TUNEL DE CG (ESTATICO) | AB14: =Preencher!$B$3&U14&V14&A14&$AB$6 -> JARINU-FRG227909MQ.TUNEL DE CG (ESTATICO) (1) | AC14: =Preencher!$B$3&U14&V14&A14&$AC$6 -> JARINU-FRG227909MQ.TUNEL DE CG (ESTATICO) (2) | AD14: =IFERROR(SUMIF('BD Otimix'!A:A,'BD VOLUME'!X14,'BD Otimix'!O:O)+SUMIF('BD Otimix'!A:A,'BD VOLUME'!Y14,'BD Otimix'!O:O)+SUMIF('BD Otimix'!A:A,'BD VOLUME'!Z14,'BD Otimix'!O:O)+SUMIF('BD Otimix'!A:A,'BD VOLUME'!AA14,'BD Otimix'!O:O)+SUMIF('BD Otimix'!A:A,'BD VOLUME'!AB14,'BD Otimix'!O:O)+SUMIF('BD Otimix'!A:A,'BD VOLUME'!AC14,'BD Otimix'!O:O)+SUMIF('BD Otimix'!A:A,'BD VOLUME'!W14,'BD Otimix'!O:O),0) -> 0 | AE14: =IFERROR(F14/$E$3/1000/AD14,0) -> 0 | AF14: =Preencher!$B$3&$U$8&$V$8&A14&$AF$6 -> JARINU-FRG227909MQ.GIROFREEZER | AG14: =Preencher!$B$3&$U$8&$V$8&A14&$AG$6 -> JARINU-FRG227909MQ.GIROFREEZER (1) | AH14: =Preencher!$B$3&$U$8&$V$8&A14&$AH$6 -> JARINU-FRG227909MQ.GIROFREEZER (2) | AI14: =Preencher!$B$3&$U$8&$V$8&A14&$AI$6 -> JARINU-FRG227909MQ.GIROFREEZER REV04 | AJ14: =Preencher!$B$3&$U$8&$V$8&A14&$AJ$6 -> JARINU-FRG227909MQ.GIROFREEZER (3) | AK14: =IFERROR(SUMIF('BD Otimix'!A:A,'BD VOLUME'!AG14,'BD Otimix'!O:O)+SUMIF('BD Otimix'!A:A,'BD VOLUME'!AH14,'BD Otimix'!O:O)+SUMIF('BD Otimix'!A:A,'BD VOLUME'!AI14,'BD Otimix'!O:O)+SUMIF('BD Otimix'!A:A,'BD VOLUME'!AJ14,'BD Otimix'!O:O)+SUMIF('BD Otimix'!A:A,'BD VOLUME'!AF14,'BD Otimix'!O:O),0) -> 0 | AL14: =IFERROR(F14/$E$3/1000/AK14,0) -> 0
A15: 999541 | C15: MIUDOS CONGELADOS DE FRANGO | D15: MIUDOS | E15: MOELA BDJ CG | F15: =SUMIF('COLAR PLANO'!$A:$A,A15,'COLAR PLANO'!$D:$D) -> 0 | G15: =IFERROR(F15/($E$3*$C$3),0) -> 0 | H15: 0.0106 | I15: =IFERROR(G15/$D$7/H15,0) -> 0 | J15: =IFERROR(I15/$B$7,0) -> 0 | K15: 0.45 | L15: 20 | M15: 9 | N15: =IFERROR(G15/K15,"-") -> 0 | P15: =IFERROR(G15/M15,"-") -> 0 | U15: - | V15: FRG | W15: =Preencher!$B$3&U15&V15&A15&$W$6 -> JARINU-FRG999541MQ.TUNEL DE CG (CONTINUO) | X15: =Preencher!$B$3&U15&V15&A15&$X$6 -> JARINU-FRG999541MQ.TUNEL DE CG (CONTINUO) (1) | Y15: =Preencher!$B$3&U15&V15&A15&$Y$6 -> JARINU-FRG999541MQ.TUNEL DE CG (CONTINUO) (2) | Z15: =Preencher!$B$3&U15&V15&A15&$Z$6 -> JARINU-FRG999541MQ.TUNEL DE CG (CONTINUO) (3) | AA15: =Preencher!$B$3&U15&V15&A15&$AA$6 -> JARINU-FRG999541MQ.TUNEL DE CG (ESTATICO) | AB15: =Preencher!$B$3&U15&V15&A15&$AB$6 -> JARINU-FRG999541MQ.TUNEL DE CG (ESTATICO) (1) | AC15: =Preencher!$B$3&U15&V15&A15&$AC$6 -> JARINU-FRG999541MQ.TUNEL DE CG (ESTATICO) (2) | AD15: =IFERROR(SUMIF('BD Otimix'!A:A,'BD VOLUME'!X15,'BD Otimix'!O:O)+SUMIF('BD Otimix'!A:A,'BD VOLUME'!Y15,'BD Otimix'!O:O)+SUMIF('BD Otimix'!A:A,'BD VOLUME'!Z15,'BD Otimix'!O:O)+SUMIF('BD Otimix'!A:A,'BD VOLUME'!AA15,'BD Otimix'!O:O)+SUMIF('BD Otimix'!A:A,'BD VOLUME'!AB15,'BD Otimix'!O:O)+SUMIF('BD Otimix'!A:A,'BD VOLUME'!AC15,'BD Otimix'!O:O)+SUMIF('BD Otimix'!A:A,'BD VOLUME'!W15,'BD Otimix'!O:O),0) -> 0 | AE15: =IFERROR(F15/$E$3/1000/AD15,0) -> 0 | AF15: =Preencher!$B$3&$U$8&$V$8&A15&$AF$6 -> JARINU-FRG999541MQ.GIROFREEZER | AG15: =Preencher!$B$3&$U$8&$V$8&A15&$AG$6 -> JARINU-FRG999541MQ.GIROFREEZER (1) | AH15: =Preencher!$B$3&$U$8&$V$8&A15&$AH$6 -> JARINU-FRG999541MQ.GIROFREEZER (2) | AI15: =Preencher!$B$3&$U$8&$V$8&A15&$AI$6 -> JARINU-FRG999541MQ.GIROFREEZER REV04 | AJ15: =Preencher!$B$3&$U$8&$V$8&A15&$AJ$6 -> JARINU-FRG999541MQ.GIROFREEZER (3) | AK15: =IFERROR(SUMIF('BD Otimix'!A:A,'BD VOLUME'!AG15,'BD Otimix'!O:O)+SUMIF('BD Otimix'!A:A,'BD VOLUME'!AH15,'BD Otimix'!O:O)+SUMIF('BD Otimix'!A:A,'BD VOLUME'!AI15,'BD Otimix'!O:O)+SUMIF('BD Otimix'!A:A,'BD VOLUME'!AJ15,'BD Otimix'!O:O)+SUMIF('BD Otimix'!A:A,'BD VOLUME'!AF15,'BD Otimix'!O:O),0) -> 0 | AL15: =IFERROR(F15/$E$3/1000/AK15,0) -> 0
A16: 999544 | C16: MIUDOS CONGELADOS DE FRANGO | D16: MIUDOS | E16: MOELA BDJ CG | F16: =SUMIF('COLAR PLANO'!$A:$A,A16,'COLAR PLANO'!$D:$D) -> 0 | G16: =IFERROR(F16/($E$3*$C$3),0) -> 0 | H16: 0.0106 | I16: =IFERROR(G16/$D$7/H16,0) -> 0 | J16: =IFERROR(I16/$B$7,0) -> 0 | K16: 0.45 | L16: 20 | M16: 9 | N16: =IFERROR(G16/K16,"-") -> 0 | P16: =IFERROR(G16/M16,"-") -> 0 | U16: - | V16: FRG | W16: =Preencher!$B$3&U16&V16&A16&$W$6 -> JARINU-FRG999544MQ.TUNEL DE CG (CONTINUO) | X16: =Preencher!$B$3&U16&V16&A16&$X$6 -> JARINU-FRG999544MQ.TUNEL DE CG (CONTINUO) (1) | Y16: =Preencher!$B$3&U16&V16&A16&$Y$6 -> JARINU-FRG999544MQ.TUNEL DE CG (CONTINUO) (2) | Z16: =Preencher!$B$3&U16&V16&A16&$Z$6 -> JARINU-FRG999544MQ.TUNEL DE CG (CONTINUO) (3) | AA16: =Preencher!$B$3&U16&V16&A16&$AA$6 -> JARINU-FRG999544MQ.TUNEL DE CG (ESTATICO) | AB16: =Preencher!$B$3&U16&V16&A16&$AB$6 -> JARINU-FRG999544MQ.TUNEL DE CG (ESTATICO) (1) | AC16: =Preencher!$B$3&U16&V16&A16&$AC$6 -> JARINU-FRG999544MQ.TUNEL DE CG (ESTATICO) (2) | AD16: =IFERROR(SUMIF('BD Otimix'!A:A,'BD VOLUME'!X16,'BD Otimix'!O:O)+SUMIF('BD Otimix'!A:A,'BD VOLUME'!Y16,'BD Otimix'!O:O)+SUMIF('BD Otimix'!A:A,'BD VOLUME'!Z16,'BD Otimix'!O:O)+SUMIF('BD Otimix'!A:A,'BD VOLUME'!AA16,'BD Otimix'!O:O)+SUMIF('BD Otimix'!A:A,'BD VOLUME'!AB16,'BD Otimix'!O:O)+SUMIF('BD Otimix'!A:A,'BD VOLUME'!AC16,'BD Otimix'!O:O)+SUMIF('BD Otimix'!A:A,'BD VOLUME'!W16,'BD Otimix'!O:O),0) -> 0 | AE16: =IFERROR(F16/$E$3/1000/AD16,0) -> 0 | AF16: =Preencher!$B$3&$U$8&$V$8&A16&$AF$6 -> JARINU-FRG999544MQ.GIROFREEZER | AG16: =Preencher!$B$3&$U$8&$V$8&A16&$AG$6 -> JARINU-FRG999544MQ.GIROFREEZER (1) | AH16: =Preencher!$B$3&$U$8&$V$8&A16&$AH$6 -> JARINU-FRG999544MQ.GIROFREEZER (2) | AI16: =Preencher!$B$3&$U$8&$V$8&A16&$AI$6 -> JARINU-FRG999544MQ.GIROFREEZER REV04 | AJ16: =Preencher!$B$3&$U$8&$V$8&A16&$AJ$6 -> JARINU-FRG999544MQ.GIROFREEZER (3) | AK16: =IFERROR(SUMIF('BD Otimix'!A:A,'BD VOLUME'!AG16,'BD Otimix'!O:O)+SUMIF('BD Otimix'!A:A,'BD VOLUME'!AH16,'BD Otimix'!O:O)+SUMIF('BD Otimix'!A:A,'BD VOLUME'!AI16,'BD Otimix'!O:O)+SUMIF('BD Otimix'!A:A,'BD VOLUME'!AJ16,'BD Otimix'!O:O)+SUMIF('BD Otimix'!A:A,'BD VOLUME'!AF16,'BD Otimix'!O:O),0) -> 0 | AL16: =IFERROR(F16/$E$3/1000/AK16,0) -> 0
A17: 12688 | C17: MOELA P/ REFEITORIO | D17: MIUDOS | E17: MOELA PACOTE 1 KG | F17: =SUMIF('COLAR PLANO'!$A:$A,A17,'COLAR PLANO'!$D:$D) -> 0 | G17: =IFERROR(F17/($E$3*$C$3),0) -> 0 | H17: 0.0106 | I17: =IFERROR(G17/$D$7/H17,0) -> 0 | J17: =IFERROR(I17/$B$7,0) -> 0 | K17: 1 | L17: 16 | M17: 16 | N17: =IFERROR(G17/K17,"-") -> 0 | P17: =IFERROR(G17/M17,"-") -> 0 | U17: - | V17: FRG | W17: =Preencher!$B$3&U17&V17&A17&$W$6 -> JARINU-FRG12688MQ.TUNEL DE CG (CONTINUO) | X17: =Preencher!$B$3&U17&V17&A17&$X$6 -> JARINU-FRG12688MQ.TUNEL DE CG (CONTINUO) (1) | Y17: =Preencher!$B$3&U17&V17&A17&$Y$6 -> JARINU-FRG12688MQ.TUNEL DE CG (CONTINUO) (2) | Z17: =Preencher!$B$3&U17&V17&A17&$Z$6 -> JARINU-FRG12688MQ.TUNEL DE CG (CONTINUO) (3) | AA17: =Preencher!$B$3&U17&V17&A17&$AA$6 -> JARINU-FRG12688MQ.TUNEL DE CG (ESTATICO) | AB17: =Preencher!$B$3&U17&V17&A17&$AB$6 -> JARINU-FRG12688MQ.TUNEL DE CG (ESTATICO) (1) | AC17: =Preencher!$B$3&U17&V17&A17&$AC$6 -> JARINU-FRG12688MQ.TUNEL DE CG (ESTATICO) (2) | AD17: =IFERROR(SUMIF('BD Otimix'!A:A,'BD VOLUME'!X17,'BD Otimix'!O:O)+SUMIF('BD Otimix'!A:A,'BD VOLUME'!Y17,'BD Otimix'!O:O)+SUMIF('BD Otimix'!A:A,'BD VOLUME'!Z17,'BD Otimix'!O:O)+SUMIF('BD Otimix'!A:A,'BD VOLUME'!AA17,'BD Otimix'!O:O)+SUMIF('BD Otimix'!A:A,'BD VOLUME'!AB17,'BD Otimix'!O:O)+SUMIF('BD Otimix'!A:A,'BD VOLUME'!AC17,'BD Otimix'!O:O)+SUMIF('BD Otimix'!A:A,'BD VOLUME'!W17,'BD Otimix'!O:O),0) -> 0 | AE17: =IFERROR(F17/$E$3/1000/AD17,0) -> 0 | AF17: =Preencher!$B$3&$U$8&$V$8&A17&$AF$6 -> JARINU-FRG12688MQ.GIROFREEZER | AG17: =Preencher!$B$3&$U$8&$V$8&A17&$AG$6 -> JARINU-FRG12688MQ.GIROFREEZER (1) | AH17: =Preencher!$B$3&$U$8&$V$8&A17&$AH$6 -> JARINU-FRG12688MQ.GIROFREEZER (2) | AI17: =Preencher!$B$3&$U$8&$V$8&A17&$AI$6 -> JARINU-FRG12688MQ.GIROFREEZER REV04 | AJ17: =Preencher!$B$3&$U$8&$V$8&A17&$AJ$6 -> JARINU-FRG12688MQ.GIROFREEZER (3) | AK17: =IFERROR(SUMIF('BD Otimix'!A:A,'BD VOLUME'!AG17,'BD Otimix'!O:O)+SUMIF('BD Otimix'!A:A,'BD VOLUME'!AH17,'BD Otimix'!O:O)+SUMIF('BD Otimix'!A:A,'BD VOLUME'!AI17,'BD Otimix'!O:O)+SUMIF('BD Otimix'!A:A,'BD VOLUME'!AJ17,'BD Otimix'!O:O)+SUMIF('BD Otimix'!A:A,'BD VOLUME'!AF17,'BD Otimix'!O:O),0) -> 0 | AL17: =IFERROR(F17/$E$3/1000/AK17,0) -> 0
A22: 997111 | C22: CORACAO CONG 18KG MP | D22: MIUDOS | E22: CORAÇÃO PACOTE 1 KG | F22: =SUMIF('COLAR PLANO'!$A:$A,A22,'COLAR PLANO'!$D:$D) -> 0 | G22: =IFERROR(F22/($E$3*$C$3),0) -> 0 | H22: 0.0047 | I22: =IFERROR(G22/$D$7/H22,0) -> 0 | J22: =IFERROR(I22/$B$7,0) -> 0 | K22: 1 | L22: 12 | M22: 12 | N22: =IFERROR(G22/K22,"-") -> 0 | P22: =IFERROR(G22/M22,"-") -> 0 | U22: - | V22: FRG | W22: =Preencher!$B$3&U22&V22&A22&$W$6 -> JARINU-FRG997111MQ.TUNEL DE CG (CONTINUO) | X22: =Preencher!$B$3&U22&V22&A22&$X$6 -> JARINU-FRG997111MQ.TUNEL DE CG (CONTINUO) (1) | Y22: =Preencher!$B$3&U22&V22&A22&$Y$6 -> JARINU-FRG997111MQ.TUNEL DE CG (CONTINUO) (2) | Z22: =Preencher!$B$3&U22&V22&A22&$Z$6 -> JARINU-FRG997111MQ.TUNEL DE CG (CONTINUO) (3) | AA22: =Preencher!$B$3&U22&V22&A22&$AA$6 -> JARINU-FRG997111MQ.TUNEL DE CG (ESTATICO) | AB22: =Preencher!$B$3&U22&V22&A22&$AB$6 -> JARINU-FRG997111MQ.TUNEL DE CG (ESTATICO) (1) | AC22: =Preencher!$B$3&U22&V22&A22&$AC$6 -> JARINU-FRG997111MQ.TUNEL DE CG (ESTATICO) (2) | AD22: =IFERROR(SUMIF('BD Otimix'!A:A,'BD VOLUME'!X22,'BD Otimix'!O:O)+SUMIF('BD Otimix'!A:A,'BD VOLUME'!Y22,'BD Otimix'!O:O)+SUMIF('BD Otimix'!A:A,'BD VOLUME'!Z22,'BD Otimix'!O:O)+SUMIF('BD Otimix'!A:A,'BD VOLUME'!AA22,'BD Otimix'!O:O)+SUMIF('BD Otimix'!A:A,'BD VOLUME'!AB22,'BD Otimix'!O:O)+SUMIF('BD Otimix'!A:A,'BD VOLUME'!AC22,'BD Otimix'!O:O)+SUMIF('BD Otimix'!A:A,'BD VOLUME'!W22,'BD Otimix'!O:O),0) -> 0 | AE22: =IFERROR(F22/$E$3/1000/AD22,0) -> 0 | AF22: =Preencher!$B$3&$U$8&$V$8&A22&$AF$6 -> JARINU-FRG997111MQ.GIROFREEZER | AG22: =Preencher!$B$3&$U$8&$V$8&A22&$AG$6 -> JARINU-FRG997111MQ.GIROFREEZER (1) | AH22: =Preencher!$B$3&$U$8&$V$8&A22&$AH$6 -> JARINU-FRG997111MQ.GIROFREEZER (2) | AI22: =Preencher!$B$3&$U$8&$V$8&A22&$AI$6 -> JARINU-FRG997111MQ.GIROFREEZER REV04 | AJ22: =Preencher!$B$3&$U$8&$V$8&A22&$AJ$6 -> JARINU-FRG997111MQ.GIROFREEZER (3) | AK22: =IFERROR(SUMIF('BD Otimix'!A:A,'BD VOLUME'!AG22,'BD Otimix'!O:O)+SUMIF('BD Otimix'!A:A,'BD VOLUME'!AH22,'BD Otimix'!O:O)+SUMIF('BD Otimix'!A:A,'BD VOLUME'!AI22,'BD Otimix'!O:O)+SUMIF('BD Otimix'!A:A,'BD VOLUME'!AJ22,'BD Otimix'!O:O)+SUMIF('BD Otimix'!A:A,'BD VOLUME'!AF22,'BD Otimix'!O:O),0) -> 0 | AL22: =IFERROR(F22/$E$3/1000/AK22,0) -> 0
A23: 18163 | C23: CORAÇÃO FGO CG ALM SE | D23: MIUDOS | E23: CORAÇÃO PACOTE 1 KG | F23: =SUMIF('COLAR PLANO'!$A:$A,A23,'COLAR PLANO'!$D:$D) -> 12096 | G23: =IFERROR(F23/($E$3*$C$3),0) -> 57.422264 | H23: 0.0047 | I23: =IFERROR(G23/$D$7/H23,0) -> 4072.501 | J23: =IFERROR(I23/$B$7,0) -> 0.86653772 | K23: 1 | L23: 12 | M23: 12 | N23: =IFERROR(G23/K23,"-") -> 57.422264 | P23: =IFERROR(G23/M23,"-") -> 4.7851887 | U23: - | V23: FRG | W23: =Preencher!$B$3&U23&V23&A23&$W$6 -> JARINU-FRG18163MQ.TUNEL DE CG (CONTINUO) | X23: =Preencher!$B$3&U23&V23&A23&$X$6 -> JARINU-FRG18163MQ.TUNEL DE CG (CONTINUO) (1) | Y23: =Preencher!$B$3&U23&V23&A23&$Y$6 -> JARINU-FRG18163MQ.TUNEL DE CG (CONTINUO) (2) | Z23: =Preencher!$B$3&U23&V23&A23&$Z$6 -> JARINU-FRG18163MQ.TUNEL DE CG (CONTINUO) (3) | AA23: =Preencher!$B$3&U23&V23&A23&$AA$6 -> JARINU-FRG18163MQ.TUNEL DE CG (ESTATICO) | AB23: =Preencher!$B$3&U23&V23&A23&$AB$6 -> JARINU-FRG18163MQ.TUNEL DE CG (ESTATICO) (1) | AC23: =Preencher!$B$3&U23&V23&A23&$AC$6 -> JARINU-FRG18163MQ.TUNEL DE CG (ESTATICO) (2) | AD23: =IFERROR(SUMIF('BD Otimix'!A:A,'BD VOLUME'!X23,'BD Otimix'!O:O)+SUMIF('BD Otimix'!A:A,'BD VOLUME'!Y23,'BD Otimix'!O:O)+SUMIF('BD Otimix'!A:A,'BD VOLUME'!Z23,'BD Otimix'!O:O)+SUMIF('BD Otimix'!A:A,'BD VOLUME'!AA23,'BD Otimix'!O:O)+SUMIF('BD Otimix'!A:A,'BD VOLUME'!AB23,'BD Otimix'!O:O)+SUMIF('BD Otimix'!A:A,'BD VOLUME'!AC23,'BD Otimix'!O:O)+SUMIF('BD Otimix'!A:A,'BD VOLUME'!W23,'BD Otimix'!O:O),0) -> 0 | AE23: =IFERROR(F23/$E$3/1000/AD23,0) -> 0 | AF23: =Preencher!$B$3&$U$8&$V$8&A23&$AF$6 -> JARINU-FRG18163MQ.GIROFREEZER | AG23: =Preencher!$B$3&$U$8&$V$8&A23&$AG$6 -> JARINU-FRG18163MQ.GIROFREEZER (1) | AH23: =Preencher!$B$3&$U$8&$V$8&A23&$AH$6 -> JARINU-FRG18163MQ.GIROFREEZER (2) | AI23: =Preencher!$B$3&$U$8&$V$8&A23&$AI$6 -> JARINU-FRG18163MQ.GIROFREEZER REV04 | AJ23: =Preencher!$B$3&$U$8&$V$8&A23&$AJ$6 -> JARINU-FRG18163MQ.GIROFREEZER (3) | AK23: =IFERROR(SUMIF('BD Otimix'!A:A,'BD VOLUME'!AG23,'BD Otimix'!O:O)+SUMIF('BD Otimix'!A:A,'BD VOLUME'!AH23,'BD Otimix'!O:O)+SUMIF('BD Otimix'!A:A,'BD VOLUME'!AI23,'BD Otimix'!O:O)+SUMIF('BD Otimix'!A:A,'BD VOLUME'!AJ23,'BD Otimix'!O:O)+SUMIF('BD Otimix'!A:A,'BD VOLUME'!AF23,'BD Otimix'!O:O),0) -> 0 | AL23: =IFERROR(F23/$E$3/1000/AK23,0) -> 0
A24: 15423 | B24: COR-BJ | C24: CORACAO FGO CG BDJ SE | D24: MIUDOS | E24: CORAÇÃO BDJ CG | F24: =SUMIF('COLAR PLANO'!$A:$A,A24,'COLAR PLANO'!$D:$D) -> 0 | G24: =IFERROR(F24/($E$3*$C$3),0) -> 0 | H24: 0.0047 | I24: =IFERROR(G24/$D$7/H24,0) -> 0 | J24: =IFERROR(I24/$B$7,0) -> 0 | K24: 0.45 | L24: 16 | M24: 9 | N24: =IFERROR(G24/K24,"-") -> 0 | P24: =IFERROR(G24/M24,"-") -> 0 | U24: - | V24: FRG | W24: =Preencher!$B$3&U24&V24&A24&$W$6 -> JARINU-FRG15423MQ.TUNEL DE CG (CONTINUO) | X24: =Preencher!$B$3&U24&V24&A24&$X$6 -> JARINU-FRG15423MQ.TUNEL DE CG (CONTINUO) (1) | Y24: =Preencher!$B$3&U24&V24&A24&$Y$6 -> JARINU-FRG15423MQ.TUNEL DE CG (CONTINUO) (2) | Z24: =Preencher!$B$3&U24&V24&A24&$Z$6 -> JARINU-FRG15423MQ.TUNEL DE CG (CONTINUO) (3) | AA24: =Preencher!$B$3&U24&V24&A24&$AA$6 -> JARINU-FRG15423MQ.TUNEL DE CG (ESTATICO) | AB24: =Preencher!$B$3&U24&V24&A24&$AB$6 -> JARINU-FRG15423MQ.TUNEL DE CG (ESTATICO) (1) | AC24: =Preencher!$B$3&U24&V24&A24&$AC$6 -> JARINU-FRG15423MQ.TUNEL DE CG (ESTATICO) (2) | AD24: =IFERROR(SUMIF('BD Otimix'!A:A,'BD VOLUME'!X24,'BD Otimix'!O:O)+SUMIF('BD Otimix'!A:A,'BD VOLUME'!Y24,'BD Otimix'!O:O)+SUMIF('BD Otimix'!A:A,'BD VOLUME'!Z24,'BD Otimix'!O:O)+SUMIF('BD Otimix'!A:A,'BD VOLUME'!AA24,'BD Otimix'!O:O)+SUMIF('BD Otimix'!A:A,'BD VOLUME'!AB24,'BD Otimix'!O:O)+SUMIF('BD Otimix'!A:A,'BD VOLUME'!AC24,'BD Otimix'!O:O)+SUMIF('BD Otimix'!A:A,'BD VOLUME'!W24,'BD Otimix'!O:O),0) -> 0 | AE24: =IFERROR(F24/$E$3/1000/AD24,0) -> 0 | AF24: =Preencher!$B$3&$U$8&$V$8&A24&$AF$6 -> JARINU-FRG15423MQ.GIROFREEZER | AG24: =Preencher!$B$3&$U$8&$V$8&A24&$AG$6 -> JARINU-FRG15423MQ.GIROFREEZER (1) | AH24: =Preencher!$B$3&$U$8&$V$8&A24&$AH$6 -> JARINU-FRG15423MQ.GIROFREEZER (2) | AI24: =Preencher!$B$3&$U$8&$V$8&A24&$AI$6 -> JARINU-FRG15423MQ.GIROFREEZER REV04 | AJ24: =Preencher!$B$3&$U$8&$V$8&A24&$AJ$6 -> JARINU-FRG15423MQ.GIROFREEZER (3) | AK24: =IFERROR(SUMIF('BD Otimix'!A:A,'BD VOLUME'!AG24,'BD Otimix'!O:O)+SUMIF('BD Otimix'!A:A,'BD VOLUME'!AH24,'BD Otimix'!O:O)+SUMIF('BD Otimix'!A:A,'BD VOLUME'!AI24,'BD Otimix'!O:O)+SUMIF('BD Otimix'!A:A,'BD VOLUME'!AJ24,'BD Otimix'!O:O)+SUMIF('BD Otimix'!A:A,'BD VOLUME'!AF24,'BD Otimix'!O:O),0) -> 0 | AL24: =IFERROR(F24/$E$3/1000/AK24,0) -> 0
A25: 729850 | B25: COR-01 | C25: CORACAO FGO RESF BDJ SE | D25: MIUDOS | E25: CORAÇÃO BDJ RF | F25: =SUMIF('COLAR PLANO'!$A:$A,A25,'COLAR PLANO'!$D:$D) -> 0 | G25: =IFERROR(F25/($E$3*$C$3),0) -> 0 | H25: 0.0047 | I25: =IFERROR(G25/$D$7/H25,0) -> 0 | J25: =IFERROR(I25/$B$7,0) -> 0 | K25: 0.65 | L25: 10 | M25: 6.5 | N25: =IFERROR(G25/K25,"-") -> 0 | P25: =IFERROR(G25/M25,"-") -> 0 | U25: - | V25: FRG | W25: =Preencher!$B$3&U25&V25&A25&$W$6 -> JARINU-FRG729850MQ.TUNEL DE CG (CONTINUO) | X25: =Preencher!$B$3&U25&V25&A25&$X$6 -> JARINU-FRG729850MQ.TUNEL DE CG (CONTINUO) (1) | Y25: =Preencher!$B$3&U25&V25&A25&$Y$6 -> JARINU-FRG729850MQ.TUNEL DE CG (CONTINUO) (2) | Z25: =Preencher!$B$3&U25&V25&A25&$Z$6 -> JARINU-FRG729850MQ.TUNEL DE CG (CONTINUO) (3) | AA25: =Preencher!$B$3&U25&V25&A25&$AA$6 -> JARINU-FRG729850MQ.TUNEL DE CG (ESTATICO) | AB25: =Preencher!$B$3&U25&V25&A25&$AB$6 -> JARINU-FRG729850MQ.TUNEL DE CG (ESTATICO) (1) | AC25: =Preencher!$B$3&U25&V25&A25&$AC$6 -> JARINU-FRG729850MQ.TUNEL DE CG (ESTATICO) (2) | AD25: =IFERROR(SUMIF('BD Otimix'!A:A,'BD VOLUME'!X25,'BD Otimix'!O:O)+SUMIF('BD Otimix'!A:A,'BD VOLUME'!Y25,'BD Otimix'!O:O)+SUMIF('BD Otimix'!A:A,'BD VOLUME'!Z25,'BD Otimix'!O:O)+SUMIF('BD Otimix'!A:A,'BD VOLUME'!AA25,'BD Otimix'!O:O)+SUMIF('BD Otimix'!A:A,'BD VOLUME'!AB25,'BD Otimix'!O:O)+SUMIF('BD Otimix'!A:A,'BD VOLUME'!AC25,'BD Otimix'!O:O)+SUMIF('BD Otimix'!A:A,'BD VOLUME'!W25,'BD Otimix'!O:O),0) -> 0 | AE25: =IFERROR(F25/$E$3/1000/AD25,0) -> 0 | AF25: =Preencher!$B$3&$U$8&$V$8&A25&$AF$6 -> JARINU-FRG729850MQ.GIROFREEZER | AG25: =Preencher!$B$3&$U$8&$V$8&A25&$AG$6 -> JARINU-FRG729850MQ.GIROFREEZER (1) | AH25: =Preencher!$B$3&$U$8&$V$8&A25&$AH$6 -> JARINU-FRG729850MQ.GIROFREEZER (2) | AI25: =Preencher!$B$3&$U$8&$V$8&A25&$AI$6 -> JARINU-FRG729850MQ.GIROFREEZER REV04 | AJ25: =Preencher!$B$3&$U$8&$V$8&A25&$AJ$6 -> JARINU-FRG729850MQ.GIROFREEZER (3) | AK25: =IFERROR(SUMIF('BD Otimix'!A:A,'BD VOLUME'!AG25,'BD Otimix'!O:O)+SUMIF('BD Otimix'!A:A,'BD VOLUME'!AH25,'BD Otimix'!O:O)+SUMIF('BD Otimix'!A:A,'BD VOLUME'!AI25,'BD Otimix'!O:O)+SUMIF('BD Otimix'!A:A,'BD VOLUME'!AJ25,'BD Otimix'!O:O)+SUMIF('BD Otimix'!A:A,'BD VOLUME'!AF25,'BD Otimix'!O:O),0) -> 0 | AL25: =IFERROR(F25/$E$3/1000/AK25,0) -> 0
A26: 956767 | C26: MIUDOS CG FG CORACAO BDJ 1KG | D26: MIUDOS | E26: CORAÇÃO BDJ CG | F26: =SUMIF('COLAR PLANO'!$A:$A,A26,'COLAR PLANO'!$D:$D) -> 0 | G26: =IFERROR(F26/($E$3*$C$3),0) -> 0 | H26: 0.0047 | I26: =IFERROR(G26/$D$7/H26,0) -> 0 | J26: =IFERROR(I26/$B$7,0) -> 0 | K26: 1 | L26: 12 | M26: 12 | N26: =IFERROR(G26/K26,"-") -> 0 | P26: =IFERROR(G26/M26,"-") -> 0 | U26: - | V26: FRG | W26: =Preencher!$B$3&U26&V26&A26&$W$6 -> JARINU-FRG956767MQ.TUNEL DE CG (CONTINUO) | X26: =Preencher!$B$3&U26&V26&A26&$X$6 -> JARINU-FRG956767MQ.TUNEL DE CG (CONTINUO) (1) | Y26: =Preencher!$B$3&U26&V26&A26&$Y$6 -> JARINU-FRG956767MQ.TUNEL DE CG (CONTINUO) (2) | Z26: =Preencher!$B$3&U26&V26&A26&$Z$6 -> JARINU-FRG956767MQ.TUNEL DE CG (CONTINUO) (3) | AA26: =Preencher!$B$3&U26&V26&A26&$AA$6 -> JARINU-FRG956767MQ.TUNEL DE CG (ESTATICO) | AB26: =Preencher!$B$3&U26&V26&A26&$AB$6 -> JARINU-FRG956767MQ.TUNEL DE CG (ESTATICO) (1) | AC26: =Preencher!$B$3&U26&V26&A26&$AC$6 -> JARINU-FRG956767MQ.TUNEL DE CG (ESTATICO) (2) | AD26: =IFERROR(SUMIF('BD Otimix'!A:A,'BD VOLUME'!X26,'BD Otimix'!O:O)+SUMIF('BD Otimix'!A:A,'BD VOLUME'!Y26,'BD Otimix'!O:O)+SUMIF('BD Otimix'!A:A,'BD VOLUME'!Z26,'BD Otimix'!O:O)+SUMIF('BD Otimix'!A:A,'BD VOLUME'!AA26,'BD Otimix'!O:O)+SUMIF('BD Otimix'!A:A,'BD VOLUME'!AB26,'BD Otimix'!O:O)+SUMIF('BD Otimix'!A:A,'BD VOLUME'!AC26,'BD Otimix'!O:O)+SUMIF('BD Otimix'!A:A,'BD VOLUME'!W26,'BD Otimix'!O:O),0) -> 0 | AE26: =IFERROR(F26/$E$3/1000/AD26,0) -> 0 | AF26: =Preencher!$B$3&$U$8&$V$8&A26&$AF$6 -> JARINU-FRG956767MQ.GIROFREEZER | AG26: =Preencher!$B$3&$U$8&$V$8&A26&$AG$6 -> JARINU-FRG956767MQ.GIROFREEZER (1) | AH26: =Preencher!$B$3&$U$8&$V$8&A26&$AH$6 -> JARINU-FRG956767MQ.GIROFREEZER (2) | AI26: =Preencher!$B$3&$U$8&$V$8&A26&$AI$6 -> JARINU-FRG956767MQ.GIROFREEZER REV04 | AJ26: =Preencher!$B$3&$U$8&$V$8&A26&$AJ$6 -> JARINU-FRG956767MQ.GIROFREEZER (3) | AK26: =IFERROR(SUMIF('BD Otimix'!A:A,'BD VOLUME'!AG26,'BD Otimix'!O:O)+SUMIF('BD Otimix'!A:A,'BD VOLUME'!AH26,'BD Otimix'!O:O)+SUMIF('BD Otimix'!A:A,'BD VOLUME'!AI26,'BD Otimix'!O:O)+SUMIF('BD Otimix'!A:A,'BD VOLUME'!AJ26,'BD Otimix'!O:O)+SUMIF('BD Otimix'!A:A,'BD VOLUME'!AF26,'BD Otimix'!O:O),0) -> 0 | AL26: =IFERROR(F26/$E$3/1000/AK26,0) -> 0
A27: 124462 | B27: tmf | C27: MIUDOS TEMP RESF FG CORACAO | D27: MIUDOS | E27: CORAÇÃO BDJ CG | F27: =SUMIF('COLAR PLANO'!$A:$A,A27,'COLAR PLANO'!$D:$D) -> 0 | G27: =IFERROR(F27/($E$3*$C$3),0) -> 0 | H27: 0.0047 | I27: =IFERROR(G27/$D$7/H27,0) -> 0 | J27: =IFERROR(I27/$B$7,0) -> 0 | K27: 1 | L27: 12 | M27: 12 | N27: =IFERROR(G27/K27,"-") -> 0 | P27: =IFERROR(G27/M27,"-") -> 0 | U27: - | V27: FRG | W27: =Preencher!$B$3&U27&V27&A27&$W$6 -> JARINU-FRG124462MQ.TUNEL DE CG (CONTINUO) | X27: =Preencher!$B$3&U27&V27&A27&$X$6 -> JARINU-FRG124462MQ.TUNEL DE CG (CONTINUO) (1) | Y27: =Preencher!$B$3&U27&V27&A27&$Y$6 -> JARINU-FRG124462MQ.TUNEL DE CG (CONTINUO) (2) | Z27: =Preencher!$B$3&U27&V27&A27&$Z$6 -> JARINU-FRG124462MQ.TUNEL DE CG (CONTINUO) (3) | AA27: =Preencher!$B$3&U27&V27&A27&$AA$6 -> JARINU-FRG124462MQ.TUNEL DE CG (ESTATICO) | AB27: =Preencher!$B$3&U27&V27&A27&$AB$6 -> JARINU-FRG124462MQ.TUNEL DE CG (ESTATICO) (1) | AC27: =Preencher!$B$3&U27&V27&A27&$AC$6 -> JARINU-FRG124462MQ.TUNEL DE CG (ESTATICO) (2) | AD27: =IFERROR(SUMIF('BD Otimix'!A:A,'BD VOLUME'!X27,'BD Otimix'!O:O)+SUMIF('BD Otimix'!A:A,'BD VOLUME'!Y27,'BD Otimix'!O:O)+SUMIF('BD Otimix'!A:A,'BD VOLUME'!Z27,'BD Otimix'!O:O)+SUMIF('BD Otimix'!A:A,'BD VOLUME'!AA27,'BD Otimix'!O:O)+SUMIF('BD Otimix'!A:A,'BD VOLUME'!AB27,'BD Otimix'!O:O)+SUMIF('BD Otimix'!A:A,'BD VOLUME'!AC27,'BD Otimix'!O:O)+SUMIF('BD Otimix'!A:A,'BD VOLUME'!W27,'BD Otimix'!O:O),0) -> 0 | AE27: =IFERROR(F27/$E$3/1000/AD27,0) -> 0 | AF27: =Preencher!$B$3&$U$8&$V$8&A27&$AF$6 -> JARINU-FRG124462MQ.GIROFREEZER | AG27: =Preencher!$B$3&$U$8&$V$8&A27&$AG$6 -> JARINU-FRG124462MQ.GIROFREEZER (1) | AH27: =Preencher!$B$3&$U$8&$V$8&A27&$AH$6 -> JARINU-FRG124462MQ.GIROFREEZER (2) | AI27: =Preencher!$B$3&$U$8&$V$8&A27&$AI$6 -> JARINU-FRG124462MQ.GIROFREEZER REV04 | AJ27: =Preencher!$B$3&$U$8&$V$8&A27&$AJ$6 -> JARINU-FRG124462MQ.GIROFREEZER (3) | AK27: =IFERROR(SUMIF('BD Otimix'!A:A,'BD VOLUME'!AG27,'BD Otimix'!O:O)+SUMIF('BD Otimix'!A:A,'BD VOLUME'!AH27,'BD Otimix'!O:O)+SUMIF('BD Otimix'!A:A,'BD VOLUME'!AI27,'BD Otimix'!O:O)+SUMIF('BD Otimix'!A:A,'BD VOLUME'!AJ27,'BD Otimix'!O:O)+SUMIF('BD Otimix'!A:A,'BD VOLUME'!AF27,'BD Otimix'!O:O),0) -> 0 | AL27: =IFERROR(F27/$E$3/1000/AK27,0) -> 0
A28: 124369 | C28: MIUDOS CG FG TEMP CORACAO BD | D28: MIUDOS | E28: CORAÇÃO BDJ CG | F28: =SUMIF('COLAR PLANO'!$A:$A,A28,'COLAR PLANO'!$D:$D) -> 0 | G28: =IFERROR(F28/($E$3*$C$3),0) -> 0 | H28: 0.0047 | I28: =IFERROR(G28/$D$7/H28,0) -> 0 | J28: =IFERROR(I28/$B$7,0) -> 0 | K28: 1 | L28: 12 | M28: 12 | N28: =IFERROR(G28/K28,"-") -> 0 | P28: =IFERROR(G28/M28,"-") -> 0 | U28: - | V28: FRG | W28: =Preencher!$B$3&U28&V28&A28&$W$6 -> JARINU-FRG124369MQ.TUNEL DE CG (CONTINUO) | X28: =Preencher!$B$3&U28&V28&A28&$X$6 -> JARINU-FRG124369MQ.TUNEL DE CG (CONTINUO) (1) | Y28: =Preencher!$B$3&U28&V28&A28&$Y$6 -> JARINU-FRG124369MQ.TUNEL DE CG (CONTINUO) (2) | Z28: =Preencher!$B$3&U28&V28&A28&$Z$6 -> JARINU-FRG124369MQ.TUNEL DE CG (CONTINUO) (3) | AA28: =Preencher!$B$3&U28&V28&A28&$AA$6 -> JARINU-FRG124369MQ.TUNEL DE CG (ESTATICO) | AB28: =Preencher!$B$3&U28&V28&A28&$AB$6 -> JARINU-FRG124369MQ.TUNEL DE CG (ESTATICO) (1) | AC28: =Preencher!$B$3&U28&V28&A28&$AC$6 -> JARINU-FRG124369MQ.TUNEL DE CG (ESTATICO) (2) | AD28: =IFERROR(SUMIF('BD Otimix'!A:A,'BD VOLUME'!X28,'BD Otimix'!O:O)+SUMIF('BD Otimix'!A:A,'BD VOLUME'!Y28,'BD Otimix'!O:O)+SUMIF('BD Otimix'!A:A,'BD VOLUME'!Z28,'BD Otimix'!O:O)+SUMIF('BD Otimix'!A:A,'BD VOLUME'!AA28,'BD Otimix'!O:O)+SUMIF('BD Otimix'!A:A,'BD VOLUME'!AB28,'BD Otimix'!O:O)+SUMIF('BD Otimix'!A:A,'BD VOLUME'!AC28,'BD Otimix'!O:O)+SUMIF('BD Otimix'!A:A,'BD VOLUME'!W28,'BD Otimix'!O:O),0) -> 0 | AE28: =IFERROR(F28/$E$3/1000/AD28,0) -> 0 | AF28: =Preencher!$B$3&$U$8&$V$8&A28&$AF$6 -> JARINU-FRG124369MQ.GIROFREEZER | AG28: =Preencher!$B$3&$U$8&$V$8&A28&$AG$6 -> JARINU-FRG124369MQ.GIROFREEZER (1) | AH28: =Preencher!$B$3&$U$8&$V$8&A28&$AH$6 -> JARINU-FRG124369MQ.GIROFREEZER (2) | AI28: =Preencher!$B$3&$U$8&$V$8&A28&$AI$6 -> JARINU-FRG124369MQ.GIROFREEZER REV04 | AJ28: =Preencher!$B$3&$U$8&$V$8&A28&$AJ$6 -> JARINU-FRG124369MQ.GIROFREEZER (3) | AK28: =IFERROR(SUMIF('BD Otimix'!A:A,'BD VOLUME'!AG28,'BD Otimix'!O:O)+SUMIF('BD Otimix'!A:A,'BD VOLUME'!AH28,'BD Otimix'!O:O)+SUMIF('BD Otimix'!A:A,'BD VOLUME'!AI28,'BD Otimix'!O:O)+SUMIF('BD Otimix'!A:A,'BD VOLUME'!AJ28,'BD Otimix'!O:O)+SUMIF('BD Otimix'!A:A,'BD VOLUME'!AF28,'BD Otimix'!O:O),0) -> 0 | AL28: =IFERROR(F28/$E$3/1000/AK28,0) -> 0
A29: 124006 | C29: CORACAO FGO (C) BDJ 12X1KG | D29: MIUDOS | E29: CORAÇÃO BDJ CG | F29: =SUMIF('COLAR PLANO'!$A:$A,A29,'COLAR PLANO'!$D:$D) -> 0 | G29: =IFERROR(F29/($E$3*$C$3),0) -> 0 | H29: 0.0047 | I29: =IFERROR(G29/$D$7/H29,0) -> 0 | J29: =IFERROR(I29/$B$7,0) -> 0 | K29: 1 | L29: 12 | M29: 12 | N29: =IFERROR(G29/K29,"-") -> 0 | P29: =IFERROR(G29/M29,"-") -> 0 | U29: - | V29: FRG | W29: =Preencher!$B$3&U29&V29&A29&$W$6 -> JARINU-FRG124006MQ.TUNEL DE CG (CONTINUO) | X29: =Preencher!$B$3&U29&V29&A29&$X$6 -> JARINU-FRG124006MQ.TUNEL DE CG (CONTINUO) (1) | Y29: =Preencher!$B$3&U29&V29&A29&$Y$6 -> JARINU-FRG124006MQ.TUNEL DE CG (CONTINUO) (2) | Z29: =Preencher!$B$3&U29&V29&A29&$Z$6 -> JARINU-FRG124006MQ.TUNEL DE CG (CONTINUO) (3) | AA29: =Preencher!$B$3&U29&V29&A29&$AA$6 -> JARINU-FRG124006MQ.TUNEL DE CG (ESTATICO) | AB29: =Preencher!$B$3&U29&V29&A29&$AB$6 -> JARINU-FRG124006MQ.TUNEL DE CG (ESTATICO) (1) | AC29: =Preencher!$B$3&U29&V29&A29&$AC$6 -> JARINU-FRG124006MQ.TUNEL DE CG (ESTATICO) (2) | AD29: =IFERROR(SUMIF('BD Otimix'!A:A,'BD VOLUME'!X29,'BD Otimix'!O:O)+SUMIF('BD Otimix'!A:A,'BD VOLUME'!Y29,'BD Otimix'!O:O)+SUMIF('BD Otimix'!A:A,'BD VOLUME'!Z29,'BD Otimix'!O:O)+SUMIF('BD Otimix'!A:A,'BD VOLUME'!AA29,'BD Otimix'!O:O)+SUMIF('BD Otimix'!A:A,'BD VOLUME'!AB29,'BD Otimix'!O:O)+SUMIF('BD Otimix'!A:A,'BD VOLUME'!AC29,'BD Otimix'!O:O)+SUMIF('BD Otimix'!A:A,'BD VOLUME'!W29,'BD Otimix'!O:O),0) -> 0 | AE29: =IFERROR(F29/$E$3/1000/AD29,0) -> 0 | AF29: =Preencher!$B$3&$U$8&$V$8&A29&$AF$6 -> JARINU-FRG124006MQ.GIROFREEZER | AG29: =Preencher!$B$3&$U$8&$V$8&A29&$AG$6 -> JARINU-FRG124006MQ.GIROFREEZER (1) | AH29: =Preencher!$B$3&$U$8&$V$8&A29&$AH$6 -> JARINU-FRG124006MQ.GIROFREEZER (2) | AI29: =Preencher!$B$3&$U$8&$V$8&A29&$AI$6 -> JARINU-FRG124006MQ.GIROFREEZER REV04 | AJ29: =Preencher!$B$3&$U$8&$V$8&A29&$AJ$6 -> JARINU-FRG124006MQ.GIROFREEZER (3) | AK29: =IFERROR(SUMIF('BD Otimix'!A:A,'BD VOLUME'!AG29,'BD Otimix'!O:O)+SUMIF('BD Otimix'!A:A,'BD VOLUME'!AH29,'BD Otimix'!O:O)+SUMIF('BD Otimix'!A:A,'BD VOLUME'!AI29,'BD Otimix'!O:O)+SUMIF('BD Otimix'!A:A,'BD VOLUME'!AJ29,'BD Otimix'!O:O)+SUMIF('BD Otimix'!A:A,'BD VOLUME'!AF29,'BD Otimix'!O:O),0) -> 0 | AL29: =IFERROR(F29/$E$3/1000/AK29,0) -> 0
D30: MIUDOS | E30: Fígado Pacote 0,45 Kg | F30: =SUMIF('COLAR PLANO'!$A:$A,A30,'COLAR PLANO'!$D:$D) -> 0 | G30: =IFERROR(F30/($E$3*$C$3),0) -> 0 | H30: 0.0175 | I30: =IFERROR(G30/$D$7/H30,0) -> 0 | J30: =IFERROR(I30/$B$7,0) -> 0 | K30: 0.5 | L30: 24 | M30: 12 | N30: =IFERROR(G30/K30,"-") -> 0 | P30: =IFERROR(G30/M30,"-") -> 0 | U30: - | V30: FRG | W30: =Preencher!$B$3&U30&V30&A30&$W$6 -> JARINU-FRGMQ.TUNEL DE CG (CONTINUO) | X30: =Preencher!$B$3&U30&V30&A30&$X$6 -> JARINU-FRGMQ.TUNEL DE CG (CONTINUO) (1) | Y30: =Preencher!$B$3&U30&V30&A30&$Y$6 -> JARINU-FRGMQ.TUNEL DE CG (CONTINUO) (2) | Z30: =Preencher!$B$3&U30&V30&A30&$Z$6 -> JARINU-FRGMQ.TUNEL DE CG (CONTINUO) (3) | AA30: =Preencher!$B$3&U30&V30&A30&$AA$6 -> JARINU-FRGMQ.TUNEL DE CG (ESTATICO) | AB30: =Preencher!$B$3&U30&V30&A30&$AB$6 -> JARINU-FRGMQ.TUNEL DE CG (ESTATICO) (1) | AC30: =Preencher!$B$3&U30&V30&A30&$AC$6 -> JARINU-FRGMQ.TUNEL DE CG (ESTATICO) (2) | AD30: =IFERROR(SUMIF('BD Otimix'!A:A,'BD VOLUME'!X30,'BD Otimix'!O:O)+SUMIF('BD Otimix'!A:A,'BD VOLUME'!Y30,'BD Otimix'!O:O)+SUMIF('BD Otimix'!A:A,'BD VOLUME'!Z30,'BD Otimix'!O:O)+SUMIF('BD Otimix'!A:A,'BD VOLUME'!AA30,'BD Otimix'!O:O)+SUMIF('BD Otimix'!A:A,'BD VOLUME'!AB30,'BD Otimix'!O:O)+SUMIF('BD Otimix'!A:A,'BD VOLUME'!AC30,'BD Otimix'!O:O)+SUMIF('BD Otimix'!A:A,'BD VOLUME'!W30,'BD Otimix'!O:O),0) -> 0 | AE30: =IFERROR(F30/$E$3/1000/AD30,0) -> 0 | AF30: =Preencher!$B$3&$U$8&$V$8&A30&$AF$6 -> JARINU-FRGMQ.GIROFREEZER | AG30: =Preencher!$B$3&$U$8&$V$8&A30&$AG$6 -> JARINU-FRGMQ.GIROFREEZER (1) | AH30: =Preencher!$B$3&$U$8&$V$8&A30&$AH$6 -> JARINU-FRGMQ.GIROFREEZER (2) | AI30: =Preencher!$B$3&$U$8&$V$8&A30&$AI$6 -> JARINU-FRGMQ.GIROFREEZER REV04 | AJ30: =Preencher!$B$3&$U$8&$V$8&A30&$AJ$6 -> JARINU-FRGMQ.GIROFREEZER (3) | AK30: =IFERROR(SUMIF('BD Otimix'!A:A,'BD VOLUME'!AG30,'BD Otimix'!O:O)+SUMIF('BD Otimix'!A:A,'BD VOLUME'!AH30,'BD Otimix'!O:O)+SUMIF('BD Otimix'!A:A,'BD VOLUME'!AI30,'BD Otimix'!O:O)+SUMIF('BD Otimix'!A:A,'BD VOLUME'!AJ30,'BD Otimix'!O:O)+SUMIF('BD Otimix'!A:A,'BD VOLUME'!AF30,'BD Otimix'!O:O),0) -> 0 | AL30: =IFERROR(F30/$E$3/1000/AK30,0) -> 0
A31: 729876 | B31: FIG-01 | C31: FIGADO FGO RESF BDJ SEARA | D31: MIUDOS | E31: Fígado BDJ RF | F31: =SUMIF('COLAR PLANO'!$A:$A,A31,'COLAR PLANO'!$D:$D) -> 0 | G31: =IFERROR(F31/($E$3*$C$3),0) -> 0 | H31: 0.0175 | I31: =IFERROR(G31/$D$7/H31,0) -> 0 | J31: =IFERROR(I31/$B$7,0) -> 0 | K31: 1 | L31: 12 | M31: 12 | N31: =IFERROR(G31/K31,"-") -> 0 | P31: =IFERROR(G31/M31,"-") -> 0 | U31: - | V31: FRG | W31: =Preencher!$B$3&U31&V31&A31&$W$6 -> JARINU-FRG729876MQ.TUNEL DE CG (CONTINUO) | X31: =Preencher!$B$3&U31&V31&A31&$X$6 -> JARINU-FRG729876MQ.TUNEL DE CG (CONTINUO) (1) | Y31: =Preencher!$B$3&U31&V31&A31&$Y$6 -> JARINU-FRG729876MQ.TUNEL DE CG (CONTINUO) (2) | Z31: =Preencher!$B$3&U31&V31&A31&$Z$6 -> JARINU-FRG729876MQ.TUNEL DE CG (CONTINUO) (3) | AA31: =Preencher!$B$3&U31&V31&A31&$AA$6 -> JARINU-FRG729876MQ.TUNEL DE CG (ESTATICO) | AB31: =Preencher!$B$3&U31&V31&A31&$AB$6 -> JARINU-FRG729876MQ.TUNEL DE CG (ESTATICO) (1) | AC31: =Preencher!$B$3&U31&V31&A31&$AC$6 -> JARINU-FRG729876MQ.TUNEL DE CG (ESTATICO) (2) | AD31: =IFERROR(SUMIF('BD Otimix'!A:A,'BD VOLUME'!X31,'BD Otimix'!O:O)+SUMIF('BD Otimix'!A:A,'BD VOLUME'!Y31,'BD Otimix'!O:O)+SUMIF('BD Otimix'!A:A,'BD VOLUME'!Z31,'BD Otimix'!O:O)+SUMIF('BD Otimix'!A:A,'BD VOLUME'!AA31,'BD Otimix'!O:O)+SUMIF('BD Otimix'!A:A,'BD VOLUME'!AB31,'BD Otimix'!O:O)+SUMIF('BD Otimix'!A:A,'BD VOLUME'!AC31,'BD Otimix'!O:O)+SUMIF('BD Otimix'!A:A,'BD VOLUME'!W31,'BD Otimix'!O:O),0) -> 0 | AE31: =IFERROR(F31/$E$3/1000/AD31,0) -> 0 | AF31: =Preencher!$B$3&$U$8&$V$8&A31&$AF$6 -> JARINU-FRG729876MQ.GIROFREEZER | AG31: =Preencher!$B$3&$U$8&$V$8&A31&$AG$6 -> JARINU-FRG729876MQ.GIROFREEZER (1) | AH31: =Preencher!$B$3&$U$8&$V$8&A31&$AH$6 -> JARINU-FRG729876MQ.GIROFREEZER (2) | AI31: =Preencher!$B$3&$U$8&$V$8&A31&$AI$6 -> JARINU-FRG729876MQ.GIROFREEZER REV04 | AJ31: =Preencher!$B$3&$U$8&$V$8&A31&$AJ$6 -> JARINU-FRG729876MQ.GIROFREEZER (3) | AK31: =IFERROR(SUMIF('BD Otimix'!A:A,'BD VOLUME'!AG31,'BD Otimix'!O:O)+SUMIF('BD Otimix'!A:A,'BD VOLUME'!AH31,'BD Otimix'!O:O)+SUMIF('BD Otimix'!A:A,'BD VOLUME'!AI31,'BD Otimix'!O:O)+SUMIF('BD Otimix'!A:A,'BD VOLUME'!AJ31,'BD Otimix'!O:O)+SUMIF('BD Otimix'!A:A,'BD VOLUME'!AF31,'BD Otimix'!O:O),0) -> 0 | AL31: =IFERROR(F31/$E$3/1000/AK31,0) -> 0
A32: 209669 | B32: 209669 | C32: FIGADO FG CG PCT | D32: MIUDOS | E32: FÍGADO PACOTE 1 KG | F32: =SUMIF('COLAR PLANO'!$A:$A,A32,'COLAR PLANO'!$D:$D) -> 42336 | G32: =IFERROR(F32/($E$3*$C$3),0) -> 200.97793 | H32: 0.0175 | I32: =IFERROR(G32/$D$7/H32,0) -> 3828.151 | J32: =IFERROR(I32/$B$7,0) -> 0.81454545 | K32: 1 | L32: 16 | M32: 16 | N32: =IFERROR(G32/K32,"-") -> 200.97793 | P32: =IFERROR(G32/M32,"-") -> 12.56112 | U32: - | V32: FRG | W32: =Preencher!$B$3&U32&V32&A32&$W$6 -> JARINU-FRG209669MQ.TUNEL DE CG (CONTINUO) | X32: =Preencher!$B$3&U32&V32&A32&$X$6 -> JARINU-FRG209669MQ.TUNEL DE CG (CONTINUO) (1) | Y32: =Preencher!$B$3&U32&V32&A32&$Y$6 -> JARINU-FRG209669MQ.TUNEL DE CG (CONTINUO) (2) | Z32: =Preencher!$B$3&U32&V32&A32&$Z$6 -> JARINU-FRG209669MQ.TUNEL DE CG (CONTINUO) (3) | AA32: =Preencher!$B$3&U32&V32&A32&$AA$6 -> JARINU-FRG209669MQ.TUNEL DE CG (ESTATICO) | AB32: =Preencher!$B$3&U32&V32&A32&$AB$6 -> JARINU-FRG209669MQ.TUNEL DE CG (ESTATICO) (1) | AC32: =Preencher!$B$3&U32&V32&A32&$AC$6 -> JARINU-FRG209669MQ.TUNEL DE CG (ESTATICO) (2) | AD32: =IFERROR(SUMIF('BD Otimix'!A:A,'BD VOLUME'!X32,'BD Otimix'!O:O)+SUMIF('BD Otimix'!A:A,'BD VOLUME'!Y32,'BD Otimix'!O:O)+SUMIF('BD Otimix'!A:A,'BD VOLUME'!Z32,'BD Otimix'!O:O)+SUMIF('BD Otimix'!A:A,'BD VOLUME'!AA32,'BD Otimix'!O:O)+SUMIF('BD Otimix'!A:A,'BD VOLUME'!AB32,'BD Otimix'!O:O)+SUMIF('BD Otimix'!A:A,'BD VOLUME'!AC32,'BD Otimix'!O:O)+SUMIF('BD Otimix'!A:A,'BD VOLUME'!W32,'BD Otimix'!O:O),0) -> 0 | AE32: =IFERROR(F32/$E$3/1000/AD32,0) -> 0 | AF32: =Preencher!$B$3&$U$8&$V$8&A32&$AF$6 -> JARINU-FRG209669MQ.GIROFREEZER | AG32: =Preencher!$B$3&$U$8&$V$8&A32&$AG$6 -> JARINU-FRG209669MQ.GIROFREEZER (1) | AH32: =Preencher!$B$3&$U$8&$V$8&A32&$AH$6 -> JARINU-FRG209669MQ.GIROFREEZER (2) | AI32: =Preencher!$B$3&$U$8&$V$8&A32&$AI$6 -> JARINU-FRG209669MQ.GIROFREEZER REV04 | AJ32: =Preencher!$B$3&$U$8&$V$8&A32&$AJ$6 -> JARINU-FRG209669MQ.GIROFREEZER (3) | AK32: =IFERROR(SUMIF('BD Otimix'!A:A,'BD VOLUME'!AG32,'BD Otimix'!O:O)+SUMIF('BD Otimix'!A:A,'BD VOLUME'!AH32,'BD Otimix'!O:O)+SUMIF('BD Otimix'!A:A,'BD VOLUME'!AI32,'BD Otimix'!O:O)+SUMIF('BD Otimix'!A:A,'BD VOLUME'!AJ32,'BD Otimix'!O:O)+SUMIF('BD Otimix'!A:A,'BD VOLUME'!AF32,'BD Otimix'!O:O),0) -> 0 | AL32: =IFERROR(F32/$E$3/1000/AK32,0) -> 0
A33: 124695 | B33: LI-83 | C33: FIGADO FG PB | D33: MIUDOS | E33: Fígado Pacote 0,45 Kg | F33: =SUMIF('COLAR PLANO'!$A:$A,A33,'COLAR PLANO'!$D:$D) -> 0 | G33: =IFERROR(F33/($E$3*$C$3),0) -> 0 | H33: 0.0175 | I33: =IFERROR(G33/$D$7/H33,0) -> 0 | J33: =IFERROR(I33/$B$7,0) -> 0 | K33: 0.5 | L33: 24 | M33: 12 | N33: =IFERROR(G33/K33,"-") -> 0 | P33: =IFERROR(G33/M33,"-") -> 0 | U33: - | V33: FRG | W33: =Preencher!$B$3&U33&V33&A33&$W$6 -> JARINU-FRG124695MQ.TUNEL DE CG (CONTINUO) | X33: =Preencher!$B$3&U33&V33&A33&$X$6 -> JARINU-FRG124695MQ.TUNEL DE CG (CONTINUO) (1) | Y33: =Preencher!$B$3&U33&V33&A33&$Y$6 -> JARINU-FRG124695MQ.TUNEL DE CG (CONTINUO) (2) | Z33: =Preencher!$B$3&U33&V33&A33&$Z$6 -> JARINU-FRG124695MQ.TUNEL DE CG (CONTINUO) (3) | AA33: =Preencher!$B$3&U33&V33&A33&$AA$6 -> JARINU-FRG124695MQ.TUNEL DE CG (ESTATICO) | AB33: =Preencher!$B$3&U33&V33&A33&$AB$6 -> JARINU-FRG124695MQ.TUNEL DE CG (ESTATICO) (1) | AC33: =Preencher!$B$3&U33&V33&A33&$AC$6 -> JARINU-FRG124695MQ.TUNEL DE CG (ESTATICO) (2) | AD33: =IFERROR(SUMIF('BD Otimix'!A:A,'BD VOLUME'!X33,'BD Otimix'!O:O)+SUMIF('BD Otimix'!A:A,'BD VOLUME'!Y33,'BD Otimix'!O:O)+SUMIF('BD Otimix'!A:A,'BD VOLUME'!Z33,'BD Otimix'!O:O)+SUMIF('BD Otimix'!A:A,'BD VOLUME'!AA33,'BD Otimix'!O:O)+SUMIF('BD Otimix'!A:A,'BD VOLUME'!AB33,'BD Otimix'!O:O)+SUMIF('BD Otimix'!A:A,'BD VOLUME'!AC33,'BD Otimix'!O:O)+SUMIF('BD Otimix'!A:A,'BD VOLUME'!W33,'BD Otimix'!O:O),0) -> 0 | AE33: =IFERROR(F33/$E$3/1000/AD33,0) -> 0 | AF33: =Preencher!$B$3&$U$8&$V$8&A33&$AF$6 -> JARINU-FRG124695MQ.GIROFREEZER | AG33: =Preencher!$B$3&$U$8&$V$8&A33&$AG$6 -> JARINU-FRG124695MQ.GIROFREEZER (1) | AH33: =Preencher!$B$3&$U$8&$V$8&A33&$AH$6 -> JARINU-FRG124695MQ.GIROFREEZER (2) | AI33: =Preencher!$B$3&$U$8&$V$8&A33&$AI$6 -> JARINU-FRG124695MQ.GIROFREEZER REV04 | AJ33: =Preencher!$B$3&$U$8&$V$8&A33&$AJ$6 -> JARINU-FRG124695MQ.GIROFREEZER (3) | AK33: =IFERROR(SUMIF('BD Otimix'!A:A,'BD VOLUME'!AG33,'BD Otimix'!O:O)+SUMIF('BD Otimix'!A:A,'BD VOLUME'!AH33,'BD Otimix'!O:O)+SUMIF('BD Otimix'!A:A,'BD VOLUME'!AI33,'BD Otimix'!O:O)+SUMIF('BD Otimix'!A:A,'BD VOLUME'!AJ33,'BD Otimix'!O:O)+SUMIF('BD Otimix'!A:A,'BD VOLUME'!AF33,'BD Otimix'!O:O),0) -> 0 | AL33: =IFERROR(F33/$E$3/1000/AK33,0) -> 0
A34: 236789 | C34: FIGADO FG BDJ GF | D34: MIUDOS | E34: FÍGADO BDJ CG | F34: =SUMIF('COLAR PLANO'!$A:$A,A34,'COLAR PLANO'!$D:$D) -> 0 | G34: =IFERROR(F34/($E$3*$C$3),0) -> 0 | H34: 0.0175 | I34: =IFERROR(G34/$D$7/H34,0) -> 0 | J34: =IFERROR(I34/$B$7,0) -> 0 | K34: 1 | L34: 12 | M34: 12 | N34: =IFERROR(G34/K34,"-") -> 0 | P34: =IFERROR(G34/M34,"-") -> 0 | U34: - | V34: FRG | W34: =Preencher!$B$3&U34&V34&A34&$W$6 -> JARINU-FRG236789MQ.TUNEL DE CG (CONTINUO) | X34: =Preencher!$B$3&U34&V34&A34&$X$6 -> JARINU-FRG236789MQ.TUNEL DE CG (CONTINUO) (1) | Y34: =Preencher!$B$3&U34&V34&A34&$Y$6 -> JARINU-FRG236789MQ.TUNEL DE CG (CONTINUO) (2) | Z34: =Preencher!$B$3&U34&V34&A34&$Z$6 -> JARINU-FRG236789MQ.TUNEL DE CG (CONTINUO) (3) | AA34: =Preencher!$B$3&U34&V34&A34&$AA$6 -> JARINU-FRG236789MQ.TUNEL DE CG (ESTATICO) | AB34: =Preencher!$B$3&U34&V34&A34&$AB$6 -> JARINU-FRG236789MQ.TUNEL DE CG (ESTATICO) (1) | AC34: =Preencher!$B$3&U34&V34&A34&$AC$6 -> JARINU-FRG236789MQ.TUNEL DE CG (ESTATICO) (2) | AD34: =IFERROR(SUMIF('BD Otimix'!A:A,'BD VOLUME'!X34,'BD Otimix'!O:O)+SUMIF('BD Otimix'!A:A,'BD VOLUME'!Y34,'BD Otimix'!O:O)+SUMIF('BD Otimix'!A:A,'BD VOLUME'!Z34,'BD Otimix'!O:O)+SUMIF('BD Otimix'!A:A,'BD VOLUME'!AA34,'BD Otimix'!O:O)+SUMIF('BD Otimix'!A:A,'BD VOLUME'!AB34,'BD Otimix'!O:O)+SUMIF('BD Otimix'!A:A,'BD VOLUME'!AC34,'BD Otimix'!O:O)+SUMIF('BD Otimix'!A:A,'BD VOLUME'!W34,'BD Otimix'!O:O),0) -> 0 | AE34: =IFERROR(F34/$E$3/1000/AD34,0) -> 0 | AF34: =Preencher!$B$3&$U$8&$V$8&A34&$AF$6 -> JARINU-FRG236789MQ.GIROFREEZER | AG34: =Preencher!$B$3&$U$8&$V$8&A34&$AG$6 -> JARINU-FRG236789MQ.GIROFREEZER (1) | AH34: =Preencher!$B$3&$U$8&$V$8&A34&$AH$6 -> JARINU-FRG236789MQ.GIROFREEZER (2) | AI34: =Preencher!$B$3&$U$8&$V$8&A34&$AI$6 -> JARINU-FRG236789MQ.GIROFREEZER REV04 | AJ34: =Preencher!$B$3&$U$8&$V$8&A34&$AJ$6 -> JARINU-FRG236789MQ.GIROFREEZER (3) | AK34: =IFERROR(SUMIF('BD Otimix'!A:A,'BD VOLUME'!AG34,'BD Otimix'!O:O)+SUMIF('BD Otimix'!A:A,'BD VOLUME'!AH34,'BD Otimix'!O:O)+SUMIF('BD Otimix'!A:A,'BD VOLUME'!AI34,'BD Otimix'!O:O)+SUMIF('BD Otimix'!A:A,'BD VOLUME'!AJ34,'BD Otimix'!O:O)+SUMIF('BD Otimix'!A:A,'BD VOLUME'!AF34,'BD Otimix'!O:O),0) -> 0 | AL34: =IFERROR(F34/$E$3/1000/AK34,0) -> 0
A35: 227929 | C35: FIGADO FG BDJ NGF | D35: MIUDOS | E35: FÍGADO BDJ CG | F35: =SUMIF('COLAR PLANO'!$A:$A,A35,'COLAR PLANO'!$D:$D) -> 0 | G35: =IFERROR(F35/($E$3*$C$3),0) -> 0 | H35: 0.0175 | I35: =IFERROR(G35/$D$7/H35,0) -> 0 | J35: =IFERROR(I35/$B$7,0) -> 0 | K35: 1 | L35: 12 | M35: 12 | N35: =IFERROR(G35/K35,"-") -> 0 | P35: =IFERROR(G35/M35,"-") -> 0 | U35: - | V35: FRG | W35: =Preencher!$B$3&U35&V35&A35&$W$6 -> JARINU-FRG227929MQ.TUNEL DE CG (CONTINUO) | X35: =Preencher!$B$3&U35&V35&A35&$X$6 -> JARINU-FRG227929MQ.TUNEL DE CG (CONTINUO) (1) | Y35: =Preencher!$B$3&U35&V35&A35&$Y$6 -> JARINU-FRG227929MQ.TUNEL DE CG (CONTINUO) (2) | Z35: =Preencher!$B$3&U35&V35&A35&$Z$6 -> JARINU-FRG227929MQ.TUNEL DE CG (CONTINUO) (3) | AA35: =Preencher!$B$3&U35&V35&A35&$AA$6 -> JARINU-FRG227929MQ.TUNEL DE CG (ESTATICO) | AB35: =Preencher!$B$3&U35&V35&A35&$AB$6 -> JARINU-FRG227929MQ.TUNEL DE CG (ESTATICO) (1) | AC35: =Preencher!$B$3&U35&V35&A35&$AC$6 -> JARINU-FRG227929MQ.TUNEL DE CG (ESTATICO) (2) | AD35: =IFERROR(SUMIF('BD Otimix'!A:A,'BD VOLUME'!X35,'BD Otimix'!O:O)+SUMIF('BD Otimix'!A:A,'BD VOLUME'!Y35,'BD Otimix'!O:O)+SUMIF('BD Otimix'!A:A,'BD VOLUME'!Z35,'BD Otimix'!O:O)+SUMIF('BD Otimix'!A:A,'BD VOLUME'!AA35,'BD Otimix'!O:O)+SUMIF('BD Otimix'!A:A,'BD VOLUME'!AB35,'BD Otimix'!O:O)+SUMIF('BD Otimix'!A:A,'BD VOLUME'!AC35,'BD Otimix'!O:O)+SUMIF('BD Otimix'!A:A,'BD VOLUME'!W35,'BD Otimix'!O:O),0) -> 0 | AE35: =IFERROR(F35/$E$3/1000/AD35,0) -> 0 | AF35: =Preencher!$B$3&$U$8&$V$8&A35&$AF$6 -> JARINU-FRG227929MQ.GIROFREEZER | AG35: =Preencher!$B$3&$U$8&$V$8&A35&$AG$6 -> JARINU-FRG227929MQ.GIROFREEZER (1) | AH35: =Preencher!$B$3&$U$8&$V$8&A35&$AH$6 -> JARINU-FRG227929MQ.GIROFREEZER (2) | AI35: =Preencher!$B$3&$U$8&$V$8&A35&$AI$6 -> JARINU-FRG227929MQ.GIROFREEZER REV04 | AJ35: =Preencher!$B$3&$U$8&$V$8&A35&$AJ$6 -> JARINU-FRG227929MQ.GIROFREEZER (3) | AK35: =IFERROR(SUMIF('BD Otimix'!A:A,'BD VOLUME'!AG35,'BD Otimix'!O:O)+SUMIF('BD Otimix'!A:A,'BD VOLUME'!AH35,'BD Otimix'!O:O)+SUMIF('BD Otimix'!A:A,'BD VOLUME'!AI35,'BD Otimix'!O:O)+SUMIF('BD Otimix'!A:A,'BD VOLUME'!AJ35,'BD Otimix'!O:O)+SUMIF('BD Otimix'!A:A,'BD VOLUME'!AF35,'BD Otimix'!O:O),0) -> 0 | AL35: =IFERROR(F35/$E$3/1000/AK35,0) -> 0
A36: 241669 | C36: FIGADO FG BDJ NGF | D36: MIUDOS | E36: FÍGADO BDJ CG | F36: =SUMIF('COLAR PLANO'!$A:$A,A36,'COLAR PLANO'!$D:$D) -> 0 | G36: =IFERROR(F36/($E$3*$C$3),0) -> 0 | H36: 0.0175 | I36: =IFERROR(G36/$D$7/H36,0) -> 0 | J36: =IFERROR(I36/$B$7,0) -> 0 | K36: 1 | L36: 12 | M36: 12 | N36: =IFERROR(G36/K36,"-") -> 0 | P36: =IFERROR(G36/M36,"-") -> 0 | U36: - | V36: FRG | W36: =Preencher!$B$3&U36&V36&A36&$W$6 -> JARINU-FRG241669MQ.TUNEL DE CG (CONTINUO) | X36: =Preencher!$B$3&U36&V36&A36&$X$6 -> JARINU-FRG241669MQ.TUNEL DE CG (CONTINUO) (1) | Y36: =Preencher!$B$3&U36&V36&A36&$Y$6 -> JARINU-FRG241669MQ.TUNEL DE CG (CONTINUO) (2) | Z36: =Preencher!$B$3&U36&V36&A36&$Z$6 -> JARINU-FRG241669MQ.TUNEL DE CG (CONTINUO) (3) | AA36: =Preencher!$B$3&U36&V36&A36&$AA$6 -> JARINU-FRG241669MQ.TUNEL DE CG (ESTATICO) | AB36: =Preencher!$B$3&U36&V36&A36&$AB$6 -> JARINU-FRG241669MQ.TUNEL DE CG (ESTATICO) (1) | AC36: =Preencher!$B$3&U36&V36&A36&$AC$6 -> JARINU-FRG241669MQ.TUNEL DE CG (ESTATICO) (2) | AD36: =IFERROR(SUMIF('BD Otimix'!A:A,'BD VOLUME'!X36,'BD Otimix'!O:O)+SUMIF('BD Otimix'!A:A,'BD VOLUME'!Y36,'BD Otimix'!O:O)+SUMIF('BD Otimix'!A:A,'BD VOLUME'!Z36,'BD Otimix'!O:O)+SUMIF('BD Otimix'!A:A,'BD VOLUME'!AA36,'BD Otimix'!O:O)+SUMIF('BD Otimix'!A:A,'BD VOLUME'!AB36,'BD Otimix'!O:O)+SUMIF('BD Otimix'!A:A,'BD VOLUME'!AC36,'BD Otimix'!O:O)+SUMIF('BD Otimix'!A:A,'BD VOLUME'!W36,'BD Otimix'!O:O),0) -> 0 | AE36: =IFERROR(F36/$E$3/1000/AD36,0) -> 0 | AF36: =Preencher!$B$3&$U$8&$V$8&A36&$AF$6 -> JARINU-FRG241669MQ.GIROFREEZER | AG36: =Preencher!$B$3&$U$8&$V$8&A36&$AG$6 -> JARINU-FRG241669MQ.GIROFREEZER (1) | AH36: =Preencher!$B$3&$U$8&$V$8&A36&$AH$6 -> JARINU-FRG241669MQ.GIROFREEZER (2) | AI36: =Preencher!$B$3&$U$8&$V$8&A36&$AI$6 -> JARINU-FRG241669MQ.GIROFREEZER REV04 | AJ36: =Preencher!$B$3&$U$8&$V$8&A36&$AJ$6 -> JARINU-FRG241669MQ.GIROFREEZER (3) | AK36: =IFERROR(SUMIF('BD Otimix'!A:A,'BD VOLUME'!AG36,'BD Otimix'!O:O)+SUMIF('BD Otimix'!A:A,'BD VOLUME'!AH36,'BD Otimix'!O:O)+SUMIF('BD Otimix'!A:A,'BD VOLUME'!AI36,'BD Otimix'!O:O)+SUMIF('BD Otimix'!A:A,'BD VOLUME'!AJ36,'BD Otimix'!O:O)+SUMIF('BD Otimix'!A:A,'BD VOLUME'!AF36,'BD Otimix'!O:O),0) -> 0 | AL36: =IFERROR(F36/$E$3/1000/AK36,0) -> 0
A37: 999543 | C37: MIUDOS CONGELADOS DE FRANGO | D37: MIUDOS | E37: FÍGADO BDJ CG | F37: =SUMIF('COLAR PLANO'!$A:$A,A37,'COLAR PLANO'!$D:$D) -> 0 | G37: =IFERROR(F37/($E$3*$C$3),0) -> 0 | H37: 0.0175 | I37: =IFERROR(G37/$D$7/H37,0) -> 0 | J37: =IFERROR(I37/$B$7,0) -> 0 | K37: 0.45 | L37: 12 | M37: 9 | N37: =IFERROR(G37/K37,"-") -> 0 | P37: =IFERROR(G37/M37,"-") -> 0 | U37: - | V37: FRG | W37: =Preencher!$B$3&U37&V37&A37&$W$6 -> JARINU-FRG999543MQ.TUNEL DE CG (CONTINUO) | X37: =Preencher!$B$3&U37&V37&A37&$X$6 -> JARINU-FRG999543MQ.TUNEL DE CG (CONTINUO) (1) | Y37: =Preencher!$B$3&U37&V37&A37&$Y$6 -> JARINU-FRG999543MQ.TUNEL DE CG (CONTINUO) (2) | Z37: =Preencher!$B$3&U37&V37&A37&$Z$6 -> JARINU-FRG999543MQ.TUNEL DE CG (CONTINUO) (3) | AA37: =Preencher!$B$3&U37&V37&A37&$AA$6 -> JARINU-FRG999543MQ.TUNEL DE CG (ESTATICO) | AB37: =Preencher!$B$3&U37&V37&A37&$AB$6 -> JARINU-FRG999543MQ.TUNEL DE CG (ESTATICO) (1) | AC37: =Preencher!$B$3&U37&V37&A37&$AC$6 -> JARINU-FRG999543MQ.TUNEL DE CG (ESTATICO) (2) | AD37: =IFERROR(SUMIF('BD Otimix'!A:A,'BD VOLUME'!X37,'BD Otimix'!O:O)+SUMIF('BD Otimix'!A:A,'BD VOLUME'!Y37,'BD Otimix'!O:O)+SUMIF('BD Otimix'!A:A,'BD VOLUME'!Z37,'BD Otimix'!O:O)+SUMIF('BD Otimix'!A:A,'BD VOLUME'!AA37,'BD Otimix'!O:O)+SUMIF('BD Otimix'!A:A,'BD VOLUME'!AB37,'BD Otimix'!O:O)+SUMIF('BD Otimix'!A:A,'BD VOLUME'!AC37,'BD Otimix'!O:O)+SUMIF('BD Otimix'!A:A,'BD VOLUME'!W37,'BD Otimix'!O:O),0) -> 0 | AE37: =IFERROR(F37/$E$3/1000/AD37,0) -> 0 | AF37: =Preencher!$B$3&$U$8&$V$8&A37&$AF$6 -> JARINU-FRG999543MQ.GIROFREEZER | AG37: =Preencher!$B$3&$U$8&$V$8&A37&$AG$6 -> JARINU-FRG999543MQ.GIROFREEZER (1) | AH37: =Preencher!$B$3&$U$8&$V$8&A37&$AH$6 -> JARINU-FRG999543MQ.GIROFREEZER (2) | AI37: =Preencher!$B$3&$U$8&$V$8&A37&$AI$6 -> JARINU-FRG999543MQ.GIROFREEZER REV04 | AJ37: =Preencher!$B$3&$U$8&$V$8&A37&$AJ$6 -> JARINU-FRG999543MQ.GIROFREEZER (3) | AK37: =IFERROR(SUMIF('BD Otimix'!A:A,'BD VOLUME'!AG37,'BD Otimix'!O:O)+SUMIF('BD Otimix'!A:A,'BD VOLUME'!AH37,'BD Otimix'!O:O)+SUMIF('BD Otimix'!A:A,'BD VOLUME'!AI37,'BD Otimix'!O:O)+SUMIF('BD Otimix'!A:A,'BD VOLUME'!AJ37,'BD Otimix'!O:O)+SUMIF('BD Otimix'!A:A,'BD VOLUME'!AF37,'BD Otimix'!O:O),0) -> 0 | AL37: =IFERROR(F37/$E$3/1000/AK37,0) -> 0
A38: 13005 | B38: FIG-PF | C38: FIGADO FGO CG BL SE PET-FOOD | D38: MIUDOS | E38: FÍGADO BLOCO | F38: =SUMIF('COLAR PLANO'!$A:$A,A38,'COLAR PLANO'!$D:$D) -> 0 | G38: =IFERROR(F38/($E$3*$C$3),0) -> 0 | H38: 0.0175 | I38: =IFERROR(G38/$D$7/H38,0) -> 0 | J38: =IFERROR(I38/$B$7,0) -> 0 | K38: 15 | L38: 1 | M38: 15 | N38: =IFERROR(G38/K38,"-") -> 0 | Q38: =IFERROR(G38/M38,"-") -> 0 | U38: - | V38: FRG | W38: =Preencher!$B$3&U38&V38&A38&$W$6 -> JARINU-FRG13005MQ.TUNEL DE CG (CONTINUO) | X38: =Preencher!$B$3&U38&V38&A38&$X$6 -> JARINU-FRG13005MQ.TUNEL DE CG (CONTINUO) (1) | Y38: =Preencher!$B$3&U38&V38&A38&$Y$6 -> JARINU-FRG13005MQ.TUNEL DE CG (CONTINUO) (2) | Z38: =Preencher!$B$3&U38&V38&A38&$Z$6 -> JARINU-FRG13005MQ.TUNEL DE CG (CONTINUO) (3) | AA38: =Preencher!$B$3&U38&V38&A38&$AA$6 -> JARINU-FRG13005MQ.TUNEL DE CG (ESTATICO) | AB38: =Preencher!$B$3&U38&V38&A38&$AB$6 -> JARINU-FRG13005MQ.TUNEL DE CG (ESTATICO) (1) | AC38: =Preencher!$B$3&U38&V38&A38&$AC$6 -> JARINU-FRG13005MQ.TUNEL DE CG (ESTATICO) (2) | AD38: =IFERROR(SUMIF('BD Otimix'!A:A,'BD VOLUME'!X38,'BD Otimix'!O:O)+SUMIF('BD Otimix'!A:A,'BD VOLUME'!Y38,'BD Otimix'!O:O)+SUMIF('BD Otimix'!A:A,'BD VOLUME'!Z38,'BD Otimix'!O:O)+SUMIF('BD Otimix'!A:A,'BD VOLUME'!AA38,'BD Otimix'!O:O)+SUMIF('BD Otimix'!A:A,'BD VOLUME'!AB38,'BD Otimix'!O:O)+SUMIF('BD Otimix'!A:A,'BD VOLUME'!AC38,'BD Otimix'!O:O)+SUMIF('BD Otimix'!A:A,'BD VOLUME'!W38,'BD Otimix'!O:O),0) -> 0 | AE38: =IFERROR(F38/$E$3/1000/AD38,0) -> 0 | AF38: =Preencher!$B$3&$U$8&$V$8&A38&$AF$6 -> JARINU-FRG13005MQ.GIROFREEZER | AG38: =Preencher!$B$3&$U$8&$V$8&A38&$AG$6 -> JARINU-FRG13005MQ.GIROFREEZER (1) | AH38: =Preencher!$B$3&$U$8&$V$8&A38&$AH$6 -> JARINU-FRG13005MQ.GIROFREEZER (2) | AI38: =Preencher!$B$3&$U$8&$V$8&A38&$AI$6 -> JARINU-FRG13005MQ.GIROFREEZER REV04 | AJ38: =Preencher!$B$3&$U$8&$V$8&A38&$AJ$6 -> JARINU-FRG13005MQ.GIROFREEZER (3) | AK38: =IFERROR(SUMIF('BD Otimix'!A:A,'BD VOLUME'!AG38,'BD Otimix'!O:O)+SUMIF('BD Otimix'!A:A,'BD VOLUME'!AH38,'BD Otimix'!O:O)+SUMIF('BD Otimix'!A:A,'BD VOLUME'!AI38,'BD Otimix'!O:O)+SUMIF('BD Otimix'!A:A,'BD VOLUME'!AJ38,'BD Otimix'!O:O)+SUMIF('BD Otimix'!A:A,'BD VOLUME'!AF38,'BD Otimix'!O:O),0) -> 0 | AL38: =IFERROR(F38/$E$3/1000/AK38,0) -> 0
A39: 726494 | B39: LI-68 | C39: FIGADO FG PF PB | D39: MIUDOS | E39: FÍGADO BLOCO | F39: =SUMIF('COLAR PLANO'!$A:$A,A39,'COLAR PLANO'!$D:$D) -> 0 | G39: =IFERROR(F39/($E$3*$C$3),0) -> 0 | H39: 0.0175 | I39: =IFERROR(G39/$D$7/H39,0) -> 0 | J39: =IFERROR(I39/$B$7,0) -> 0 | K39: 15 | L39: 1 | M39: 15 | N39: =IFERROR(G39/K39,"-") -> 0 | Q39: =IFERROR(G39/M39,"-") -> 0 | U39: - | V39: FRG | W39: =Preencher!$B$3&U39&V39&A39&$W$6 -> JARINU-FRG726494MQ.TUNEL DE CG (CONTINUO) | X39: =Preencher!$B$3&U39&V39&A39&$X$6 -> JARINU-FRG726494MQ.TUNEL DE CG (CONTINUO) (1) | Y39: =Preencher!$B$3&U39&V39&A39&$Y$6 -> JARINU-FRG726494MQ.TUNEL DE CG (CONTINUO) (2) | Z39: =Preencher!$B$3&U39&V39&A39&$Z$6 -> JARINU-FRG726494MQ.TUNEL DE CG (CONTINUO) (3) | AA39: =Preencher!$B$3&U39&V39&A39&$AA$6 -> JARINU-FRG726494MQ.TUNEL DE CG (ESTATICO) | AB39: =Preencher!$B$3&U39&V39&A39&$AB$6 -> JARINU-FRG726494MQ.TUNEL DE CG (ESTATICO) (1) | AC39: =Preencher!$B$3&U39&V39&A39&$AC$6 -> JARINU-FRG726494MQ.TUNEL DE CG (ESTATICO) (2) | AD39: =IFERROR(SUMIF('BD Otimix'!A:A,'BD VOLUME'!X39,'BD Otimix'!O:O)+SUMIF('BD Otimix'!A:A,'BD VOLUME'!Y39,'BD Otimix'!O:O)+SUMIF('BD Otimix'!A:A,'BD VOLUME'!Z39,'BD Otimix'!O:O)+SUMIF('BD Otimix'!A:A,'BD VOLUME'!AA39,'BD Otimix'!O:O)+SUMIF('BD Otimix'!A:A,'BD VOLUME'!AB39,'BD Otimix'!O:O)+SUMIF('BD Otimix'!A:A,'BD VOLUME'!AC39,'BD Otimix'!O:O)+SUMIF('BD Otimix'!A:A,'BD VOLUME'!W39,'BD Otimix'!O:O),0) -> 0 | AE39: =IFERROR(F39/$E$3/1000/AD39,0) -> 0 | AF39: =Preencher!$B$3&$U$8&$V$8&A39&$AF$6 -> JARINU-FRG726494MQ.GIROFREEZER | AG39: =Preencher!$B$3&$U$8&$V$8&A39&$AG$6 -> JARINU-FRG726494MQ.GIROFREEZER (1) | AH39: =Preencher!$B$3&$U$8&$V$8&A39&$AH$6 -> JARINU-FRG726494MQ.GIROFREEZER (2) | AI39: =Preencher!$B$3&$U$8&$V$8&A39&$AI$6 -> JARINU-FRG726494MQ.GIROFREEZER REV04 | AJ39: =Preencher!$B$3&$U$8&$V$8&A39&$AJ$6 -> JARINU-FRG726494MQ.GIROFREEZER (3) | AK39: =IFERROR(SUMIF('BD Otimix'!A:A,'BD VOLUME'!AG39,'BD Otimix'!O:O)+SUMIF('BD Otimix'!A:A,'BD VOLUME'!AH39,'BD Otimix'!O:O)+SUMIF('BD Otimix'!A:A,'BD VOLUME'!AI39,'BD Otimix'!O:O)+SUMIF('BD Otimix'!A:A,'BD VOLUME'!AJ39,'BD Otimix'!O:O)+SUMIF('BD Otimix'!A:A,'BD VOLUME'!AF39,'BD Otimix'!O:O),0) -> 0 | AL39: =IFERROR(F39/$E$3/1000/AK39,0) -> 0
D40: MIUDOS | E40: FÍGADO BDJ RF | F40: =SUMIF('COLAR PLANO'!$A:$A,A40,'COLAR PLANO'!$D:$D) -> 0 | G40: =IFERROR(F40/($E$3*$C$3),0) -> 0 | H40: 0.0175 | I40: =IFERROR(G40/$D$7/H40,0) -> 0 | J40: =IFERROR(I40/$B$7,0) -> 0 | K40: 1 | L40: 12 | M40: 12 | N40: =IFERROR(G40/K40,"-") -> 0 | P40: =IFERROR(G40/M40,"-") -> 0 | U40: - | V40: FRG | W40: =Preencher!$B$3&U40&V40&A40&$W$6 -> JARINU-FRGMQ.TUNEL DE CG (CONTINUO) | X40: =Preencher!$B$3&U40&V40&A40&$X$6 -> JARINU-FRGMQ.TUNEL DE CG (CONTINUO) (1) | Y40: =Preencher!$B$3&U40&V40&A40&$Y$6 -> JARINU-FRGMQ.TUNEL DE CG (CONTINUO) (2) | Z40: =Preencher!$B$3&U40&V40&A40&$Z$6 -> JARINU-FRGMQ.TUNEL DE CG (CONTINUO) (3) | AA40: =Preencher!$B$3&U40&V40&A40&$AA$6 -> JARINU-FRGMQ.TUNEL DE CG (ESTATICO) | AB40: =Preencher!$B$3&U40&V40&A40&$AB$6 -> JARINU-FRGMQ.TUNEL DE CG (ESTATICO) (1) | AC40: =Preencher!$B$3&U40&V40&A40&$AC$6 -> JARINU-FRGMQ.TUNEL DE CG (ESTATICO) (2) | AD40: =IFERROR(SUMIF('BD Otimix'!A:A,'BD VOLUME'!X40,'BD Otimix'!O:O)+SUMIF('BD Otimix'!A:A,'BD VOLUME'!Y40,'BD Otimix'!O:O)+SUMIF('BD Otimix'!A:A,'BD VOLUME'!Z40,'BD Otimix'!O:O)+SUMIF('BD Otimix'!A:A,'BD VOLUME'!AA40,'BD Otimix'!O:O)+SUMIF('BD Otimix'!A:A,'BD VOLUME'!AB40,'BD Otimix'!O:O)+SUMIF('BD Otimix'!A:A,'BD VOLUME'!AC40,'BD Otimix'!O:O)+SUMIF('BD Otimix'!A:A,'BD VOLUME'!W40,'BD Otimix'!O:O),0) -> 0 | AE40: =IFERROR(F40/$E$3/1000/AD40,0) -> 0 | AF40: =Preencher!$B$3&$U$8&$V$8&A40&$AF$6 -> JARINU-FRGMQ.GIROFREEZER | AG40: =Preencher!$B$3&$U$8&$V$8&A40&$AG$6 -> JARINU-FRGMQ.GIROFREEZER (1) | AH40: =Preencher!$B$3&$U$8&$V$8&A40&$AH$6 -> JARINU-FRGMQ.GIROFREEZER (2) | AI40: =Preencher!$B$3&$U$8&$V$8&A40&$AI$6 -> JARINU-FRGMQ.GIROFREEZER REV04 | AJ40: =Preencher!$B$3&$U$8&$V$8&A40&$AJ$6 -> JARINU-FRGMQ.GIROFREEZER (3) | AK40: =IFERROR(SUMIF('BD Otimix'!A:A,'BD VOLUME'!AG40,'BD Otimix'!O:O)+SUMIF('BD Otimix'!A:A,'BD VOLUME'!AH40,'BD Otimix'!O:O)+SUMIF('BD Otimix'!A:A,'BD VOLUME'!AI40,'BD Otimix'!O:O)+SUMIF('BD Otimix'!A:A,'BD VOLUME'!AJ40,'BD Otimix'!O:O)+SUMIF('BD Otimix'!A:A,'BD VOLUME'!AF40,'BD Otimix'!O:O),0) -> 0 | AL40: =IFERROR(F40/$E$3/1000/AK40,0) -> 0
A41: 12246 | C41: FIGADO FGO CG BL SE MP | D41: MIUDOS | E41: FÍGADO BLOCO | F41: =SUMIF('COLAR PLANO'!$A:$A,A41,'COLAR PLANO'!$D:$D) -> 0 | G41: =IFERROR(F41/($E$3*$C$3),0) -> 0 | H41: 0.0175 | I41: =IFERROR(G41/$D$7/H41,0) -> 0 | J41: =IFERROR(I41/$B$7,0) -> 0 | K41: 15 | L41: 1 | M41: 15 | N41: =IFERROR(G41/K41,"-") -> 0 | Q41: =IFERROR(G41/M41,"-") -> 0 | U41: - | V41: FRG | W41: =Preencher!$B$3&U41&V41&A41&$W$6 -> JARINU-FRG12246MQ.TUNEL DE CG (CONTINUO) | X41: =Preencher!$B$3&U41&V41&A41&$X$6 -> JARINU-FRG12246MQ.TUNEL DE CG (CONTINUO) (1) | Y41: =Preencher!$B$3&U41&V41&A41&$Y$6 -> JARINU-FRG12246MQ.TUNEL DE CG (CONTINUO) (2) | Z41: =Preencher!$B$3&U41&V41&A41&$Z$6 -> JARINU-FRG12246MQ.TUNEL DE CG (CONTINUO) (3) | AA41: =Preencher!$B$3&U41&V41&A41&$AA$6 -> JARINU-FRG12246MQ.TUNEL DE CG (ESTATICO) | AB41: =Preencher!$B$3&U41&V41&A41&$AB$6 -> JARINU-FRG12246MQ.TUNEL DE CG (ESTATICO) (1) | AC41: =Preencher!$B$3&U41&V41&A41&$AC$6 -> JARINU-FRG12246MQ.TUNEL DE CG (ESTATICO) (2) | AD41: =IFERROR(SUMIF('BD Otimix'!A:A,'BD VOLUME'!X41,'BD Otimix'!O:O)+SUMIF('BD Otimix'!A:A,'BD VOLUME'!Y41,'BD Otimix'!O:O)+SUMIF('BD Otimix'!A:A,'BD VOLUME'!Z41,'BD Otimix'!O:O)+SUMIF('BD Otimix'!A:A,'BD VOLUME'!AA41,'BD Otimix'!O:O)+SUMIF('BD Otimix'!A:A,'BD VOLUME'!AB41,'BD Otimix'!O:O)+SUMIF('BD Otimix'!A:A,'BD VOLUME'!AC41,'BD Otimix'!O:O)+SUMIF('BD Otimix'!A:A,'BD VOLUME'!W41,'BD Otimix'!O:O),0) -> 0 | AE41: =IFERROR(F41/$E$3/1000/AD41,0) -> 0 | AF41: =Preencher!$B$3&$U$8&$V$8&A41&$AF$6 -> JARINU-FRG12246MQ.GIROFREEZER | AG41: =Preencher!$B$3&$U$8&$V$8&A41&$AG$6 -> JARINU-FRG12246MQ.GIROFREEZER (1) | AH41: =Preencher!$B$3&$U$8&$V$8&A41&$AH$6 -> JARINU-FRG12246MQ.GIROFREEZER (2) | AI41: =Preencher!$B$3&$U$8&$V$8&A41&$AI$6 -> JARINU-FRG12246MQ.GIROFREEZER REV04 | AJ41: =Preencher!$B$3&$U$8&$V$8&A41&$AJ$6 -> JARINU-FRG12246MQ.GIROFREEZER (3) | AK41: =IFERROR(SUMIF('BD Otimix'!A:A,'BD VOLUME'!AG41,'BD Otimix'!O:O)+SUMIF('BD Otimix'!A:A,'BD VOLUME'!AH41,'BD Otimix'!O:O)+SUMIF('BD Otimix'!A:A,'BD VOLUME'!AI41,'BD Otimix'!O:O)+SUMIF('BD Otimix'!A:A,'BD VOLUME'!AJ41,'BD Otimix'!O:O)+SUMIF('BD Otimix'!A:A,'BD VOLUME'!AF41,'BD Otimix'!O:O),0) -> 0 | AL41: =IFERROR(F41/$E$3/1000/AK41,0) -> 0
A42: 55638 | C42: FIGADO FRANGO CG BL PF | D42: MIUDOS | E42: FÍGADO BLOCO | F42: =SUMIF('COLAR PLANO'!$A:$A,A42,'COLAR PLANO'!$D:$D) -> 0 | G42: =IFERROR(F42/($E$3*$C$3),0) -> 0 | H42: 0.0175 | I42: =IFERROR(G42/$D$7/H42,0) -> 0 | J42: =IFERROR(I42/$B$7,0) -> 0 | K42: 15 | L42: 1 | M42: 15 | N42: =IFERROR(G42/K42,"-") -> 0 | Q42: =IFERROR(G42/M42,"-") -> 0 | U42: - | V42: FRG | W42: =Preencher!$B$3&U42&V42&A42&$W$6 -> JARINU-FRG55638MQ.TUNEL DE CG (CONTINUO) | X42: =Preencher!$B$3&U42&V42&A42&$X$6 -> JARINU-FRG55638MQ.TUNEL DE CG (CONTINUO) (1) | Y42: =Preencher!$B$3&U42&V42&A42&$Y$6 -> JARINU-FRG55638MQ.TUNEL DE CG (CONTINUO) (2) | Z42: =Preencher!$B$3&U42&V42&A42&$Z$6 -> JARINU-FRG55638MQ.TUNEL DE CG (CONTINUO) (3) | AA42: =Preencher!$B$3&U42&V42&A42&$AA$6 -> JARINU-FRG55638MQ.TUNEL DE CG (ESTATICO) | AB42: =Preencher!$B$3&U42&V42&A42&$AB$6 -> JARINU-FRG55638MQ.TUNEL DE CG (ESTATICO) (1) | AC42: =Preencher!$B$3&U42&V42&A42&$AC$6 -> JARINU-FRG55638MQ.TUNEL DE CG (ESTATICO) (2) | AD42: =IFERROR(SUMIF('BD Otimix'!A:A,'BD VOLUME'!X42,'BD Otimix'!O:O)+SUMIF('BD Otimix'!A:A,'BD VOLUME'!Y42,'BD Otimix'!O:O)+SUMIF('BD Otimix'!A:A,'BD VOLUME'!Z42,'BD Otimix'!O:O)+SUMIF('BD Otimix'!A:A,'BD VOLUME'!AA42,'BD Otimix'!O:O)+SUMIF('BD Otimix'!A:A,'BD VOLUME'!AB42,'BD Otimix'!O:O)+SUMIF('BD Otimix'!A:A,'BD VOLUME'!AC42,'BD Otimix'!O:O)+SUMIF('BD Otimix'!A:A,'BD VOLUME'!W42,'BD Otimix'!O:O),0) -> 0 | AE42: =IFERROR(F42/$E$3/1000/AD42,0) -> 0 | AF42: =Preencher!$B$3&$U$8&$V$8&A42&$AF$6 -> JARINU-FRG55638MQ.GIROFREEZER | AG42: =Preencher!$B$3&$U$8&$V$8&A42&$AG$6 -> JARINU-FRG55638MQ.GIROFREEZER (1) | AH42: =Preencher!$B$3&$U$8&$V$8&A42&$AH$6 -> JARINU-FRG55638MQ.GIROFREEZER (2) | AI42: =Preencher!$B$3&$U$8&$V$8&A42&$AI$6 -> JARINU-FRG55638MQ.GIROFREEZER REV04 | AJ42: =Preencher!$B$3&$U$8&$V$8&A42&$AJ$6 -> JARINU-FRG55638MQ.GIROFREEZER (3) | AK42: =IFERROR(SUMIF('BD Otimix'!A:A,'BD VOLUME'!AG42,'BD Otimix'!O:O)+SUMIF('BD Otimix'!A:A,'BD VOLUME'!AH42,'BD Otimix'!O:O)+SUMIF('BD Otimix'!A:A,'BD VOLUME'!AI42,'BD Otimix'!O:O)+SUMIF('BD Otimix'!A:A,'BD VOLUME'!AJ42,'BD Otimix'!O:O)+SUMIF('BD Otimix'!A:A,'BD VOLUME'!AF42,'BD Otimix'!O:O),0) -> 0 | AL42: =IFERROR(F42/$E$3/1000/AK42,0) -> 0
A43: 796425 | C43: FIGADO FG CG BL PET FOOD | D43: MIUDOS | E43: FÍGADO BLOCO | F43: =SUMIF('COLAR PLANO'!$A:$A,A43,'COLAR PLANO'!$D:$D) -> 0 | G43: =IFERROR(F43/($E$3*$C$3),0) -> 0 | H43: 0.0175 | I43: =IFERROR(G43/$D$7/H43,0) -> 0 | J43: =IFERROR(I43/$B$7,0) -> 0 | K43: 15 | L43: 1 | M43: 15 | N43: =IFERROR(G43/K43,"-") -> 0 | Q43: =IFERROR(G43/M43,"-") -> 0 | U43: - | V43: FRG | W43: =Preencher!$B$3&U43&V43&A43&$W$6 -> JARINU-FRG796425MQ.TUNEL DE CG (CONTINUO) | X43: =Preencher!$B$3&U43&V43&A43&$X$6 -> JARINU-FRG796425MQ.TUNEL DE CG (CONTINUO) (1) | Y43: =Preencher!$B$3&U43&V43&A43&$Y$6 -> JARINU-FRG796425MQ.TUNEL DE CG (CONTINUO) (2) | Z43: =Preencher!$B$3&U43&V43&A43&$Z$6 -> JARINU-FRG796425MQ.TUNEL DE CG (CONTINUO) (3) | AA43: =Preencher!$B$3&U43&V43&A43&$AA$6 -> JARINU-FRG796425MQ.TUNEL DE CG (ESTATICO) | AB43: =Preencher!$B$3&U43&V43&A43&$AB$6 -> JARINU-FRG796425MQ.TUNEL DE CG (ESTATICO) (1) | AC43: =Preencher!$B$3&U43&V43&A43&$AC$6 -> JARINU-FRG796425MQ.TUNEL DE CG (ESTATICO) (2) | AD43: =IFERROR(SUMIF('BD Otimix'!A:A,'BD VOLUME'!X43,'BD Otimix'!O:O)+SUMIF('BD Otimix'!A:A,'BD VOLUME'!Y43,'BD Otimix'!O:O)+SUMIF('BD Otimix'!A:A,'BD VOLUME'!Z43,'BD Otimix'!O:O)+SUMIF('BD Otimix'!A:A,'BD VOLUME'!AA43,'BD Otimix'!O:O)+SUMIF('BD Otimix'!A:A,'BD VOLUME'!AB43,'BD Otimix'!O:O)+SUMIF('BD Otimix'!A:A,'BD VOLUME'!AC43,'BD Otimix'!O:O)+SUMIF('BD Otimix'!A:A,'BD VOLUME'!W43,'BD Otimix'!O:O),0) -> 0 | AE43: =IFERROR(F43/$E$3/1000/AD43,0) -> 0 | AF43: =Preencher!$B$3&$U$8&$V$8&A43&$AF$6 -> JARINU-FRG796425MQ.GIROFREEZER | AG43: =Preencher!$B$3&$U$8&$V$8&A43&$AG$6 -> JARINU-FRG796425MQ.GIROFREEZER (1) | AH43: =Preencher!$B$3&$U$8&$V$8&A43&$AH$6 -> JARINU-FRG796425MQ.GIROFREEZER (2) | AI43: =Preencher!$B$3&$U$8&$V$8&A43&$AI$6 -> JARINU-FRG796425MQ.GIROFREEZER REV04 | AJ43: =Preencher!$B$3&$U$8&$V$8&A43&$AJ$6 -> JARINU-FRG796425MQ.GIROFREEZER (3) | AK43: =IFERROR(SUMIF('BD Otimix'!A:A,'BD VOLUME'!AG43,'BD Otimix'!O:O)+SUMIF('BD Otimix'!A:A,'BD VOLUME'!AH43,'BD Otimix'!O:O)+SUMIF('BD Otimix'!A:A,'BD VOLUME'!AI43,'BD Otimix'!O:O)+SUMIF('BD Otimix'!A:A,'BD VOLUME'!AJ43,'BD Otimix'!O:O)+SUMIF('BD Otimix'!A:A,'BD VOLUME'!AF43,'BD Otimix'!O:O),0) -> 0 | AL43: =IFERROR(F43/$E$3/1000/AK43,0) -> 0
A44: 124014 | C44: MIUDOS CG FG FIGADO PET FOOD | D44: MIUDOS | E44: FÍGADO BLOCO | F44: =SUMIF('COLAR PLANO'!$A:$A,A44,'COLAR PLANO'!$D:$D) -> 0 | G44: =IFERROR(F44/($E$3*$C$3),0) -> 0 | H44: 0.0175 | I44: =IFERROR(G44/$D$7/H44,0) -> 0 | J44: =IFERROR(I44/$B$7,0) -> 0 | K44: 15 | L44: 1 | M44: 15 | N44: =IFERROR(G44/K44,"-") -> 0 | Q44: =IFERROR(G44/M44,"-") -> 0 | U44: - | V44: FRG | W44: =Preencher!$B$3&U44&V44&A44&$W$6 -> JARINU-FRG124014MQ.TUNEL DE CG (CONTINUO) | X44: =Preencher!$B$3&U44&V44&A44&$X$6 -> JARINU-FRG124014MQ.TUNEL DE CG (CONTINUO) (1) | Y44: =Preencher!$B$3&U44&V44&A44&$Y$6 -> JARINU-FRG124014MQ.TUNEL DE CG (CONTINUO) (2) | Z44: =Preencher!$B$3&U44&V44&A44&$Z$6 -> JARINU-FRG124014MQ.TUNEL DE CG (CONTINUO) (3) | AA44: =Preencher!$B$3&U44&V44&A44&$AA$6 -> JARINU-FRG124014MQ.TUNEL DE CG (ESTATICO) | AB44: =Preencher!$B$3&U44&V44&A44&$AB$6 -> JARINU-FRG124014MQ.TUNEL DE CG (ESTATICO) (1) | AC44: =Preencher!$B$3&U44&V44&A44&$AC$6 -> JARINU-FRG124014MQ.TUNEL DE CG (ESTATICO) (2) | AD44: =IFERROR(SUMIF('BD Otimix'!A:A,'BD VOLUME'!X44,'BD Otimix'!O:O)+SUMIF('BD Otimix'!A:A,'BD VOLUME'!Y44,'BD Otimix'!O:O)+SUMIF('BD Otimix'!A:A,'BD VOLUME'!Z44,'BD Otimix'!O:O)+SUMIF('BD Otimix'!A:A,'BD VOLUME'!AA44,'BD Otimix'!O:O)+SUMIF('BD Otimix'!A:A,'BD VOLUME'!AB44,'BD Otimix'!O:O)+SUMIF('BD Otimix'!A:A,'BD VOLUME'!AC44,'BD Otimix'!O:O)+SUMIF('BD Otimix'!A:A,'BD VOLUME'!W44,'BD Otimix'!O:O),0) -> 0 | AE44: =IFERROR(F44/$E$3/1000/AD44,0) -> 0 | AF44: =Preencher!$B$3&$U$8&$V$8&A44&$AF$6 -> JARINU-FRG124014MQ.GIROFREEZER | AG44: =Preencher!$B$3&$U$8&$V$8&A44&$AG$6 -> JARINU-FRG124014MQ.GIROFREEZER (1) | AH44: =Preencher!$B$3&$U$8&$V$8&A44&$AH$6 -> JARINU-FRG124014MQ.GIROFREEZER (2) | AI44: =Preencher!$B$3&$U$8&$V$8&A44&$AI$6 -> JARINU-FRG124014MQ.GIROFREEZER REV04 | AJ44: =Preencher!$B$3&$U$8&$V$8&A44&$AJ$6 -> JARINU-FRG124014MQ.GIROFREEZER (3) | AK44: =IFERROR(SUMIF('BD Otimix'!A:A,'BD VOLUME'!AG44,'BD Otimix'!O:O)+SUMIF('BD Otimix'!A:A,'BD VOLUME'!AH44,'BD Otimix'!O:O)+SUMIF('BD Otimix'!A:A,'BD VOLUME'!AI44,'BD Otimix'!O:O)+SUMIF('BD Otimix'!A:A,'BD VOLUME'!AJ44,'BD Otimix'!O:O)+SUMIF('BD Otimix'!A:A,'BD VOLUME'!AF44,'BD Otimix'!O:O),0) -> 0 | AL44: =IFERROR(F44/$E$3/1000/AK44,0) -> 0
A46: 45517 | B46: 45517 | C46: PES DE FRANGO | D46: MIUDOS | E46: PE 10 KG | F46: =SUMIF('COLAR PLANO'!$A:$A,A46,'COLAR PLANO'!$D:$D) -> 68256 | G46: =IFERROR(F46/($E$3*$C$3),0) -> 324.02563 | H46: 0.023326397 | I46: =IFERROR(G46/$D$7/H46,0) -> 4630.314 | J46: =IFERROR(I46/$B$7,0) -> 0.98522792 | K46: 10 | L46: 1 | M46: 10 | N46: =IFERROR(G46/K46,"-") -> 32.402563 | P46: =IFERROR(G46/M46,"-") -> 32.402563 | U46: - | V46: FRG | W46: =Preencher!$B$3&U46&V46&A46&$W$6 -> JARINU-FRG45517MQ.TUNEL DE CG (CONTINUO) | X46: =Preencher!$B$3&U46&V46&A46&$X$6 -> JARINU-FRG45517MQ.TUNEL DE CG (CONTINUO) (1) | Y46: =Preencher!$B$3&U46&V46&A46&$Y$6 -> JARINU-FRG45517MQ.TUNEL DE CG (CONTINUO) (2) | Z46: =Preencher!$B$3&U46&V46&A46&$Z$6 -> JARINU-FRG45517MQ.TUNEL DE CG (CONTINUO) (3) | AA46: =Preencher!$B$3&U46&V46&A46&$AA$6 -> JARINU-FRG45517MQ.TUNEL DE CG (ESTATICO) | AB46: =Preencher!$B$3&U46&V46&A46&$AB$6 -> JARINU-FRG45517MQ.TUNEL DE CG (ESTATICO) (1) | AC46: =Preencher!$B$3&U46&V46&A46&$AC$6 -> JARINU-FRG45517MQ.TUNEL DE CG (ESTATICO) (2) | AD46: =IFERROR(SUMIF('BD Otimix'!A:A,'BD VOLUME'!X46,'BD Otimix'!O:O)+SUMIF('BD Otimix'!A:A,'BD VOLUME'!Y46,'BD Otimix'!O:O)+SUMIF('BD Otimix'!A:A,'BD VOLUME'!Z46,'BD Otimix'!O:O)+SUMIF('BD Otimix'!A:A,'BD VOLUME'!AA46,'BD Otimix'!O:O)+SUMIF('BD Otimix'!A:A,'BD VOLUME'!AB46,'BD Otimix'!O:O)+SUMIF('BD Otimix'!A:A,'BD VOLUME'!AC46,'BD Otimix'!O:O)+SUMIF('BD Otimix'!A:A,'BD VOLUME'!W46,'BD Otimix'!O:O),0) -> 0 | AE46: =IFERROR(F46/$E$3/1000/AD46,0) -> 0 | AF46: =Preencher!$B$3&$U$8&$V$8&A46&$AF$6 -> JARINU-FRG45517MQ.GIROFREEZER | AG46: =Preencher!$B$3&$U$8&$V$8&A46&$AG$6 -> JARINU-FRG45517MQ.GIROFREEZER (1) | AH46: =Preencher!$B$3&$U$8&$V$8&A46&$AH$6 -> JARINU-FRG45517MQ.GIROFREEZER (2) | AI46: =Preencher!$B$3&$U$8&$V$8&A46&$AI$6 -> JARINU-FRG45517MQ.GIROFREEZER REV04 | AJ46: =Preencher!$B$3&$U$8&$V$8&A46&$AJ$6 -> JARINU-FRG45517MQ.GIROFREEZER (3) | AK46: =IFERROR(SUMIF('BD Otimix'!A:A,'BD VOLUME'!AG46,'BD Otimix'!O:O)+SUMIF('BD Otimix'!A:A,'BD VOLUME'!AH46,'BD Otimix'!O:O)+SUMIF('BD Otimix'!A:A,'BD VOLUME'!AI46,'BD Otimix'!O:O)+SUMIF('BD Otimix'!A:A,'BD VOLUME'!AJ46,'BD Otimix'!O:O)+SUMIF('BD Otimix'!A:A,'BD VOLUME'!AF46,'BD Otimix'!O:O),0) -> 0 | AL46: =IFERROR(F46/$E$3/1000/AK46,0) -> 0
A47: 41262 | C47: PES FG 35G UP GR A PB | D47: MIUDOS | E47: PE 10 KG | F47: =SUMIF('COLAR PLANO'!$A:$A,A47,'COLAR PLANO'!$D:$D) -> 0 | G47: =IFERROR(F47/($E$3*$C$3),0) -> 0 | H47: 0.023326397 | I47: =IFERROR(G47/$D$7/H47,0) -> 0 | J47: =IFERROR(I47/$B$7,0) -> 0 | K47: 10 | L47: 1 | M47: 10 | N47: =IFERROR(G47/K47,"-") -> 0 | P47: =IFERROR(G47/M47,"-") -> 0 | U47: - | V47: FRG | W47: =Preencher!$B$3&U47&V47&A47&$W$6 -> JARINU-FRG41262MQ.TUNEL DE CG (CONTINUO) | X47: =Preencher!$B$3&U47&V47&A47&$X$6 -> JARINU-FRG41262MQ.TUNEL DE CG (CONTINUO) (1) | Y47: =Preencher!$B$3&U47&V47&A47&$Y$6 -> JARINU-FRG41262MQ.TUNEL DE CG (CONTINUO) (2) | Z47: =Preencher!$B$3&U47&V47&A47&$Z$6 -> JARINU-FRG41262MQ.TUNEL DE CG (CONTINUO) (3) | AA47: =Preencher!$B$3&U47&V47&A47&$AA$6 -> JARINU-FRG41262MQ.TUNEL DE CG (ESTATICO) | AB47: =Preencher!$B$3&U47&V47&A47&$AB$6 -> JARINU-FRG41262MQ.TUNEL DE CG (ESTATICO) (1) | AC47: =Preencher!$B$3&U47&V47&A47&$AC$6 -> JARINU-FRG41262MQ.TUNEL DE CG (ESTATICO) (2) | AD47: =IFERROR(SUMIF('BD Otimix'!A:A,'BD VOLUME'!X47,'BD Otimix'!O:O)+SUMIF('BD Otimix'!A:A,'BD VOLUME'!Y47,'BD Otimix'!O:O)+SUMIF('BD Otimix'!A:A,'BD VOLUME'!Z47,'BD Otimix'!O:O)+SUMIF('BD Otimix'!A:A,'BD VOLUME'!AA47,'BD Otimix'!O:O)+SUMIF('BD Otimix'!A:A,'BD VOLUME'!AB47,'BD Otimix'!O:O)+SUMIF('BD Otimix'!A:A,'BD VOLUME'!AC47,'BD Otimix'!O:O)+SUMIF('BD Otimix'!A:A,'BD VOLUME'!W47,'BD Otimix'!O:O),0) -> 0 | AE47: =IFERROR(F47/$E$3/1000/AD47,0) -> 0 | AF47: =Preencher!$B$3&$U$8&$V$8&A47&$AF$6 -> JARINU-FRG41262MQ.GIROFREEZER | AG47: =Preencher!$B$3&$U$8&$V$8&A47&$AG$6 -> JARINU-FRG41262MQ.GIROFREEZER (1) | AH47: =Preencher!$B$3&$U$8&$V$8&A47&$AH$6 -> JARINU-FRG41262MQ.GIROFREEZER (2) | AI47: =Preencher!$B$3&$U$8&$V$8&A47&$AI$6 -> JARINU-FRG41262MQ.GIROFREEZER REV04 | AJ47: =Preencher!$B$3&$U$8&$V$8&A47&$AJ$6 -> JARINU-FRG41262MQ.GIROFREEZER (3) | AK47: =IFERROR(SUMIF('BD Otimix'!A:A,'BD VOLUME'!AG47,'BD Otimix'!O:O)+SUMIF('BD Otimix'!A:A,'BD VOLUME'!AH47,'BD Otimix'!O:O)+SUMIF('BD Otimix'!A:A,'BD VOLUME'!AI47,'BD Otimix'!O:O)+SUMIF('BD Otimix'!A:A,'BD VOLUME'!AJ47,'BD Otimix'!O:O)+SUMIF('BD Otimix'!A:A,'BD VOLUME'!AF47,'BD Otimix'!O:O),0) -> 0 | AL47: =IFERROR(F47/$E$3/1000/AK47,0) -> 0
A48: 790729 | B48: P-38 | C48: PES FG 35g UP GR A PB | D48: MIUDOS | E48: PE 10 KG | F48: =SUMIF('COLAR PLANO'!$A:$A,A48,'COLAR PLANO'!$D:$D) -> 0 | G48: =IFERROR(F48/($E$3*$C$3),0) -> 0 | H48: 0.023326397 | I48: =IFERROR(G48/$D$7/H48,0) -> 0 | J48: =IFERROR(I48/$B$7,0) -> 0 | K48: 10 | L48: 1 | M48: 10 | N48: =IFERROR(G48/K48,"-") -> 0 | P48: =IFERROR(G48/M48,"-") -> 0 | U48: - | V48: FRG | W48: =Preencher!$B$3&U48&V48&A48&$W$6 -> JARINU-FRG790729MQ.TUNEL DE CG (CONTINUO) | X48: =Preencher!$B$3&U48&V48&A48&$X$6 -> JARINU-FRG790729MQ.TUNEL DE CG (CONTINUO) (1) | Y48: =Preencher!$B$3&U48&V48&A48&$Y$6 -> JARINU-FRG790729MQ.TUNEL DE CG (CONTINUO) (2) | Z48: =Preencher!$B$3&U48&V48&A48&$Z$6 -> JARINU-FRG790729MQ.TUNEL DE CG (CONTINUO) (3) | AA48: =Preencher!$B$3&U48&V48&A48&$AA$6 -> JARINU-FRG790729MQ.TUNEL DE CG (ESTATICO) | AB48: =Preencher!$B$3&U48&V48&A48&$AB$6 -> JARINU-FRG790729MQ.TUNEL DE CG (ESTATICO) (1) | AC48: =Preencher!$B$3&U48&V48&A48&$AC$6 -> JARINU-FRG790729MQ.TUNEL DE CG (ESTATICO) (2) | AD48: =IFERROR(SUMIF('BD Otimix'!A:A,'BD VOLUME'!X48,'BD Otimix'!O:O)+SUMIF('BD Otimix'!A:A,'BD VOLUME'!Y48,'BD Otimix'!O:O)+SUMIF('BD Otimix'!A:A,'BD VOLUME'!Z48,'BD Otimix'!O:O)+SUMIF('BD Otimix'!A:A,'BD VOLUME'!AA48,'BD Otimix'!O:O)+SUMIF('BD Otimix'!A:A,'BD VOLUME'!AB48,'BD Otimix'!O:O)+SUMIF('BD Otimix'!A:A,'BD VOLUME'!AC48,'BD Otimix'!O:O)+SUMIF('BD Otimix'!A:A,'BD VOLUME'!W48,'BD Otimix'!O:O),0) -> 0 | AE48: =IFERROR(F48/$E$3/1000/AD48,0) -> 0 | AF48: =Preencher!$B$3&$U$8&$V$8&A48&$AF$6 -> JARINU-FRG790729MQ.GIROFREEZER | AG48: =Preencher!$B$3&$U$8&$V$8&A48&$AG$6 -> JARINU-FRG790729MQ.GIROFREEZER (1) | AH48: =Preencher!$B$3&$U$8&$V$8&A48&$AH$6 -> JARINU-FRG790729MQ.GIROFREEZER (2) | AI48: =Preencher!$B$3&$U$8&$V$8&A48&$AI$6 -> JARINU-FRG790729MQ.GIROFREEZER REV04 | AJ48: =Preencher!$B$3&$U$8&$V$8&A48&$AJ$6 -> JARINU-FRG790729MQ.GIROFREEZER (3) | AK48: =IFERROR(SUMIF('BD Otimix'!A:A,'BD VOLUME'!AG48,'BD Otimix'!O:O)+SUMIF('BD Otimix'!A:A,'BD VOLUME'!AH48,'BD Otimix'!O:O)+SUMIF('BD Otimix'!A:A,'BD VOLUME'!AI48,'BD Otimix'!O:O)+SUMIF('BD Otimix'!A:A,'BD VOLUME'!AJ48,'BD Otimix'!O:O)+SUMIF('BD Otimix'!A:A,'BD VOLUME'!AF48,'BD Otimix'!O:O),0) -> 0 | AL48: =IFERROR(F48/$E$3/1000/AK48,0) -> 0
A49: 977128 | B49: P-71 | C49: PES FG 35g UP GR B PB | D49: MIUDOS | E49: PE 10 KG | F49: =SUMIF('COLAR PLANO'!$A:$A,A49,'COLAR PLANO'!$D:$D) -> 0 | G49: =IFERROR(F49/($E$3*$C$3),0) -> 0 | H49: 0.023326397 | I49: =IFERROR(G49/$D$7/H49,0) -> 0 | J49: =IFERROR(I49/$B$7,0) -> 0 | K49: 10 | L49: 1 | M49: 10 | N49: =IFERROR(G49/K49,"-") -> 0 | P49: =IFERROR(G49/M49,"-") -> 0 | U49: - | V49: FRG | W49: =Preencher!$B$3&U49&V49&A49&$W$6 -> JARINU-FRG977128MQ.TUNEL DE CG (CONTINUO) | X49: =Preencher!$B$3&U49&V49&A49&$X$6 -> JARINU-FRG977128MQ.TUNEL DE CG (CONTINUO) (1) | Y49: =Preencher!$B$3&U49&V49&A49&$Y$6 -> JARINU-FRG977128MQ.TUNEL DE CG (CONTINUO) (2) | Z49: =Preencher!$B$3&U49&V49&A49&$Z$6 -> JARINU-FRG977128MQ.TUNEL DE CG (CONTINUO) (3) | AA49: =Preencher!$B$3&U49&V49&A49&$AA$6 -> JARINU-FRG977128MQ.TUNEL DE CG (ESTATICO) | AB49: =Preencher!$B$3&U49&V49&A49&$AB$6 -> JARINU-FRG977128MQ.TUNEL DE CG (ESTATICO) (1) | AC49: =Preencher!$B$3&U49&V49&A49&$AC$6 -> JARINU-FRG977128MQ.TUNEL DE CG (ESTATICO) (2) | AD49: =IFERROR(SUMIF('BD Otimix'!A:A,'BD VOLUME'!X49,'BD Otimix'!O:O)+SUMIF('BD Otimix'!A:A,'BD VOLUME'!Y49,'BD Otimix'!O:O)+SUMIF('BD Otimix'!A:A,'BD VOLUME'!Z49,'BD Otimix'!O:O)+SUMIF('BD Otimix'!A:A,'BD VOLUME'!AA49,'BD Otimix'!O:O)+SUMIF('BD Otimix'!A:A,'BD VOLUME'!AB49,'BD Otimix'!O:O)+SUMIF('BD Otimix'!A:A,'BD VOLUME'!AC49,'BD Otimix'!O:O)+SUMIF('BD Otimix'!A:A,'BD VOLUME'!W49,'BD Otimix'!O:O),0) -> 0 | AE49: =IFERROR(F49/$E$3/1000/AD49,0) -> 0 | AF49: =Preencher!$B$3&$U$8&$V$8&A49&$AF$6 -> JARINU-FRG977128MQ.GIROFREEZER | AG49: =Preencher!$B$3&$U$8&$V$8&A49&$AG$6 -> JARINU-FRG977128MQ.GIROFREEZER (1) | AH49: =Preencher!$B$3&$U$8&$V$8&A49&$AH$6 -> JARINU-FRG977128MQ.GIROFREEZER (2) | AI49: =Preencher!$B$3&$U$8&$V$8&A49&$AI$6 -> JARINU-FRG977128MQ.GIROFREEZER REV04 | AJ49: =Preencher!$B$3&$U$8&$V$8&A49&$AJ$6 -> JARINU-FRG977128MQ.GIROFREEZER (3) | AK49: =IFERROR(SUMIF('BD Otimix'!A:A,'BD VOLUME'!AG49,'BD Otimix'!O:O)+SUMIF('BD Otimix'!A:A,'BD VOLUME'!AH49,'BD Otimix'!O:O)+SUMIF('BD Otimix'!A:A,'BD VOLUME'!AI49,'BD Otimix'!O:O)+SUMIF('BD Otimix'!A:A,'BD VOLUME'!AJ49,'BD Otimix'!O:O)+SUMIF('BD Otimix'!A:A,'BD VOLUME'!AF49,'BD Otimix'!O:O),0) -> 0 | AL49: =IFERROR(F49/$E$3/1000/AK49,0) -> 0
A50: 929301 | B50: P-62 | C50: PES FRANGO PALMA 25G UP | D50: MIUDOS | E50: PE 13 KG | F50: =SUMIF('COLAR PLANO'!$A:$A,A50,'COLAR PLANO'!$D:$D) -> 0 | G50: =IFERROR(F50/($E$3*$C$3),0) -> 0 | H50: 0.023326397 | I50: =IFERROR(G50/$D$7/H50,0) -> 0 | J50: =IFERROR(I50/$B$7,0) -> 0 | K50: 15 | L50: 1 | M50: 15 | N50: =IFERROR(G50/K50,"-") -> 0 | P50: =IFERROR(G50/M50,"-") -> 0 | U50: - | V50: FRG | W50: =Preencher!$B$3&U50&V50&A50&$W$6 -> JARINU-FRG929301MQ.TUNEL DE CG (CONTINUO) | X50: =Preencher!$B$3&U50&V50&A50&$X$6 -> JARINU-FRG929301MQ.TUNEL DE CG (CONTINUO) (1) | Y50: =Preencher!$B$3&U50&V50&A50&$Y$6 -> JARINU-FRG929301MQ.TUNEL DE CG (CONTINUO) (2) | Z50: =Preencher!$B$3&U50&V50&A50&$Z$6 -> JARINU-FRG929301MQ.TUNEL DE CG (CONTINUO) (3) | AA50: =Preencher!$B$3&U50&V50&A50&$AA$6 -> JARINU-FRG929301MQ.TUNEL DE CG (ESTATICO) | AB50: =Preencher!$B$3&U50&V50&A50&$AB$6 -> JARINU-FRG929301MQ.TUNEL DE CG (ESTATICO) (1) | AC50: =Preencher!$B$3&U50&V50&A50&$AC$6 -> JARINU-FRG929301MQ.TUNEL DE CG (ESTATICO) (2) | AD50: =IFERROR(SUMIF('BD Otimix'!A:A,'BD VOLUME'!X50,'BD Otimix'!O:O)+SUMIF('BD Otimix'!A:A,'BD VOLUME'!Y50,'BD Otimix'!O:O)+SUMIF('BD Otimix'!A:A,'BD VOLUME'!Z50,'BD Otimix'!O:O)+SUMIF('BD Otimix'!A:A,'BD VOLUME'!AA50,'BD Otimix'!O:O)+SUMIF('BD Otimix'!A:A,'BD VOLUME'!AB50,'BD Otimix'!O:O)+SUMIF('BD Otimix'!A:A,'BD VOLUME'!AC50,'BD Otimix'!O:O)+SUMIF('BD Otimix'!A:A,'BD VOLUME'!W50,'BD Otimix'!O:O),0) -> 0 | AE50: =IFERROR(F50/$E$3/1000/AD50,0) -> 0 | AF50: =Preencher!$B$3&$U$8&$V$8&A50&$AF$6 -> JARINU-FRG929301MQ.GIROFREEZER | AG50: =Preencher!$B$3&$U$8&$V$8&A50&$AG$6 -> JARINU-FRG929301MQ.GIROFREEZER (1) | AH50: =Preencher!$B$3&$U$8&$V$8&A50&$AH$6 -> JARINU-FRG929301MQ.GIROFREEZER (2) | AI50: =Preencher!$B$3&$U$8&$V$8&A50&$AI$6 -> JARINU-FRG929301MQ.GIROFREEZER REV04 | AJ50: =Preencher!$B$3&$U$8&$V$8&A50&$AJ$6 -> JARINU-FRG929301MQ.GIROFREEZER (3) | AK50: =IFERROR(SUMIF('BD Otimix'!A:A,'BD VOLUME'!AG50,'BD Otimix'!O:O)+SUMIF('BD Otimix'!A:A,'BD VOLUME'!AH50,'BD Otimix'!O:O)+SUMIF('BD Otimix'!A:A,'BD VOLUME'!AI50,'BD Otimix'!O:O)+SUMIF('BD Otimix'!A:A,'BD VOLUME'!AJ50,'BD Otimix'!O:O)+SUMIF('BD Otimix'!A:A,'BD VOLUME'!AF50,'BD Otimix'!O:O),0) -> 0 | AL50: =IFERROR(F50/$E$3/1000/AK50,0) -> 0
A51: 977110 | B51: P-70 | C51: PES FG 35g UP GR B PB | D51: MIUDOS | E51: PE 13 KG | F51: =SUMIF('COLAR PLANO'!$A:$A,A51,'COLAR PLANO'!$D:$D) -> 0 | G51: =IFERROR(F51/($E$3*$C$3),0) -> 0 | H51: 0.023326397 | I51: =IFERROR(G51/$D$7/H51,0) -> 0 | J51: =IFERROR(I51/$B$7,0) -> 0 | K51: 15 | L51: 1 | M51: 15 | N51: =IFERROR(G51/K51,"-") -> 0 | P51: =IFERROR(G51/M51,"-") -> 0 | U51: - | V51: FRG | W51: =Preencher!$B$3&U51&V51&A51&$W$6 -> JARINU-FRG977110MQ.TUNEL DE CG (CONTINUO) | X51: =Preencher!$B$3&U51&V51&A51&$X$6 -> JARINU-FRG977110MQ.TUNEL DE CG (CONTINUO) (1) | Y51: =Preencher!$B$3&U51&V51&A51&$Y$6 -> JARINU-FRG977110MQ.TUNEL DE CG (CONTINUO) (2) | Z51: =Preencher!$B$3&U51&V51&A51&$Z$6 -> JARINU-FRG977110MQ.TUNEL DE CG (CONTINUO) (3) | AA51: =Preencher!$B$3&U51&V51&A51&$AA$6 -> JARINU-FRG977110MQ.TUNEL DE CG (ESTATICO) | AB51: =Preencher!$B$3&U51&V51&A51&$AB$6 -> JARINU-FRG977110MQ.TUNEL DE CG (ESTATICO) (1) | AC51: =Preencher!$B$3&U51&V51&A51&$AC$6 -> JARINU-FRG977110MQ.TUNEL DE CG (ESTATICO) (2) | AD51: =IFERROR(SUMIF('BD Otimix'!A:A,'BD VOLUME'!X51,'BD Otimix'!O:O)+SUMIF('BD Otimix'!A:A,'BD VOLUME'!Y51,'BD Otimix'!O:O)+SUMIF('BD Otimix'!A:A,'BD VOLUME'!Z51,'BD Otimix'!O:O)+SUMIF('BD Otimix'!A:A,'BD VOLUME'!AA51,'BD Otimix'!O:O)+SUMIF('BD Otimix'!A:A,'BD VOLUME'!AB51,'BD Otimix'!O:O)+SUMIF('BD Otimix'!A:A,'BD VOLUME'!AC51,'BD Otimix'!O:O)+SUMIF('BD Otimix'!A:A,'BD VOLUME'!W51,'BD Otimix'!O:O),0) -> 0 | AE51: =IFERROR(F51/$E$3/1000/AD51,0) -> 0 | AF51: =Preencher!$B$3&$U$8&$V$8&A51&$AF$6 -> JARINU-FRG977110MQ.GIROFREEZER | AG51: =Preencher!$B$3&$U$8&$V$8&A51&$AG$6 -> JARINU-FRG977110MQ.GIROFREEZER (1) | AH51: =Preencher!$B$3&$U$8&$V$8&A51&$AH$6 -> JARINU-FRG977110MQ.GIROFREEZER (2) | AI51: =Preencher!$B$3&$U$8&$V$8&A51&$AI$6 -> JARINU-FRG977110MQ.GIROFREEZER REV04 | AJ51: =Preencher!$B$3&$U$8&$V$8&A51&$AJ$6 -> JARINU-FRG977110MQ.GIROFREEZER (3) | AK51: =IFERROR(SUMIF('BD Otimix'!A:A,'BD VOLUME'!AG51,'BD Otimix'!O:O)+SUMIF('BD Otimix'!A:A,'BD VOLUME'!AH51,'BD Otimix'!O:O)+SUMIF('BD Otimix'!A:A,'BD VOLUME'!AI51,'BD Otimix'!O:O)+SUMIF('BD Otimix'!A:A,'BD VOLUME'!AJ51,'BD Otimix'!O:O)+SUMIF('BD Otimix'!A:A,'BD VOLUME'!AF51,'BD Otimix'!O:O),0) -> 0 | AL51: =IFERROR(F51/$E$3/1000/AK51,0) -> 0
A52: 59510 | B52: P-44 | C52: PES FG 35g UP GR A PB | D52: MIUDOS | E52: PE 13 KG | F52: =SUMIF('COLAR PLANO'!$A:$A,A52,'COLAR PLANO'!$D:$D) -> 0 | G52: =IFERROR(F52/($E$3*$C$3),0) -> 0 | H52: 0.023326397 | I52: =IFERROR(G52/$D$7/H52,0) -> 0 | J52: =IFERROR(I52/$B$7,0) -> 0 | K52: 15 | L52: 1 | M52: 15 | N52: =IFERROR(G52/K52,"-") -> 0 | P52: =IFERROR(G52/M52,"-") -> 0 | U52: - | V52: FRG | W52: =Preencher!$B$3&U52&V52&A52&$W$6 -> JARINU-FRG59510MQ.TUNEL DE CG (CONTINUO) | X52: =Preencher!$B$3&U52&V52&A52&$X$6 -> JARINU-FRG59510MQ.TUNEL DE CG (CONTINUO) (1) | Y52: =Preencher!$B$3&U52&V52&A52&$Y$6 -> JARINU-FRG59510MQ.TUNEL DE CG (CONTINUO) (2) | Z52: =Preencher!$B$3&U52&V52&A52&$Z$6 -> JARINU-FRG59510MQ.TUNEL DE CG (CONTINUO) (3) | AA52: =Preencher!$B$3&U52&V52&A52&$AA$6 -> JARINU-FRG59510MQ.TUNEL DE CG (ESTATICO) | AB52: =Preencher!$B$3&U52&V52&A52&$AB$6 -> JARINU-FRG59510MQ.TUNEL DE CG (ESTATICO) (1) | AC52: =Preencher!$B$3&U52&V52&A52&$AC$6 -> JARINU-FRG59510MQ.TUNEL DE CG (ESTATICO) (2) | AD52: =IFERROR(SUMIF('BD Otimix'!A:A,'BD VOLUME'!X52,'BD Otimix'!O:O)+SUMIF('BD Otimix'!A:A,'BD VOLUME'!Y52,'BD Otimix'!O:O)+SUMIF('BD Otimix'!A:A,'BD VOLUME'!Z52,'BD Otimix'!O:O)+SUMIF('BD Otimix'!A:A,'BD VOLUME'!AA52,'BD Otimix'!O:O)+SUMIF('BD Otimix'!A:A,'BD VOLUME'!AB52,'BD Otimix'!O:O)+SUMIF('BD Otimix'!A:A,'BD VOLUME'!AC52,'BD Otimix'!O:O)+SUMIF('BD Otimix'!A:A,'BD VOLUME'!W52,'BD Otimix'!O:O),0) -> 0 | AE52: =IFERROR(F52/$E$3/1000/AD52,0) -> 0 | AF52: =Preencher!$B$3&$U$8&$V$8&A52&$AF$6 -> JARINU-FRG59510MQ.GIROFREEZER | AG52: =Preencher!$B$3&$U$8&$V$8&A52&$AG$6 -> JARINU-FRG59510MQ.GIROFREEZER (1) | AH52: =Preencher!$B$3&$U$8&$V$8&A52&$AH$6 -> JARINU-FRG59510MQ.GIROFREEZER (2) | AI52: =Preencher!$B$3&$U$8&$V$8&A52&$AI$6 -> JARINU-FRG59510MQ.GIROFREEZER REV04 | AJ52: =Preencher!$B$3&$U$8&$V$8&A52&$AJ$6 -> JARINU-FRG59510MQ.GIROFREEZER (3) | AK52: =IFERROR(SUMIF('BD Otimix'!A:A,'BD VOLUME'!AG52,'BD Otimix'!O:O)+SUMIF('BD Otimix'!A:A,'BD VOLUME'!AH52,'BD Otimix'!O:O)+SUMIF('BD Otimix'!A:A,'BD VOLUME'!AI52,'BD Otimix'!O:O)+SUMIF('BD Otimix'!A:A,'BD VOLUME'!AJ52,'BD Otimix'!O:O)+SUMIF('BD Otimix'!A:A,'BD VOLUME'!AF52,'BD Otimix'!O:O),0) -> 0 | AL52: =IFERROR(F52/$E$3/1000/AK52,0) -> 0
A53: 42030 | B53: P-41 | C53: PALMA FG 25g UP GR A PB | D53: MIUDOS | E53: PE 7,5 KG | F53: =SUMIF('COLAR PLANO'!$A:$A,A53,'COLAR PLANO'!$D:$D) -> 0 | G53: =IFERROR(F53/($E$3*$C$3),0) -> 0 | H53: 0.035 | I53: =IFERROR(G53/$D$7/H53,0) -> 0 | J53: =IFERROR(I53/$B$7,0) -> 0 | K53: 7.5 | L53: 2 | M53: 15 | N53: =IFERROR(G53/K53,"-") -> 0 | O53: =IFERROR(G53/M53,"-") -> 0 | U53: - | V53: FRG | W53: =Preencher!$B$3&U53&V53&A53&$W$6 -> JARINU-FRG42030MQ.TUNEL DE CG (CONTINUO) | X53: =Preencher!$B$3&U53&V53&A53&$X$6 -> JARINU-FRG42030MQ.TUNEL DE CG (CONTINUO) (1) | Y53: =Preencher!$B$3&U53&V53&A53&$Y$6 -> JARINU-FRG42030MQ.TUNEL DE CG (CONTINUO) (2) | Z53: =Preencher!$B$3&U53&V53&A53&$Z$6 -> JARINU-FRG42030MQ.TUNEL DE CG (CONTINUO) (3) | AA53: =Preencher!$B$3&U53&V53&A53&$AA$6 -> JARINU-FRG42030MQ.TUNEL DE CG (ESTATICO) | AB53: =Preencher!$B$3&U53&V53&A53&$AB$6 -> JARINU-FRG42030MQ.TUNEL DE CG (ESTATICO) (1) | AC53: =Preencher!$B$3&U53&V53&A53&$AC$6 -> JARINU-FRG42030MQ.TUNEL DE CG (ESTATICO) (2) | AD53: =IFERROR(SUMIF('BD Otimix'!A:A,'BD VOLUME'!X53,'BD Otimix'!O:O)+SUMIF('BD Otimix'!A:A,'BD VOLUME'!Y53,'BD Otimix'!O:O)+SUMIF('BD Otimix'!A:A,'BD VOLUME'!Z53,'BD Otimix'!O:O)+SUMIF('BD Otimix'!A:A,'BD VOLUME'!AA53,'BD Otimix'!O:O)+SUMIF('BD Otimix'!A:A,'BD VOLUME'!AB53,'BD Otimix'!O:O)+SUMIF('BD Otimix'!A:A,'BD VOLUME'!AC53,'BD Otimix'!O:O)+SUMIF('BD Otimix'!A:A,'BD VOLUME'!W53,'BD Otimix'!O:O),0) -> 0 | AE53: =IFERROR(F53/$E$3/1000/AD53,0) -> 0 | AF53: =Preencher!$B$3&$U$8&$V$8&A53&$AF$6 -> JARINU-FRG42030MQ.GIROFREEZER | AG53: =Preencher!$B$3&$U$8&$V$8&A53&$AG$6 -> JARINU-FRG42030MQ.GIROFREEZER (1) | AH53: =Preencher!$B$3&$U$8&$V$8&A53&$AH$6 -> JARINU-FRG42030MQ.GIROFREEZER (2) | AI53: =Preencher!$B$3&$U$8&$V$8&A53&$AI$6 -> JARINU-FRG42030MQ.GIROFREEZER REV04 | AJ53: =Preencher!$B$3&$U$8&$V$8&A53&$AJ$6 -> JARINU-FRG42030MQ.GIROFREEZER (3) | AK53: =IFERROR(SUMIF('BD Otimix'!A:A,'BD VOLUME'!AG53,'BD Otimix'!O:O)+SUMIF('BD Otimix'!A:A,'BD VOLUME'!AH53,'BD Otimix'!O:O)+SUMIF('BD Otimix'!A:A,'BD VOLUME'!AI53,'BD Otimix'!O:O)+SUMIF('BD Otimix'!A:A,'BD VOLUME'!AJ53,'BD Otimix'!O:O)+SUMIF('BD Otimix'!A:A,'BD VOLUME'!AF53,'BD Otimix'!O:O),0) -> 0 | AL53: =IFERROR(F53/$E$3/1000/AK53,0) -> 0
A54: 977713 | B54: P-78 | C54: PALMA FG 25g UP GR B PB | D54: MIUDOS | E54: PE 7,5 KG | F54: =SUMIF('COLAR PLANO'!$A:$A,A54,'COLAR PLANO'!$D:$D) -> 0 | G54: =IFERROR(F54/($E$3*$C$3),0) -> 0 | H54: 0.035 | I54: =IFERROR(G54/$D$7/H54,0) -> 0 | J54: =IFERROR(I54/$B$7,0) -> 0 | K54: 7.5 | L54: 2 | M54: 15 | N54: =IFERROR(G54/K54,"-") -> 0 | O54: =IFERROR(G54/M54,"-") -> 0 | U54: - | V54: FRG | W54: =Preencher!$B$3&U54&V54&A54&$W$6 -> JARINU-FRG977713MQ.TUNEL DE CG (CONTINUO) | X54: =Preencher!$B$3&U54&V54&A54&$X$6 -> JARINU-FRG977713MQ.TUNEL DE CG (CONTINUO) (1) | Y54: =Preencher!$B$3&U54&V54&A54&$Y$6 -> JARINU-FRG977713MQ.TUNEL DE CG (CONTINUO) (2) | Z54: =Preencher!$B$3&U54&V54&A54&$Z$6 -> JARINU-FRG977713MQ.TUNEL DE CG (CONTINUO) (3) | AA54: =Preencher!$B$3&U54&V54&A54&$AA$6 -> JARINU-FRG977713MQ.TUNEL DE CG (ESTATICO) | AB54: =Preencher!$B$3&U54&V54&A54&$AB$6 -> JARINU-FRG977713MQ.TUNEL DE CG (ESTATICO) (1) | AC54: =Preencher!$B$3&U54&V54&A54&$AC$6 -> JARINU-FRG977713MQ.TUNEL DE CG (ESTATICO) (2) | AD54: =IFERROR(SUMIF('BD Otimix'!A:A,'BD VOLUME'!X54,'BD Otimix'!O:O)+SUMIF('BD Otimix'!A:A,'BD VOLUME'!Y54,'BD Otimix'!O:O)+SUMIF('BD Otimix'!A:A,'BD VOLUME'!Z54,'BD Otimix'!O:O)+SUMIF('BD Otimix'!A:A,'BD VOLUME'!AA54,'BD Otimix'!O:O)+SUMIF('BD Otimix'!A:A,'BD VOLUME'!AB54,'BD Otimix'!O:O)+SUMIF('BD Otimix'!A:A,'BD VOLUME'!AC54,'BD Otimix'!O:O)+SUMIF('BD Otimix'!A:A,'BD VOLUME'!W54,'BD Otimix'!O:O),0) -> 0 | AE54: =IFERROR(F54/$E$3/1000/AD54,0) -> 0 | AF54: =Preencher!$B$3&$U$8&$V$8&A54&$AF$6 -> JARINU-FRG977713MQ.GIROFREEZER | AG54: =Preencher!$B$3&$U$8&$V$8&A54&$AG$6 -> JARINU-FRG977713MQ.GIROFREEZER (1) | AH54: =Preencher!$B$3&$U$8&$V$8&A54&$AH$6 -> JARINU-FRG977713MQ.GIROFREEZER (2) | AI54: =Preencher!$B$3&$U$8&$V$8&A54&$AI$6 -> JARINU-FRG977713MQ.GIROFREEZER REV04 | AJ54: =Preencher!$B$3&$U$8&$V$8&A54&$AJ$6 -> JARINU-FRG977713MQ.GIROFREEZER (3) | AK54: =IFERROR(SUMIF('BD Otimix'!A:A,'BD VOLUME'!AG54,'BD Otimix'!O:O)+SUMIF('BD Otimix'!A:A,'BD VOLUME'!AH54,'BD Otimix'!O:O)+SUMIF('BD Otimix'!A:A,'BD VOLUME'!AI54,'BD Otimix'!O:O)+SUMIF('BD Otimix'!A:A,'BD VOLUME'!AJ54,'BD Otimix'!O:O)+SUMIF('BD Otimix'!A:A,'BD VOLUME'!AF54,'BD Otimix'!O:O),0) -> 0 | AL54: =IFERROR(F54/$E$3/1000/AK54,0) -> 0
A55: 40819 | B55: P-27 | C55: PES FRANGO 35UP CG PB | D55: MIUDOS | E55: PE 13 KG | F55: =SUMIF('COLAR PLANO'!$A:$A,A55,'COLAR PLANO'!$D:$D) -> 0 | G55: =IFERROR(F55/($E$3*$C$3),0) -> 0 | H55: 0.023326397 | I55: =IFERROR(G55/$D$7/H55,0) -> 0 | J55: =IFERROR(I55/$B$7,0) -> 0 | K55: 15 | L55: 1 | M55: 15 | N55: =IFERROR(G55/K55,"-") -> 0 | P55: =IFERROR(G55/M55,"-") -> 0 | U55: - | V55: FRG | W55: =Preencher!$B$3&U55&V55&A55&$W$6 -> JARINU-FRG40819MQ.TUNEL DE CG (CONTINUO) | X55: =Preencher!$B$3&U55&V55&A55&$X$6 -> JARINU-FRG40819MQ.TUNEL DE CG (CONTINUO) (1) | Y55: =Preencher!$B$3&U55&V55&A55&$Y$6 -> JARINU-FRG40819MQ.TUNEL DE CG (CONTINUO) (2) | Z55: =Preencher!$B$3&U55&V55&A55&$Z$6 -> JARINU-FRG40819MQ.TUNEL DE CG (CONTINUO) (3) | AA55: =Preencher!$B$3&U55&V55&A55&$AA$6 -> JARINU-FRG40819MQ.TUNEL DE CG (ESTATICO) | AB55: =Preencher!$B$3&U55&V55&A55&$AB$6 -> JARINU-FRG40819MQ.TUNEL DE CG (ESTATICO) (1) | AC55: =Preencher!$B$3&U55&V55&A55&$AC$6 -> JARINU-FRG40819MQ.TUNEL DE CG (ESTATICO) (2) | AD55: =IFERROR(SUMIF('BD Otimix'!A:A,'BD VOLUME'!X55,'BD Otimix'!O:O)+SUMIF('BD Otimix'!A:A,'BD VOLUME'!Y55,'BD Otimix'!O:O)+SUMIF('BD Otimix'!A:A,'BD VOLUME'!Z55,'BD Otimix'!O:O)+SUMIF('BD Otimix'!A:A,'BD VOLUME'!AA55,'BD Otimix'!O:O)+SUMIF('BD Otimix'!A:A,'BD VOLUME'!AB55,'BD Otimix'!O:O)+SUMIF('BD Otimix'!A:A,'BD VOLUME'!AC55,'BD Otimix'!O:O)+SUMIF('BD Otimix'!A:A,'BD VOLUME'!W55,'BD Otimix'!O:O),0) -> 0 | AE55: =IFERROR(F55/$E$3/1000/AD55,0) -> 0 | AF55: =Preencher!$B$3&$U$8&$V$8&A55&$AF$6 -> JARINU-FRG40819MQ.GIROFREEZER | AG55: =Preencher!$B$3&$U$8&$V$8&A55&$AG$6 -> JARINU-FRG40819MQ.GIROFREEZER (1) | AH55: =Preencher!$B$3&$U$8&$V$8&A55&$AH$6 -> JARINU-FRG40819MQ.GIROFREEZER (2) | AI55: =Preencher!$B$3&$U$8&$V$8&A55&$AI$6 -> JARINU-FRG40819MQ.GIROFREEZER REV04 | AJ55: =Preencher!$B$3&$U$8&$V$8&A55&$AJ$6 -> JARINU-FRG40819MQ.GIROFREEZER (3) | AK55: =IFERROR(SUMIF('BD Otimix'!A:A,'BD VOLUME'!AG55,'BD Otimix'!O:O)+SUMIF('BD Otimix'!A:A,'BD VOLUME'!AH55,'BD Otimix'!O:O)+SUMIF('BD Otimix'!A:A,'BD VOLUME'!AI55,'BD Otimix'!O:O)+SUMIF('BD Otimix'!A:A,'BD VOLUME'!AJ55,'BD Otimix'!O:O)+SUMIF('BD Otimix'!A:A,'BD VOLUME'!AF55,'BD Otimix'!O:O),0) -> 0 | AL55: =IFERROR(F55/$E$3/1000/AK55,0) -> 0
A56: 11193 | B56: PES-BC | C56: PES FRANGO CG | D56: MIUDOS | E56: PE 13 KG | F56: =SUMIF('COLAR PLANO'!$A:$A,A56,'COLAR PLANO'!$D:$D) -> 0 | G56: =IFERROR(F56/($E$3*$C$3),0) -> 0 | H56: 0.023326397 | I56: =IFERROR(G56/$D$7/H56,0) -> 0 | J56: =IFERROR(I56/$B$7,0) -> 0 | K56: 15 | L56: 1 | M56: 15 | N56: =IFERROR(G56/K56,"-") -> 0 | P56: =IFERROR(G56/M56,"-") -> 0 | U56: - | V56: FRG | W56: =Preencher!$B$3&U56&V56&A56&$W$6 -> JARINU-FRG11193MQ.TUNEL DE CG (CONTINUO) | X56: =Preencher!$B$3&U56&V56&A56&$X$6 -> JARINU-FRG11193MQ.TUNEL DE CG (CONTINUO) (1) | Y56: =Preencher!$B$3&U56&V56&A56&$Y$6 -> JARINU-FRG11193MQ.TUNEL DE CG (CONTINUO) (2) | Z56: =Preencher!$B$3&U56&V56&A56&$Z$6 -> JARINU-FRG11193MQ.TUNEL DE CG (CONTINUO) (3) | AA56: =Preencher!$B$3&U56&V56&A56&$AA$6 -> JARINU-FRG11193MQ.TUNEL DE CG (ESTATICO) | AB56: =Preencher!$B$3&U56&V56&A56&$AB$6 -> JARINU-FRG11193MQ.TUNEL DE CG (ESTATICO) (1) | AC56: =Preencher!$B$3&U56&V56&A56&$AC$6 -> JARINU-FRG11193MQ.TUNEL DE CG (ESTATICO) (2) | AD56: =IFERROR(SUMIF('BD Otimix'!A:A,'BD VOLUME'!X56,'BD Otimix'!O:O)+SUMIF('BD Otimix'!A:A,'BD VOLUME'!Y56,'BD Otimix'!O:O)+SUMIF('BD Otimix'!A:A,'BD VOLUME'!Z56,'BD Otimix'!O:O)+SUMIF('BD Otimix'!A:A,'BD VOLUME'!AA56,'BD Otimix'!O:O)+SUMIF('BD Otimix'!A:A,'BD VOLUME'!AB56,'BD Otimix'!O:O)+SUMIF('BD Otimix'!A:A,'BD VOLUME'!AC56,'BD Otimix'!O:O)+SUMIF('BD Otimix'!A:A,'BD VOLUME'!W56,'BD Otimix'!O:O),0) -> 0 | AE56: =IFERROR(F56/$E$3/1000/AD56,0) -> 0 | AF56: =Preencher!$B$3&$U$8&$V$8&A56&$AF$6 -> JARINU-FRG11193MQ.GIROFREEZER | AG56: =Preencher!$B$3&$U$8&$V$8&A56&$AG$6 -> JARINU-FRG11193MQ.GIROFREEZER (1) | AH56: =Preencher!$B$3&$U$8&$V$8&A56&$AH$6 -> JARINU-FRG11193MQ.GIROFREEZER (2) | AI56: =Preencher!$B$3&$U$8&$V$8&A56&$AI$6 -> JARINU-FRG11193MQ.GIROFREEZER REV04 | AJ56: =Preencher!$B$3&$U$8&$V$8&A56&$AJ$6 -> JARINU-FRG11193MQ.GIROFREEZER (3) | AK56: =IFERROR(SUMIF('BD Otimix'!A:A,'BD VOLUME'!AG56,'BD Otimix'!O:O)+SUMIF('BD Otimix'!A:A,'BD VOLUME'!AH56,'BD Otimix'!O:O)+SUMIF('BD Otimix'!A:A,'BD VOLUME'!AI56,'BD Otimix'!O:O)+SUMIF('BD Otimix'!A:A,'BD VOLUME'!AJ56,'BD Otimix'!O:O)+SUMIF('BD Otimix'!A:A,'BD VOLUME'!AF56,'BD Otimix'!O:O),0) -> 0 | AL56: =IFERROR(F56/$E$3/1000/AK56,0) -> 0
A57: 792837 | C57: PALMA FG 25g UP GR A PB | D57: MIUDOS | E57: PE 10 KG | F57: =SUMIF('COLAR PLANO'!$A:$A,A57,'COLAR PLANO'!$D:$D) -> 0 | G57: =IFERROR(F57/($E$3*$C$3),0) -> 0 | H57: 0.023326397 | I57: =IFERROR(G57/$D$7/H57,0) -> 0 | J57: =IFERROR(I57/$B$7,0) -> 0 | K57: 10 | L57: 1 | M57: 10 | N57: =IFERROR(G57/K57,"-") -> 0 | P57: =IFERROR(G57/M57,"-") -> 0 | U57: - | V57: FRG | W57: =Preencher!$B$3&U57&V57&A57&$W$6 -> JARINU-FRG792837MQ.TUNEL DE CG (CONTINUO) | X57: =Preencher!$B$3&U57&V57&A57&$X$6 -> JARINU-FRG792837MQ.TUNEL DE CG (CONTINUO) (1) | Y57: =Preencher!$B$3&U57&V57&A57&$Y$6 -> JARINU-FRG792837MQ.TUNEL DE CG (CONTINUO) (2) | Z57: =Preencher!$B$3&U57&V57&A57&$Z$6 -> JARINU-FRG792837MQ.TUNEL DE CG (CONTINUO) (3) | AA57: =Preencher!$B$3&U57&V57&A57&$AA$6 -> JARINU-FRG792837MQ.TUNEL DE CG (ESTATICO) | AB57: =Preencher!$B$3&U57&V57&A57&$AB$6 -> JARINU-FRG792837MQ.TUNEL DE CG (ESTATICO) (1) | AC57: =Preencher!$B$3&U57&V57&A57&$AC$6 -> JARINU-FRG792837MQ.TUNEL DE CG (ESTATICO) (2) | AD57: =IFERROR(SUMIF('BD Otimix'!A:A,'BD VOLUME'!X57,'BD Otimix'!O:O)+SUMIF('BD Otimix'!A:A,'BD VOLUME'!Y57,'BD Otimix'!O:O)+SUMIF('BD Otimix'!A:A,'BD VOLUME'!Z57,'BD Otimix'!O:O)+SUMIF('BD Otimix'!A:A,'BD VOLUME'!AA57,'BD Otimix'!O:O)+SUMIF('BD Otimix'!A:A,'BD VOLUME'!AB57,'BD Otimix'!O:O)+SUMIF('BD Otimix'!A:A,'BD VOLUME'!AC57,'BD Otimix'!O:O)+SUMIF('BD Otimix'!A:A,'BD VOLUME'!W57,'BD Otimix'!O:O),0) -> 0 | AE57: =IFERROR(F57/$E$3/1000/AD57,0) -> 0 | AF57: =Preencher!$B$3&$U$8&$V$8&A57&$AF$6 -> JARINU-FRG792837MQ.GIROFREEZER | AG57: =Preencher!$B$3&$U$8&$V$8&A57&$AG$6 -> JARINU-FRG792837MQ.GIROFREEZER (1) | AH57: =Preencher!$B$3&$U$8&$V$8&A57&$AH$6 -> JARINU-FRG792837MQ.GIROFREEZER (2) | AI57: =Preencher!$B$3&$U$8&$V$8&A57&$AI$6 -> JARINU-FRG792837MQ.GIROFREEZER REV04 | AJ57: =Preencher!$B$3&$U$8&$V$8&A57&$AJ$6 -> JARINU-FRG792837MQ.GIROFREEZER (3) | AK57: =IFERROR(SUMIF('BD Otimix'!A:A,'BD VOLUME'!AG57,'BD Otimix'!O:O)+SUMIF('BD Otimix'!A:A,'BD VOLUME'!AH57,'BD Otimix'!O:O)+SUMIF('BD Otimix'!A:A,'BD VOLUME'!AI57,'BD Otimix'!O:O)+SUMIF('BD Otimix'!A:A,'BD VOLUME'!AJ57,'BD Otimix'!O:O)+SUMIF('BD Otimix'!A:A,'BD VOLUME'!AF57,'BD Otimix'!O:O),0) -> 0 | AL57: =IFERROR(F57/$E$3/1000/AK57,0) -> 0
A58: 977160 | C58: PALMA FG 25g DOWN GR A PB | D58: MIUDOS | E58: PE 10 KG | F58: =SUMIF('COLAR PLANO'!$A:$A,A58,'COLAR PLANO'!$D:$D) -> 0 | G58: =IFERROR(F58/($E$3*$C$3),0) -> 0 | H58: 0.023326397 | I58: =IFERROR(G58/$D$7/H58,0) -> 0 | J58: =IFERROR(I58/$B$7,0) -> 0 | K58: 10 | L58: 1 | M58: 10 | N58: =IFERROR(G58/K58,"-") -> 0 | P58: =IFERROR(G58/M58,"-") -> 0 | U58: - | V58: FRG | W58: =Preencher!$B$3&U58&V58&A58&$W$6 -> JARINU-FRG977160MQ.TUNEL DE CG (CONTINUO) | X58: =Preencher!$B$3&U58&V58&A58&$X$6 -> JARINU-FRG977160MQ.TUNEL DE CG (CONTINUO) (1) | Y58: =Preencher!$B$3&U58&V58&A58&$Y$6 -> JARINU-FRG977160MQ.TUNEL DE CG (CONTINUO) (2) | Z58: =Preencher!$B$3&U58&V58&A58&$Z$6 -> JARINU-FRG977160MQ.TUNEL DE CG (CONTINUO) (3) | AA58: =Preencher!$B$3&U58&V58&A58&$AA$6 -> JARINU-FRG977160MQ.TUNEL DE CG (ESTATICO) | AB58: =Preencher!$B$3&U58&V58&A58&$AB$6 -> JARINU-FRG977160MQ.TUNEL DE CG (ESTATICO) (1) | AC58: =Preencher!$B$3&U58&V58&A58&$AC$6 -> JARINU-FRG977160MQ.TUNEL DE CG (ESTATICO) (2) | AD58: =IFERROR(SUMIF('BD Otimix'!A:A,'BD VOLUME'!X58,'BD Otimix'!O:O)+SUMIF('BD Otimix'!A:A,'BD VOLUME'!Y58,'BD Otimix'!O:O)+SUMIF('BD Otimix'!A:A,'BD VOLUME'!Z58,'BD Otimix'!O:O)+SUMIF('BD Otimix'!A:A,'BD VOLUME'!AA58,'BD Otimix'!O:O)+SUMIF('BD Otimix'!A:A,'BD VOLUME'!AB58,'BD Otimix'!O:O)+SUMIF('BD Otimix'!A:A,'BD VOLUME'!AC58,'BD Otimix'!O:O)+SUMIF('BD Otimix'!A:A,'BD VOLUME'!W58,'BD Otimix'!O:O),0) -> 0 | AE58: =IFERROR(F58/$E$3/1000/AD58,0) -> 0 | AF58: =Preencher!$B$3&$U$8&$V$8&A58&$AF$6 -> JARINU-FRG977160MQ.GIROFREEZER | AG58: =Preencher!$B$3&$U$8&$V$8&A58&$AG$6 -> JARINU-FRG977160MQ.GIROFREEZER (1) | AH58: =Preencher!$B$3&$U$8&$V$8&A58&$AH$6 -> JARINU-FRG977160MQ.GIROFREEZER (2) | AI58: =Preencher!$B$3&$U$8&$V$8&A58&$AI$6 -> JARINU-FRG977160MQ.GIROFREEZER REV04 | AJ58: =Preencher!$B$3&$U$8&$V$8&A58&$AJ$6 -> JARINU-FRG977160MQ.GIROFREEZER (3) | AK58: =IFERROR(SUMIF('BD Otimix'!A:A,'BD VOLUME'!AG58,'BD Otimix'!O:O)+SUMIF('BD Otimix'!A:A,'BD VOLUME'!AH58,'BD Otimix'!O:O)+SUMIF('BD Otimix'!A:A,'BD VOLUME'!AI58,'BD Otimix'!O:O)+SUMIF('BD Otimix'!A:A,'BD VOLUME'!AJ58,'BD Otimix'!O:O)+SUMIF('BD Otimix'!A:A,'BD VOLUME'!AF58,'BD Otimix'!O:O),0) -> 0 | AL58: =IFERROR(F58/$E$3/1000/AK58,0) -> 0
A59: 977187 | C59: PALMA FG 25g DOWN GR B PB | D59: MIUDOS | E59: PE 10 KG | F59: =SUMIF('COLAR PLANO'!$A:$A,A59,'COLAR PLANO'!$D:$D) -> 0 | G59: =IFERROR(F59/($E$3*$C$3),0) -> 0 | H59: 0.023326397 | I59: =IFERROR(G59/$D$7/H59,0) -> 0 | J59: =IFERROR(I59/$B$7,0) -> 0 | K59: 10 | L59: 1 | M59: 10 | N59: =IFERROR(G59/K59,"-") -> 0 | P59: =IFERROR(G59/M59,"-") -> 0 | U59: - | V59: FRG | W59: =Preencher!$B$3&U59&V59&A59&$W$6 -> JARINU-FRG977187MQ.TUNEL DE CG (CONTINUO) | X59: =Preencher!$B$3&U59&V59&A59&$X$6 -> JARINU-FRG977187MQ.TUNEL DE CG (CONTINUO) (1) | Y59: =Preencher!$B$3&U59&V59&A59&$Y$6 -> JARINU-FRG977187MQ.TUNEL DE CG (CONTINUO) (2) | Z59: =Preencher!$B$3&U59&V59&A59&$Z$6 -> JARINU-FRG977187MQ.TUNEL DE CG (CONTINUO) (3) | AA59: =Preencher!$B$3&U59&V59&A59&$AA$6 -> JARINU-FRG977187MQ.TUNEL DE CG (ESTATICO) | AB59: =Preencher!$B$3&U59&V59&A59&$AB$6 -> JARINU-FRG977187MQ.TUNEL DE CG (ESTATICO) (1) | AC59: =Preencher!$B$3&U59&V59&A59&$AC$6 -> JARINU-FRG977187MQ.TUNEL DE CG (ESTATICO) (2) | AD59: =IFERROR(SUMIF('BD Otimix'!A:A,'BD VOLUME'!X59,'BD Otimix'!O:O)+SUMIF('BD Otimix'!A:A,'BD VOLUME'!Y59,'BD Otimix'!O:O)+SUMIF('BD Otimix'!A:A,'BD VOLUME'!Z59,'BD Otimix'!O:O)+SUMIF('BD Otimix'!A:A,'BD VOLUME'!AA59,'BD Otimix'!O:O)+SUMIF('BD Otimix'!A:A,'BD VOLUME'!AB59,'BD Otimix'!O:O)+SUMIF('BD Otimix'!A:A,'BD VOLUME'!AC59,'BD Otimix'!O:O)+SUMIF('BD Otimix'!A:A,'BD VOLUME'!W59,'BD Otimix'!O:O),0) -> 0 | AE59: =IFERROR(F59/$E$3/1000/AD59,0) -> 0 | AF59: =Preencher!$B$3&$U$8&$V$8&A59&$AF$6 -> JARINU-FRG977187MQ.GIROFREEZER | AG59: =Preencher!$B$3&$U$8&$V$8&A59&$AG$6 -> JARINU-FRG977187MQ.GIROFREEZER (1) | AH59: =Preencher!$B$3&$U$8&$V$8&A59&$AH$6 -> JARINU-FRG977187MQ.GIROFREEZER (2) | AI59: =Preencher!$B$3&$U$8&$V$8&A59&$AI$6 -> JARINU-FRG977187MQ.GIROFREEZER REV04 | AJ59: =Preencher!$B$3&$U$8&$V$8&A59&$AJ$6 -> JARINU-FRG977187MQ.GIROFREEZER (3) | AK59: =IFERROR(SUMIF('BD Otimix'!A:A,'BD VOLUME'!AG59,'BD Otimix'!O:O)+SUMIF('BD Otimix'!A:A,'BD VOLUME'!AH59,'BD Otimix'!O:O)+SUMIF('BD Otimix'!A:A,'BD VOLUME'!AI59,'BD Otimix'!O:O)+SUMIF('BD Otimix'!A:A,'BD VOLUME'!AJ59,'BD Otimix'!O:O)+SUMIF('BD Otimix'!A:A,'BD VOLUME'!AF59,'BD Otimix'!O:O),0) -> 0 | AL59: =IFERROR(F59/$E$3/1000/AK59,0) -> 0
A60: 977721 | C60: PALMA FG 25g UP GR B PB | D60: MIUDOS | E60: PE 10 KG | F60: =SUMIF('COLAR PLANO'!$A:$A,A60,'COLAR PLANO'!$D:$D) -> 0 | G60: =IFERROR(F60/($E$3*$C$3),0) -> 0 | H60: 0.023326397 | I60: =IFERROR(G60/$D$7/H60,0) -> 0 | J60: =IFERROR(I60/$B$7,0) -> 0 | K60: 10 | L60: 1 | M60: 10 | N60: =IFERROR(G60/K60,"-") -> 0 | P60: =IFERROR(G60/M60,"-") -> 0 | U60: - | V60: FRG | W60: =Preencher!$B$3&U60&V60&A60&$W$6 -> JARINU-FRG977721MQ.TUNEL DE CG (CONTINUO) | X60: =Preencher!$B$3&U60&V60&A60&$X$6 -> JARINU-FRG977721MQ.TUNEL DE CG (CONTINUO) (1) | Y60: =Preencher!$B$3&U60&V60&A60&$Y$6 -> JARINU-FRG977721MQ.TUNEL DE CG (CONTINUO) (2) | Z60: =Preencher!$B$3&U60&V60&A60&$Z$6 -> JARINU-FRG977721MQ.TUNEL DE CG (CONTINUO) (3) | AA60: =Preencher!$B$3&U60&V60&A60&$AA$6 -> JARINU-FRG977721MQ.TUNEL DE CG (ESTATICO) | AB60: =Preencher!$B$3&U60&V60&A60&$AB$6 -> JARINU-FRG977721MQ.TUNEL DE CG (ESTATICO) (1) | AC60: =Preencher!$B$3&U60&V60&A60&$AC$6 -> JARINU-FRG977721MQ.TUNEL DE CG (ESTATICO) (2) | AD60: =IFERROR(SUMIF('BD Otimix'!A:A,'BD VOLUME'!X60,'BD Otimix'!O:O)+SUMIF('BD Otimix'!A:A,'BD VOLUME'!Y60,'BD Otimix'!O:O)+SUMIF('BD Otimix'!A:A,'BD VOLUME'!Z60,'BD Otimix'!O:O)+SUMIF('BD Otimix'!A:A,'BD VOLUME'!AA60,'BD Otimix'!O:O)+SUMIF('BD Otimix'!A:A,'BD VOLUME'!AB60,'BD Otimix'!O:O)+SUMIF('BD Otimix'!A:A,'BD VOLUME'!AC60,'BD Otimix'!O:O)+SUMIF('BD Otimix'!A:A,'BD VOLUME'!W60,'BD Otimix'!O:O),0) -> 0 | AE60: =IFERROR(F60/$E$3/1000/AD60,0) -> 0 | AF60: =Preencher!$B$3&$U$8&$V$8&A60&$AF$6 -> JARINU-FRG977721MQ.GIROFREEZER | AG60: =Preencher!$B$3&$U$8&$V$8&A60&$AG$6 -> JARINU-FRG977721MQ.GIROFREEZER (1) | AH60: =Preencher!$B$3&$U$8&$V$8&A60&$AH$6 -> JARINU-FRG977721MQ.GIROFREEZER (2) | AI60: =Preencher!$B$3&$U$8&$V$8&A60&$AI$6 -> JARINU-FRG977721MQ.GIROFREEZER REV04 | AJ60: =Preencher!$B$3&$U$8&$V$8&A60&$AJ$6 -> JARINU-FRG977721MQ.GIROFREEZER (3) | AK60: =IFERROR(SUMIF('BD Otimix'!A:A,'BD VOLUME'!AG60,'BD Otimix'!O:O)+SUMIF('BD Otimix'!A:A,'BD VOLUME'!AH60,'BD Otimix'!O:O)+SUMIF('BD Otimix'!A:A,'BD VOLUME'!AI60,'BD Otimix'!O:O)+SUMIF('BD Otimix'!A:A,'BD VOLUME'!AJ60,'BD Otimix'!O:O)+SUMIF('BD Otimix'!A:A,'BD VOLUME'!AF60,'BD Otimix'!O:O),0) -> 0 | AL60: =IFERROR(F60/$E$3/1000/AK60,0) -> 0
A61: 51292 | B61: P-07 | C61: PES FRANGO B CG PB | D61: MIUDOS | E61: PE 10 KG | F61: =SUMIF('COLAR PLANO'!$A:$A,A61,'COLAR PLANO'!$D:$D) -> 0 | G61: =IFERROR(F61/($E$3*$C$3),0) -> 0 | H61: 0.03453 | I61: =IFERROR(G61/$D$7/H61,0) -> 0 | J61: =IFERROR(I61/$B$7,0) -> 0 | K61: 10 | L61: 1 | M61: 10 | N61: =IFERROR(G61/K61,"-") -> 0 | P61: =IFERROR(G61/M61,"-") -> 0 | U61: - | V61: FRG | W61: =Preencher!$B$3&U61&V61&A61&$W$6 -> JARINU-FRG51292MQ.TUNEL DE CG (CONTINUO) | X61: =Preencher!$B$3&U61&V61&A61&$X$6 -> JARINU-FRG51292MQ.TUNEL DE CG (CONTINUO) (1) | Y61: =Preencher!$B$3&U61&V61&A61&$Y$6 -> JARINU-FRG51292MQ.TUNEL DE CG (CONTINUO) (2) | Z61: =Preencher!$B$3&U61&V61&A61&$Z$6 -> JARINU-FRG51292MQ.TUNEL DE CG (CONTINUO) (3) | AA61: =Preencher!$B$3&U61&V61&A61&$AA$6 -> JARINU-FRG51292MQ.TUNEL DE CG (ESTATICO) | AB61: =Preencher!$B$3&U61&V61&A61&$AB$6 -> JARINU-FRG51292MQ.TUNEL DE CG (ESTATICO) (1) | AC61: =Preencher!$B$3&U61&V61&A61&$AC$6 -> JARINU-FRG51292MQ.TUNEL DE CG (ESTATICO) (2) | AD61: =IFERROR(SUMIF('BD Otimix'!A:A,'BD VOLUME'!X61,'BD Otimix'!O:O)+SUMIF('BD Otimix'!A:A,'BD VOLUME'!Y61,'BD Otimix'!O:O)+SUMIF('BD Otimix'!A:A,'BD VOLUME'!Z61,'BD Otimix'!O:O)+SUMIF('BD Otimix'!A:A,'BD VOLUME'!AA61,'BD Otimix'!O:O)+SUMIF('BD Otimix'!A:A,'BD VOLUME'!AB61,'BD Otimix'!O:O)+SUMIF('BD Otimix'!A:A,'BD VOLUME'!AC61,'BD Otimix'!O:O)+SUMIF('BD Otimix'!A:A,'BD VOLUME'!W61,'BD Otimix'!O:O),0) -> 0 | AE61: =IFERROR(F61/$E$3/1000/AD61,0) -> 0 | AF61: =Preencher!$B$3&$U$8&$V$8&A61&$AF$6 -> JARINU-FRG51292MQ.GIROFREEZER | AG61: =Preencher!$B$3&$U$8&$V$8&A61&$AG$6 -> JARINU-FRG51292MQ.GIROFREEZER (1) | AH61: =Preencher!$B$3&$U$8&$V$8&A61&$AH$6 -> JARINU-FRG51292MQ.GIROFREEZER (2) | AI61: =Preencher!$B$3&$U$8&$V$8&A61&$AI$6 -> JARINU-FRG51292MQ.GIROFREEZER REV04 | AJ61: =Preencher!$B$3&$U$8&$V$8&A61&$AJ$6 -> JARINU-FRG51292MQ.GIROFREEZER (3) | AK61: =IFERROR(SUMIF('BD Otimix'!A:A,'BD VOLUME'!AG61,'BD Otimix'!O:O)+SUMIF('BD Otimix'!A:A,'BD VOLUME'!AH61,'BD Otimix'!O:O)+SUMIF('BD Otimix'!A:A,'BD VOLUME'!AI61,'BD Otimix'!O:O)+SUMIF('BD Otimix'!A:A,'BD VOLUME'!AJ61,'BD Otimix'!O:O)+SUMIF('BD Otimix'!A:A,'BD VOLUME'!AF61,'BD Otimix'!O:O),0) -> 0 | AL61: =IFERROR(F61/$E$3/1000/AK61,0) -> 0
A62: 727571 | B62: HOB-01 | C62: CANELA FG PB | D62: MIUDOS | E62: PE 13 KG | F62: =SUMIF('COLAR PLANO'!$A:$A,A62,'COLAR PLANO'!$D:$D) -> 0 | G62: =IFERROR(F62/($E$3*$C$3),0) -> 0 | H62: 0.035 | I62: =IFERROR(G62/$D$7/H62,0) -> 0 | J62: =IFERROR(I62/$B$7,0) -> 0 | K62: 15 | L62: 1 | M62: 15 | N62: =IFERROR(G62/K62,"-") -> 0 | P62: =IFERROR(G62/M62,"-") -> 0 | U62: - | V62: FRG | W62: =Preencher!$B$3&U62&V62&A62&$W$6 -> JARINU-FRG727571MQ.TUNEL DE CG (CONTINUO) | X62: =Preencher!$B$3&U62&V62&A62&$X$6 -> JARINU-FRG727571MQ.TUNEL DE CG (CONTINUO) (1) | Y62: =Preencher!$B$3&U62&V62&A62&$Y$6 -> JARINU-FRG727571MQ.TUNEL DE CG (CONTINUO) (2) | Z62: =Preencher!$B$3&U62&V62&A62&$Z$6 -> JARINU-FRG727571MQ.TUNEL DE CG (CONTINUO) (3) | AA62: =Preencher!$B$3&U62&V62&A62&$AA$6 -> JARINU-FRG727571MQ.TUNEL DE CG (ESTATICO) | AB62: =Preencher!$B$3&U62&V62&A62&$AB$6 -> JARINU-FRG727571MQ.TUNEL DE CG (ESTATICO) (1) | AC62: =Preencher!$B$3&U62&V62&A62&$AC$6 -> JARINU-FRG727571MQ.TUNEL DE CG (ESTATICO) (2) | AD62: =IFERROR(SUMIF('BD Otimix'!A:A,'BD VOLUME'!X62,'BD Otimix'!O:O)+SUMIF('BD Otimix'!A:A,'BD VOLUME'!Y62,'BD Otimix'!O:O)+SUMIF('BD Otimix'!A:A,'BD VOLUME'!Z62,'BD Otimix'!O:O)+SUMIF('BD Otimix'!A:A,'BD VOLUME'!AA62,'BD Otimix'!O:O)+SUMIF('BD Otimix'!A:A,'BD VOLUME'!AB62,'BD Otimix'!O:O)+SUMIF('BD Otimix'!A:A,'BD VOLUME'!AC62,'BD Otimix'!O:O)+SUMIF('BD Otimix'!A:A,'BD VOLUME'!W62,'BD Otimix'!O:O),0) -> 0 | AE62: =IFERROR(F62/$E$3/1000/AD62,0) -> 0 | AF62: =Preencher!$B$3&$U$8&$V$8&A62&$AF$6 -> JARINU-FRG727571MQ.GIROFREEZER | AG62: =Preencher!$B$3&$U$8&$V$8&A62&$AG$6 -> JARINU-FRG727571MQ.GIROFREEZER (1) | AH62: =Preencher!$B$3&$U$8&$V$8&A62&$AH$6 -> JARINU-FRG727571MQ.GIROFREEZER (2) | AI62: =Preencher!$B$3&$U$8&$V$8&A62&$AI$6 -> JARINU-FRG727571MQ.GIROFREEZER REV04 | AJ62: =Preencher!$B$3&$U$8&$V$8&A62&$AJ$6 -> JARINU-FRG727571MQ.GIROFREEZER (3) | AK62: =IFERROR(SUMIF('BD Otimix'!A:A,'BD VOLUME'!AG62,'BD Otimix'!O:O)+SUMIF('BD Otimix'!A:A,'BD VOLUME'!AH62,'BD Otimix'!O:O)+SUMIF('BD Otimix'!A:A,'BD VOLUME'!AI62,'BD Otimix'!O:O)+SUMIF('BD Otimix'!A:A,'BD VOLUME'!AJ62,'BD Otimix'!O:O)+SUMIF('BD Otimix'!A:A,'BD VOLUME'!AF62,'BD Otimix'!O:O),0) -> 0 | AL62: =IFERROR(F62/$E$3/1000/AK62,0) -> 0
U63: - | V63: FRG | W63: =Preencher!$B$3&U63&V63&A63&$W$6 -> JARINU-FRGMQ.TUNEL DE CG (CONTINUO) | X63: =Preencher!$B$3&U63&V63&A63&$X$6 -> JARINU-FRGMQ.TUNEL DE CG (CONTINUO) (1) | Y63: =Preencher!$B$3&U63&V63&A63&$Y$6 -> JARINU-FRGMQ.TUNEL DE CG (CONTINUO) (2) | Z63: =Preencher!$B$3&U63&V63&A63&$Z$6 -> JARINU-FRGMQ.TUNEL DE CG (CONTINUO) (3) | AA63: =Preencher!$B$3&U63&V63&A63&$AA$6 -> JARINU-FRGMQ.TUNEL DE CG (ESTATICO) | AB63: =Preencher!$B$3&U63&V63&A63&$AB$6 -> JARINU-FRGMQ.TUNEL DE CG (ESTATICO) (1) | AC63: =Preencher!$B$3&U63&V63&A63&$AC$6 -> JARINU-FRGMQ.TUNEL DE CG (ESTATICO) (2) | AD63: =IFERROR(SUMIF('BD Otimix'!A:A,'BD VOLUME'!X63,'BD Otimix'!O:O)+SUMIF('BD Otimix'!A:A,'BD VOLUME'!Y63,'BD Otimix'!O:O)+SUMIF('BD Otimix'!A:A,'BD VOLUME'!Z63,'BD Otimix'!O:O)+SUMIF('BD Otimix'!A:A,'BD VOLUME'!AA63,'BD Otimix'!O:O)+SUMIF('BD Otimix'!A:A,'BD VOLUME'!AB63,'BD Otimix'!O:O)+SUMIF('BD Otimix'!A:A,'BD VOLUME'!AC63,'BD Otimix'!O:O)+SUMIF('BD Otimix'!A:A,'BD VOLUME'!W63,'BD Otimix'!O:O),0) -> 0 | AE63: =IFERROR(F63/$E$3/1000/AD63,0) -> 0 | AF63: =Preencher!$B$3&$U$8&$V$8&A63&$AF$6 -> JARINU-FRGMQ.GIROFREEZER | AG63: =Preencher!$B$3&$U$8&$V$8&A63&$AG$6 -> JARINU-FRGMQ.GIROFREEZER (1) | AH63: =Preencher!$B$3&$U$8&$V$8&A63&$AH$6 -> JARINU-FRGMQ.GIROFREEZER (2) | AI63: =Preencher!$B$3&$U$8&$V$8&A63&$AI$6 -> JARINU-FRGMQ.GIROFREEZER REV04 | AJ63: =Preencher!$B$3&$U$8&$V$8&A63&$AJ$6 -> JARINU-FRGMQ.GIROFREEZER (3) | AK63: =IFERROR(SUMIF('BD Otimix'!A:A,'BD VOLUME'!AG63,'BD Otimix'!O:O)+SUMIF('BD Otimix'!A:A,'BD VOLUME'!AH63,'BD Otimix'!O:O)+SUMIF('BD Otimix'!A:A,'BD VOLUME'!AI63,'BD Otimix'!O:O)+SUMIF('BD Otimix'!A:A,'BD VOLUME'!AJ63,'BD Otimix'!O:O)+SUMIF('BD Otimix'!A:A,'BD VOLUME'!AF63,'BD Otimix'!O:O),0) -> 0 | AL63: =IFERROR(F63/$E$3/1000/AK63,0) -> 0
A65: INTEIROS PESADO | B65: =B3 -> 4699.7389 | I65: =SUBTOTAL(9,I66:I143) -> 0 | J65: =SUBTOTAL(9,J66:J143) -> 0
A66: 963232 | C66: CARC C/GORD C/P PESC S/PESC C/SAMB | D66: INTEIROS | E66: BROILER MI | F66: =SUMIF('COLAR PLANO'!$A:$A,A66,'COLAR PLANO'!$D:$D) -> 0 | G66: =IFERROR(F66/($E$3*$C$3),0) -> 0 | H66: 0.7895 | I66: =IFERROR(G66/$D$3/H66,0) -> 0 | J66: =IFERROR(I66/$B$65,0) -> 0 | K66: 2.125 | L66: 8 | M66: 17 | N66: =IFERROR(G66/K66,"-") -> 0 | U66: - | V66: FRG | W66: =Preencher!$B$3&U66&V66&A66&$W$6 -> JARINU-FRG963232MQ.TUNEL DE CG (CONTINUO) | X66: =Preencher!$B$3&U66&V66&A66&$X$6 -> JARINU-FRG963232MQ.TUNEL DE CG (CONTINUO) (1) | Y66: =Preencher!$B$3&U66&V66&A66&$Y$6 -> JARINU-FRG963232MQ.TUNEL DE CG (CONTINUO) (2) | Z66: =Preencher!$B$3&U66&V66&A66&$Z$6 -> JARINU-FRG963232MQ.TUNEL DE CG (CONTINUO) (3) | AA66: =Preencher!$B$3&U66&V66&A66&$AA$6 -> JARINU-FRG963232MQ.TUNEL DE CG (ESTATICO) | AB66: =Preencher!$B$3&U66&V66&A66&$AB$6 -> JARINU-FRG963232MQ.TUNEL DE CG (ESTATICO) (1) | AC66: =Preencher!$B$3&U66&V66&A66&$AC$6 -> JARINU-FRG963232MQ.TUNEL DE CG (ESTATICO) (2) | AD66: =IFERROR(SUMIF('BD Otimix'!A:A,'BD VOLUME'!X66,'BD Otimix'!O:O)+SUMIF('BD Otimix'!A:A,'BD VOLUME'!Y66,'BD Otimix'!O:O)+SUMIF('BD Otimix'!A:A,'BD VOLUME'!Z66,'BD Otimix'!O:O)+SUMIF('BD Otimix'!A:A,'BD VOLUME'!AA66,'BD Otimix'!O:O)+SUMIF('BD Otimix'!A:A,'BD VOLUME'!AB66,'BD Otimix'!O:O)+SUMIF('BD Otimix'!A:A,'BD VOLUME'!AC66,'BD Otimix'!O:O)+SUMIF('BD Otimix'!A:A,'BD VOLUME'!W66,'BD Otimix'!O:O),0) -> 0 | AE66: =IFERROR(F66/$E$3/1000/AD66,0) -> 0 | AF66: =Preencher!$B$3&$U$8&$V$8&A66&$AF$6 -> JARINU-FRG963232MQ.GIROFREEZER | AG66: =Preencher!$B$3&$U$8&$V$8&A66&$AG$6 -> JARINU-FRG963232MQ.GIROFREEZER (1) | AH66: =Preencher!$B$3&$U$8&$V$8&A66&$AH$6 -> JARINU-FRG963232MQ.GIROFREEZER (2) | AI66: =Preencher!$B$3&$U$8&$V$8&A66&$AI$6 -> JARINU-FRG963232MQ.GIROFREEZER REV04 | AJ66: =Preencher!$B$3&$U$8&$V$8&A66&$AJ$6 -> JARINU-FRG963232MQ.GIROFREEZER (3) | AK66: =IFERROR(SUMIF('BD Otimix'!A:A,'BD VOLUME'!AG66,'BD Otimix'!O:O)+SUMIF('BD Otimix'!A:A,'BD VOLUME'!AH66,'BD Otimix'!O:O)+SUMIF('BD Otimix'!A:A,'BD VOLUME'!AI66,'BD Otimix'!O:O)+SUMIF('BD Otimix'!A:A,'BD VOLUME'!AJ66,'BD Otimix'!O:O)+SUMIF('BD Otimix'!A:A,'BD VOLUME'!AF66,'BD Otimix'!O:O),0) -> 0 | AL66: =IFERROR(F66/$E$3/1000/AK66,0) -> 0
A67: 11061 | B67: BRI-04 | C67: CARC C/GORD C/P PESC S/PESC C/SAMB | D67: INTEIROS | E67: BROILER MI | F67: =SUMIF('COLAR PLANO'!$A:$A,A67,'COLAR PLANO'!$D:$D) -> 0 | G67: =IFERROR(F67/($E$3*$C$3),0) -> 0 | H67: 0.7413 | I67: =IFERROR(G67/$D$3/H67,0) -> 0 | J67: =IFERROR(I67/$B$65,0) -> 0 | K67: 2.125 | L67: 8 | M67: 17 | N67: =IFERROR(G67/K67,"-") -> 0 | U67: - | V67: FRG | W67: =Preencher!$B$3&U67&V67&A67&$W$6 -> JARINU-FRG11061MQ.TUNEL DE CG (CONTINUO) | X67: =Preencher!$B$3&U67&V67&A67&$X$6 -> JARINU-FRG11061MQ.TUNEL DE CG (CONTINUO) (1) | Y67: =Preencher!$B$3&U67&V67&A67&$Y$6 -> JARINU-FRG11061MQ.TUNEL DE CG (CONTINUO) (2) | Z67: =Preencher!$B$3&U67&V67&A67&$Z$6 -> JARINU-FRG11061MQ.TUNEL DE CG (CONTINUO) (3) | AA67: =Preencher!$B$3&U67&V67&A67&$AA$6 -> JARINU-FRG11061MQ.TUNEL DE CG (ESTATICO) | AB67: =Preencher!$B$3&U67&V67&A67&$AB$6 -> JARINU-FRG11061MQ.TUNEL DE CG (ESTATICO) (1) | AC67: =Preencher!$B$3&U67&V67&A67&$AC$6 -> JARINU-FRG11061MQ.TUNEL DE CG (ESTATICO) (2) | AD67: =IFERROR(SUMIF('BD Otimix'!A:A,'BD VOLUME'!X67,'BD Otimix'!O:O)+SUMIF('BD Otimix'!A:A,'BD VOLUME'!Y67,'BD Otimix'!O:O)+SUMIF('BD Otimix'!A:A,'BD VOLUME'!Z67,'BD Otimix'!O:O)+SUMIF('BD Otimix'!A:A,'BD VOLUME'!AA67,'BD Otimix'!O:O)+SUMIF('BD Otimix'!A:A,'BD VOLUME'!AB67,'BD Otimix'!O:O)+SUMIF('BD Otimix'!A:A,'BD VOLUME'!AC67,'BD Otimix'!O:O)+SUMIF('BD Otimix'!A:A,'BD VOLUME'!W67,'BD Otimix'!O:O),0) -> 0 | AE67: =IFERROR(F67/$E$3/1000/AD67,0) -> 0 | AF67: =Preencher!$B$3&$U$8&$V$8&A67&$AF$6 -> JARINU-FRG11061MQ.GIROFREEZER | AG67: =Preencher!$B$3&$U$8&$V$8&A67&$AG$6 -> JARINU-FRG11061MQ.GIROFREEZER (1) | AH67: =Preencher!$B$3&$U$8&$V$8&A67&$AH$6 -> JARINU-FRG11061MQ.GIROFREEZER (2) | AI67: =Preencher!$B$3&$U$8&$V$8&A67&$AI$6 -> JARINU-FRG11061MQ.GIROFREEZER REV04 | AJ67: =Preencher!$B$3&$U$8&$V$8&A67&$AJ$6 -> JARINU-FRG11061MQ.GIROFREEZER (3) | AK67: =IFERROR(SUMIF('BD Otimix'!A:A,'BD VOLUME'!AG67,'BD Otimix'!O:O)+SUMIF('BD Otimix'!A:A,'BD VOLUME'!AH67,'BD Otimix'!O:O)+SUMIF('BD Otimix'!A:A,'BD VOLUME'!AI67,'BD Otimix'!O:O)+SUMIF('BD Otimix'!A:A,'BD VOLUME'!AJ67,'BD Otimix'!O:O)+SUMIF('BD Otimix'!A:A,'BD VOLUME'!AF67,'BD Otimix'!O:O),0) -> 0 | AL67: =IFERROR(F67/$E$3/1000/AK67,0) -> 0
A68: 929638 | C68: CARC C/GORD C/P PESC S/PESC C/SAMB | D68: INTEIROS | E68: BROILER MI | F68: =SUMIF('COLAR PLANO'!$A:$A,A68,'COLAR PLANO'!$D:$D) -> 0 | G68: =IFERROR(F68/($E$3*$C$3),0) -> 0 | H68: 0.7813 | I68: =IFERROR(G68/$D$3/H68,0) -> 0 | J68: =IFERROR(I68/$B$65,0) -> 0 | K68: 2.125 | L68: 8 | M68: 17 | N68: =IFERROR(G68/K68,"-") -> 0 | U68: - | V68: FRG | W68: =Preencher!$B$3&U68&V68&A68&$W$6 -> JARINU-FRG929638MQ.TUNEL DE CG (CONTINUO) | X68: =Preencher!$B$3&U68&V68&A68&$X$6 -> JARINU-FRG929638MQ.TUNEL DE CG (CONTINUO) (1) | Y68: =Preencher!$B$3&U68&V68&A68&$Y$6 -> JARINU-FRG929638MQ.TUNEL DE CG (CONTINUO) (2) | Z68: =Preencher!$B$3&U68&V68&A68&$Z$6 -> JARINU-FRG929638MQ.TUNEL DE CG (CONTINUO) (3) | AA68: =Preencher!$B$3&U68&V68&A68&$AA$6 -> JARINU-FRG929638MQ.TUNEL DE CG (ESTATICO) | AB68: =Preencher!$B$3&U68&V68&A68&$AB$6 -> JARINU-FRG929638MQ.TUNEL DE CG (ESTATICO) (1) | AC68: =Preencher!$B$3&U68&V68&A68&$AC$6 -> JARINU-FRG929638MQ.TUNEL DE CG (ESTATICO) (2) | AD68: =IFERROR(SUMIF('BD Otimix'!A:A,'BD VOLUME'!X68,'BD Otimix'!O:O)+SUMIF('BD Otimix'!A:A,'BD VOLUME'!Y68,'BD Otimix'!O:O)+SUMIF('BD Otimix'!A:A,'BD VOLUME'!Z68,'BD Otimix'!O:O)+SUMIF('BD Otimix'!A:A,'BD VOLUME'!AA68,'BD Otimix'!O:O)+SUMIF('BD Otimix'!A:A,'BD VOLUME'!AB68,'BD Otimix'!O:O)+SUMIF('BD Otimix'!A:A,'BD VOLUME'!AC68,'BD Otimix'!O:O)+SUMIF('BD Otimix'!A:A,'BD VOLUME'!W68,'BD Otimix'!O:O),0) -> 0 | AE68: =IFERROR(F68/$E$3/1000/AD68,0) -> 0 | AF68: =Preencher!$B$3&$U$8&$V$8&A68&$AF$6 -> JARINU-FRG929638MQ.GIROFREEZER | AG68: =Preencher!$B$3&$U$8&$V$8&A68&$AG$6 -> JARINU-FRG929638MQ.GIROFREEZER (1) | AH68: =Preencher!$B$3&$U$8&$V$8&A68&$AH$6 -> JARINU-FRG929638MQ.GIROFREEZER (2) | AI68: =Preencher!$B$3&$U$8&$V$8&A68&$AI$6 -> JARINU-FRG929638MQ.GIROFREEZER REV04 | AJ68: =Preencher!$B$3&$U$8&$V$8&A68&$AJ$6 -> JARINU-FRG929638MQ.GIROFREEZER (3) | AK68: =IFERROR(SUMIF('BD Otimix'!A:A,'BD VOLUME'!AG68,'BD Otimix'!O:O)+SUMIF('BD Otimix'!A:A,'BD VOLUME'!AH68,'BD Otimix'!O:O)+SUMIF('BD Otimix'!A:A,'BD VOLUME'!AI68,'BD Otimix'!O:O)+SUMIF('BD Otimix'!A:A,'BD VOLUME'!AJ68,'BD Otimix'!O:O)+SUMIF('BD Otimix'!A:A,'BD VOLUME'!AF68,'BD Otimix'!O:O),0) -> 0 | AL68: =IFERROR(F68/$E$3/1000/AK68,0) -> 0
A69: 928313 | B69: FGO-03 | C69: CARC C/GORD C/P PESC S/PESC C/SAMB | D69: INTEIROS | E69: Frango s/ miudos | F69: =SUMIF('COLAR PLANO'!$A:$A,A69,'COLAR PLANO'!$D:$D) -> 0 | G69: =IFERROR(F69/($E$3*$C$3),0) -> 0 | H69: 0.7799 | I69: =IFERROR(G69/$D$3/H69,0) -> 0 | J69: =IFERROR(I69/$B$65,0) -> 0 | K69: 2.125 | L69: 8 | M69: 17 | N69: =IFERROR(G69/K69,"-") -> 0 | U69: - | V69: FRG | W69: =Preencher!$B$3&U69&V69&A69&$W$6 -> JARINU-FRG928313MQ.TUNEL DE CG (CONTINUO) | X69: =Preencher!$B$3&U69&V69&A69&$X$6 -> JARINU-FRG928313MQ.TUNEL DE CG (CONTINUO) (1) | Y69: =Preencher!$B$3&U69&V69&A69&$Y$6 -> JARINU-FRG928313MQ.TUNEL DE CG (CONTINUO) (2) | Z69: =Preencher!$B$3&U69&V69&A69&$Z$6 -> JARINU-FRG928313MQ.TUNEL DE CG (CONTINUO) (3) | AA69: =Preencher!$B$3&U69&V69&A69&$AA$6 -> JARINU-FRG928313MQ.TUNEL DE CG (ESTATICO) | AB69: =Preencher!$B$3&U69&V69&A69&$AB$6 -> JARINU-FRG928313MQ.TUNEL DE CG (ESTATICO) (1) | AC69: =Preencher!$B$3&U69&V69&A69&$AC$6 -> JARINU-FRG928313MQ.TUNEL DE CG (ESTATICO) (2) | AD69: =IFERROR(SUMIF('BD Otimix'!A:A,'BD VOLUME'!X69,'BD Otimix'!O:O)+SUMIF('BD Otimix'!A:A,'BD VOLUME'!Y69,'BD Otimix'!O:O)+SUMIF('BD Otimix'!A:A,'BD VOLUME'!Z69,'BD Otimix'!O:O)+SUMIF('BD Otimix'!A:A,'BD VOLUME'!AA69,'BD Otimix'!O:O)+SUMIF('BD Otimix'!A:A,'BD VOLUME'!AB69,'BD Otimix'!O:O)+SUMIF('BD Otimix'!A:A,'BD VOLUME'!AC69,'BD Otimix'!O:O)+SUMIF('BD Otimix'!A:A,'BD VOLUME'!W69,'BD Otimix'!O:O),0) -> 0 | AE69: =IFERROR(F69/$E$3/1000/AD69,0) -> 0 | AF69: =Preencher!$B$3&$U$8&$V$8&A69&$AF$6 -> JARINU-FRG928313MQ.GIROFREEZER | AG69: =Preencher!$B$3&$U$8&$V$8&A69&$AG$6 -> JARINU-FRG928313MQ.GIROFREEZER (1) | AH69: =Preencher!$B$3&$U$8&$V$8&A69&$AH$6 -> JARINU-FRG928313MQ.GIROFREEZER (2) | AI69: =Preencher!$B$3&$U$8&$V$8&A69&$AI$6 -> JARINU-FRG928313MQ.GIROFREEZER REV04 | AJ69: =Preencher!$B$3&$U$8&$V$8&A69&$AJ$6 -> JARINU-FRG928313MQ.GIROFREEZER (3) | AK69: =IFERROR(SUMIF('BD Otimix'!A:A,'BD VOLUME'!AG69,'BD Otimix'!O:O)+SUMIF('BD Otimix'!A:A,'BD VOLUME'!AH69,'BD Otimix'!O:O)+SUMIF('BD Otimix'!A:A,'BD VOLUME'!AI69,'BD Otimix'!O:O)+SUMIF('BD Otimix'!A:A,'BD VOLUME'!AJ69,'BD Otimix'!O:O)+SUMIF('BD Otimix'!A:A,'BD VOLUME'!AF69,'BD Otimix'!O:O),0) -> 0 | AL69: =IFERROR(F69/$E$3/1000/AK69,0) -> 0
A70: 213129 | C70: FRANGO RF S/ MIUDOS | D70: INTEIROS | E70: Frango s/ miudos RF | F70: =SUMIF('COLAR PLANO'!$A:$A,A70,'COLAR PLANO'!$D:$D) -> 0 | G70: =IFERROR(F70/($E$3*$C$3),0) -> 0 | H70: 0.7799 | I70: =IFERROR(G70/$D$3/H70,0) -> 0 | J70: =IFERROR(I70/$B$65,0) -> 0 | K70: 2.125 | L70: 8 | M70: 17 | N70: =IFERROR(G70/K70,"-") -> 0 | P70: =IFERROR(G70/M70,"-") -> 0 | U70: - | V70: FRG | W70: =Preencher!$B$3&U70&V70&A70&$W$6 -> JARINU-FRG213129MQ.TUNEL DE CG (CONTINUO) | X70: =Preencher!$B$3&U70&V70&A70&$X$6 -> JARINU-FRG213129MQ.TUNEL DE CG (CONTINUO) (1) | Y70: =Preencher!$B$3&U70&V70&A70&$Y$6 -> JARINU-FRG213129MQ.TUNEL DE CG (CONTINUO) (2) | Z70: =Preencher!$B$3&U70&V70&A70&$Z$6 -> JARINU-FRG213129MQ.TUNEL DE CG (CONTINUO) (3) | AA70: =Preencher!$B$3&U70&V70&A70&$AA$6 -> JARINU-FRG213129MQ.TUNEL DE CG (ESTATICO) | AB70: =Preencher!$B$3&U70&V70&A70&$AB$6 -> JARINU-FRG213129MQ.TUNEL DE CG (ESTATICO) (1) | AC70: =Preencher!$B$3&U70&V70&A70&$AC$6 -> JARINU-FRG213129MQ.TUNEL DE CG (ESTATICO) (2) | AD70: =IFERROR(SUMIF('BD Otimix'!A:A,'BD VOLUME'!X70,'BD Otimix'!O:O)+SUMIF('BD Otimix'!A:A,'BD VOLUME'!Y70,'BD Otimix'!O:O)+SUMIF('BD Otimix'!A:A,'BD VOLUME'!Z70,'BD Otimix'!O:O)+SUMIF('BD Otimix'!A:A,'BD VOLUME'!AA70,'BD Otimix'!O:O)+SUMIF('BD Otimix'!A:A,'BD VOLUME'!AB70,'BD Otimix'!O:O)+SUMIF('BD Otimix'!A:A,'BD VOLUME'!AC70,'BD Otimix'!O:O)+SUMIF('BD Otimix'!A:A,'BD VOLUME'!W70,'BD Otimix'!O:O),0) -> 0 | AE70: =IFERROR(F70/$E$3/1000/AD70,0) -> 0 | AF70: =Preencher!$B$3&$U$8&$V$8&A70&$AF$6 -> JARINU-FRG213129MQ.GIROFREEZER | AG70: =Preencher!$B$3&$U$8&$V$8&A70&$AG$6 -> JARINU-FRG213129MQ.GIROFREEZER (1) | AH70: =Preencher!$B$3&$U$8&$V$8&A70&$AH$6 -> JARINU-FRG213129MQ.GIROFREEZER (2) | AI70: =Preencher!$B$3&$U$8&$V$8&A70&$AI$6 -> JARINU-FRG213129MQ.GIROFREEZER REV04 | AJ70: =Preencher!$B$3&$U$8&$V$8&A70&$AJ$6 -> JARINU-FRG213129MQ.GIROFREEZER (3) | AK70: =IFERROR(SUMIF('BD Otimix'!A:A,'BD VOLUME'!AG70,'BD Otimix'!O:O)+SUMIF('BD Otimix'!A:A,'BD VOLUME'!AH70,'BD Otimix'!O:O)+SUMIF('BD Otimix'!A:A,'BD VOLUME'!AI70,'BD Otimix'!O:O)+SUMIF('BD Otimix'!A:A,'BD VOLUME'!AJ70,'BD Otimix'!O:O)+SUMIF('BD Otimix'!A:A,'BD VOLUME'!AF70,'BD Otimix'!O:O),0) -> 0 | AL70: =IFERROR(F70/$E$3/1000/AK70,0) -> 0
A71: 952846 | C71: CARC C/GORD C/P PESC S/PESC C/SAMB | D71: INTEIROS | E71: BROILER MI | F71: =SUMIF('COLAR PLANO'!$A:$A,A71,'COLAR PLANO'!$D:$D) -> 0 | G71: =IFERROR(F71/($E$3*$C$3),0) -> 0 | H71: 0.7817 | I71: =IFERROR(G71/$D$3/H71,0) -> 0 | J71: =IFERROR(I71/$B$65,0) -> 0 | K71: 2.125 | L71: 8 | M71: 17 | N71: =IFERROR(G71/K71,"-") -> 0 | P71: =IFERROR(G71/M71,"-") -> 0 | U71: - | V71: FRG | W71: =Preencher!$B$3&U71&V71&A71&$W$6 -> JARINU-FRG952846MQ.TUNEL DE CG (CONTINUO) | X71: =Preencher!$B$3&U71&V71&A71&$X$6 -> JARINU-FRG952846MQ.TUNEL DE CG (CONTINUO) (1) | Y71: =Preencher!$B$3&U71&V71&A71&$Y$6 -> JARINU-FRG952846MQ.TUNEL DE CG (CONTINUO) (2) | Z71: =Preencher!$B$3&U71&V71&A71&$Z$6 -> JARINU-FRG952846MQ.TUNEL DE CG (CONTINUO) (3) | AA71: =Preencher!$B$3&U71&V71&A71&$AA$6 -> JARINU-FRG952846MQ.TUNEL DE CG (ESTATICO) | AB71: =Preencher!$B$3&U71&V71&A71&$AB$6 -> JARINU-FRG952846MQ.TUNEL DE CG (ESTATICO) (1) | AC71: =Preencher!$B$3&U71&V71&A71&$AC$6 -> JARINU-FRG952846MQ.TUNEL DE CG (ESTATICO) (2) | AD71: =IFERROR(SUMIF('BD Otimix'!A:A,'BD VOLUME'!X71,'BD Otimix'!O:O)+SUMIF('BD Otimix'!A:A,'BD VOLUME'!Y71,'BD Otimix'!O:O)+SUMIF('BD Otimix'!A:A,'BD VOLUME'!Z71,'BD Otimix'!O:O)+SUMIF('BD Otimix'!A:A,'BD VOLUME'!AA71,'BD Otimix'!O:O)+SUMIF('BD Otimix'!A:A,'BD VOLUME'!AB71,'BD Otimix'!O:O)+SUMIF('BD Otimix'!A:A,'BD VOLUME'!AC71,'BD Otimix'!O:O)+SUMIF('BD Otimix'!A:A,'BD VOLUME'!W71,'BD Otimix'!O:O),0) -> 0 | AE71: =IFERROR(F71/$E$3/1000/AD71,0) -> 0 | AF71: =Preencher!$B$3&$U$8&$V$8&A71&$AF$6 -> JARINU-FRG952846MQ.GIROFREEZER | AG71: =Preencher!$B$3&$U$8&$V$8&A71&$AG$6 -> JARINU-FRG952846MQ.GIROFREEZER (1) | AH71: =Preencher!$B$3&$U$8&$V$8&A71&$AH$6 -> JARINU-FRG952846MQ.GIROFREEZER (2) | AI71: =Preencher!$B$3&$U$8&$V$8&A71&$AI$6 -> JARINU-FRG952846MQ.GIROFREEZER REV04 | AJ71: =Preencher!$B$3&$U$8&$V$8&A71&$AJ$6 -> JARINU-FRG952846MQ.GIROFREEZER (3) | AK71: =IFERROR(SUMIF('BD Otimix'!A:A,'BD VOLUME'!AG71,'BD Otimix'!O:O)+SUMIF('BD Otimix'!A:A,'BD VOLUME'!AH71,'BD Otimix'!O:O)+SUMIF('BD Otimix'!A:A,'BD VOLUME'!AI71,'BD Otimix'!O:O)+SUMIF('BD Otimix'!A:A,'BD VOLUME'!AJ71,'BD Otimix'!O:O)+SUMIF('BD Otimix'!A:A,'BD VOLUME'!AF71,'BD Otimix'!O:O),0) -> 0 | AL71: =IFERROR(F71/$E$3/1000/AK71,0) -> 0
A72: 953320 | C72: CARC C/GORD C/P PESC S/PESC C/SAMB | D72: INTEIROS | E72: BROILER MI | F72: =SUMIF('COLAR PLANO'!$A:$A,A72,'COLAR PLANO'!$D:$D) -> 0 | G72: =IFERROR(F72/($E$3*$C$3),0) -> 0 | H72: 0.7817 | I72: =IFERROR(G72/$D$3/H72,0) -> 0 | J72: =IFERROR(I72/$B$65,0) -> 0 | K72: 2.125 | L72: 8 | M72: 17 | N72: =IFERROR(G72/K72,"-") -> 0 | P72: =IFERROR(G72/M72,"-") -> 0 | U72: - | V72: FRG | W72: =Preencher!$B$3&U72&V72&A72&$W$6 -> JARINU-FRG953320MQ.TUNEL DE CG (CONTINUO) | X72: =Preencher!$B$3&U72&V72&A72&$X$6 -> JARINU-FRG953320MQ.TUNEL DE CG (CONTINUO) (1) | Y72: =Preencher!$B$3&U72&V72&A72&$Y$6 -> JARINU-FRG953320MQ.TUNEL DE CG (CONTINUO) (2) | Z72: =Preencher!$B$3&U72&V72&A72&$Z$6 -> JARINU-FRG953320MQ.TUNEL DE CG (CONTINUO) (3) | AA72: =Preencher!$B$3&U72&V72&A72&$AA$6 -> JARINU-FRG953320MQ.TUNEL DE CG (ESTATICO) | AB72: =Preencher!$B$3&U72&V72&A72&$AB$6 -> JARINU-FRG953320MQ.TUNEL DE CG (ESTATICO) (1) | AC72: =Preencher!$B$3&U72&V72&A72&$AC$6 -> JARINU-FRG953320MQ.TUNEL DE CG (ESTATICO) (2) | AD72: =IFERROR(SUMIF('BD Otimix'!A:A,'BD VOLUME'!X72,'BD Otimix'!O:O)+SUMIF('BD Otimix'!A:A,'BD VOLUME'!Y72,'BD Otimix'!O:O)+SUMIF('BD Otimix'!A:A,'BD VOLUME'!Z72,'BD Otimix'!O:O)+SUMIF('BD Otimix'!A:A,'BD VOLUME'!AA72,'BD Otimix'!O:O)+SUMIF('BD Otimix'!A:A,'BD VOLUME'!AB72,'BD Otimix'!O:O)+SUMIF('BD Otimix'!A:A,'BD VOLUME'!AC72,'BD Otimix'!O:O)+SUMIF('BD Otimix'!A:A,'BD VOLUME'!W72,'BD Otimix'!O:O),0) -> 0 | AE72: =IFERROR(F72/$E$3/1000/AD72,0) -> 0 | AF72: =Preencher!$B$3&$U$8&$V$8&A72&$AF$6 -> JARINU-FRG953320MQ.GIROFREEZER | AG72: =Preencher!$B$3&$U$8&$V$8&A72&$AG$6 -> JARINU-FRG953320MQ.GIROFREEZER (1) | AH72: =Preencher!$B$3&$U$8&$V$8&A72&$AH$6 -> JARINU-FRG953320MQ.GIROFREEZER (2) | AI72: =Preencher!$B$3&$U$8&$V$8&A72&$AI$6 -> JARINU-FRG953320MQ.GIROFREEZER REV04 | AJ72: =Preencher!$B$3&$U$8&$V$8&A72&$AJ$6 -> JARINU-FRG953320MQ.GIROFREEZER (3) | AK72: =IFERROR(SUMIF('BD Otimix'!A:A,'BD VOLUME'!AG72,'BD Otimix'!O:O)+SUMIF('BD Otimix'!A:A,'BD VOLUME'!AH72,'BD Otimix'!O:O)+SUMIF('BD Otimix'!A:A,'BD VOLUME'!AI72,'BD Otimix'!O:O)+SUMIF('BD Otimix'!A:A,'BD VOLUME'!AJ72,'BD Otimix'!O:O)+SUMIF('BD Otimix'!A:A,'BD VOLUME'!AF72,'BD Otimix'!O:O),0) -> 0 | AL72: =IFERROR(F72/$E$3/1000/AK72,0) -> 0
A73: 953895 | C73: CARC C/GORD C/P PESC S/PESC C/SAMB | D73: INTEIROS | E73: BROILER MI | F73: =SUMIF('COLAR PLANO'!$A:$A,A73,'COLAR PLANO'!$D:$D) -> 0 | G73: =IFERROR(F73/($E$3*$C$3),0) -> 0 | H73: 0.7817 | I73: =IFERROR(G73/$D$3/H73,0) -> 0 | J73: =IFERROR(I73/$B$65,0) -> 0 | K73: 2.125 | L73: 8 | M73: 17 | N73: =IFERROR(G73/K73,"-") -> 0 | P73: =IFERROR(G73/M73,"-") -> 0 | U73: - | V73: FRG | W73: =Preencher!$B$3&U73&V73&A73&$W$6 -> JARINU-FRG953895MQ.TUNEL DE CG (CONTINUO) | X73: =Preencher!$B$3&U73&V73&A73&$X$6 -> JARINU-FRG953895MQ.TUNEL DE CG (CONTINUO) (1) | Y73: =Preencher!$B$3&U73&V73&A73&$Y$6 -> JARINU-FRG953895MQ.TUNEL DE CG (CONTINUO) (2) | Z73: =Preencher!$B$3&U73&V73&A73&$Z$6 -> JARINU-FRG953895MQ.TUNEL DE CG (CONTINUO) (3) | AA73: =Preencher!$B$3&U73&V73&A73&$AA$6 -> JARINU-FRG953895MQ.TUNEL DE CG (ESTATICO) | AB73: =Preencher!$B$3&U73&V73&A73&$AB$6 -> JARINU-FRG953895MQ.TUNEL DE CG (ESTATICO) (1) | AC73: =Preencher!$B$3&U73&V73&A73&$AC$6 -> JARINU-FRG953895MQ.TUNEL DE CG (ESTATICO) (2) | AD73: =IFERROR(SUMIF('BD Otimix'!A:A,'BD VOLUME'!X73,'BD Otimix'!O:O)+SUMIF('BD Otimix'!A:A,'BD VOLUME'!Y73,'BD Otimix'!O:O)+SUMIF('BD Otimix'!A:A,'BD VOLUME'!Z73,'BD Otimix'!O:O)+SUMIF('BD Otimix'!A:A,'BD VOLUME'!AA73,'BD Otimix'!O:O)+SUMIF('BD Otimix'!A:A,'BD VOLUME'!AB73,'BD Otimix'!O:O)+SUMIF('BD Otimix'!A:A,'BD VOLUME'!AC73,'BD Otimix'!O:O)+SUMIF('BD Otimix'!A:A,'BD VOLUME'!W73,'BD Otimix'!O:O),0) -> 0 | AE73: =IFERROR(F73/$E$3/1000/AD73,0) -> 0 | AF73: =Preencher!$B$3&$U$8&$V$8&A73&$AF$6 -> JARINU-FRG953895MQ.GIROFREEZER | AG73: =Preencher!$B$3&$U$8&$V$8&A73&$AG$6 -> JARINU-FRG953895MQ.GIROFREEZER (1) | AH73: =Preencher!$B$3&$U$8&$V$8&A73&$AH$6 -> JARINU-FRG953895MQ.GIROFREEZER (2) | AI73: =Preencher!$B$3&$U$8&$V$8&A73&$AI$6 -> JARINU-FRG953895MQ.GIROFREEZER REV04 | AJ73: =Preencher!$B$3&$U$8&$V$8&A73&$AJ$6 -> JARINU-FRG953895MQ.GIROFREEZER (3) | AK73: =IFERROR(SUMIF('BD Otimix'!A:A,'BD VOLUME'!AG73,'BD Otimix'!O:O)+SUMIF('BD Otimix'!A:A,'BD VOLUME'!AH73,'BD Otimix'!O:O)+SUMIF('BD Otimix'!A:A,'BD VOLUME'!AI73,'BD Otimix'!O:O)+SUMIF('BD Otimix'!A:A,'BD VOLUME'!AJ73,'BD Otimix'!O:O)+SUMIF('BD Otimix'!A:A,'BD VOLUME'!AF73,'BD Otimix'!O:O),0) -> 0 | AL73: =IFERROR(F73/$E$3/1000/AK73,0) -> 0
A74: 954540 | C74: CARC C/GORD C/P PESC S/PESC C/SAMB | D74: INTEIROS | E74: BROILER MI | F74: =SUMIF('COLAR PLANO'!$A:$A,A74,'COLAR PLANO'!$D:$D) -> 0 | G74: =IFERROR(F74/($E$3*$C$3),0) -> 0 | H74: 0.7817 | I74: =IFERROR(G74/$D$3/H74,0) -> 0 | J74: =IFERROR(I74/$B$65,0) -> 0 | K74: 2.125 | L74: 8 | M74: 17 | N74: =IFERROR(G74/K74,"-") -> 0 | P74: =IFERROR(G74/M74,"-") -> 0 | U74: - | V74: FRG | W74: =Preencher!$B$3&U74&V74&A74&$W$6 -> JARINU-FRG954540MQ.TUNEL DE CG (CONTINUO) | X74: =Preencher!$B$3&U74&V74&A74&$X$6 -> JARINU-FRG954540MQ.TUNEL DE CG (CONTINUO) (1) | Y74: =Preencher!$B$3&U74&V74&A74&$Y$6 -> JARINU-FRG954540MQ.TUNEL DE CG (CONTINUO) (2) | Z74: =Preencher!$B$3&U74&V74&A74&$Z$6 -> JARINU-FRG954540MQ.TUNEL DE CG (CONTINUO) (3) | AA74: =Preencher!$B$3&U74&V74&A74&$AA$6 -> JARINU-FRG954540MQ.TUNEL DE CG (ESTATICO) | AB74: =Preencher!$B$3&U74&V74&A74&$AB$6 -> JARINU-FRG954540MQ.TUNEL DE CG (ESTATICO) (1) | AC74: =Preencher!$B$3&U74&V74&A74&$AC$6 -> JARINU-FRG954540MQ.TUNEL DE CG (ESTATICO) (2) | AD74: =IFERROR(SUMIF('BD Otimix'!A:A,'BD VOLUME'!X74,'BD Otimix'!O:O)+SUMIF('BD Otimix'!A:A,'BD VOLUME'!Y74,'BD Otimix'!O:O)+SUMIF('BD Otimix'!A:A,'BD VOLUME'!Z74,'BD Otimix'!O:O)+SUMIF('BD Otimix'!A:A,'BD VOLUME'!AA74,'BD Otimix'!O:O)+SUMIF('BD Otimix'!A:A,'BD VOLUME'!AB74,'BD Otimix'!O:O)+SUMIF('BD Otimix'!A:A,'BD VOLUME'!AC74,'BD Otimix'!O:O)+SUMIF('BD Otimix'!A:A,'BD VOLUME'!W74,'BD Otimix'!O:O),0) -> 0 | AE74: =IFERROR(F74/$E$3/1000/AD74,0) -> 0 | AF74: =Preencher!$B$3&$U$8&$V$8&A74&$AF$6 -> JARINU-FRG954540MQ.GIROFREEZER | AG74: =Preencher!$B$3&$U$8&$V$8&A74&$AG$6 -> JARINU-FRG954540MQ.GIROFREEZER (1) | AH74: =Preencher!$B$3&$U$8&$V$8&A74&$AH$6 -> JARINU-FRG954540MQ.GIROFREEZER (2) | AI74: =Preencher!$B$3&$U$8&$V$8&A74&$AI$6 -> JARINU-FRG954540MQ.GIROFREEZER REV04 | AJ74: =Preencher!$B$3&$U$8&$V$8&A74&$AJ$6 -> JARINU-FRG954540MQ.GIROFREEZER (3) | AK74: =IFERROR(SUMIF('BD Otimix'!A:A,'BD VOLUME'!AG74,'BD Otimix'!O:O)+SUMIF('BD Otimix'!A:A,'BD VOLUME'!AH74,'BD Otimix'!O:O)+SUMIF('BD Otimix'!A:A,'BD VOLUME'!AI74,'BD Otimix'!O:O)+SUMIF('BD Otimix'!A:A,'BD VOLUME'!AJ74,'BD Otimix'!O:O)+SUMIF('BD Otimix'!A:A,'BD VOLUME'!AF74,'BD Otimix'!O:O),0) -> 0 | AL74: =IFERROR(F74/$E$3/1000/AK74,0) -> 0
A75: 954542 | C75: CARC C/GORD C/P PESC S/PESC C/SAMB | D75: INTEIROS | E75: BROILER MI | F75: =SUMIF('COLAR PLANO'!$A:$A,A75,'COLAR PLANO'!$D:$D) -> 0 | G75: =IFERROR(F75/($E$3*$C$3),0) -> 0 | H75: 0.7817 | I75: =IFERROR(G75/$D$3/H75,0) -> 0 | J75: =IFERROR(I75/$B$65,0) -> 0 | K75: 2.125 | L75: 8 | M75: 17 | N75: =IFERROR(G75/K75,"-") -> 0 | P75: =IFERROR(G75/M75,"-") -> 0 | U75: - | V75: FRG | W75: =Preencher!$B$3&U75&V75&A75&$W$6 -> JARINU-FRG954542MQ.TUNEL DE CG (CONTINUO) | X75: =Preencher!$B$3&U75&V75&A75&$X$6 -> JARINU-FRG954542MQ.TUNEL DE CG (CONTINUO) (1) | Y75: =Preencher!$B$3&U75&V75&A75&$Y$6 -> JARINU-FRG954542MQ.TUNEL DE CG (CONTINUO) (2) | Z75: =Preencher!$B$3&U75&V75&A75&$Z$6 -> JARINU-FRG954542MQ.TUNEL DE CG (CONTINUO) (3) | AA75: =Preencher!$B$3&U75&V75&A75&$AA$6 -> JARINU-FRG954542MQ.TUNEL DE CG (ESTATICO) | AB75: =Preencher!$B$3&U75&V75&A75&$AB$6 -> JARINU-FRG954542MQ.TUNEL DE CG (ESTATICO) (1) | AC75: =Preencher!$B$3&U75&V75&A75&$AC$6 -> JARINU-FRG954542MQ.TUNEL DE CG (ESTATICO) (2) | AD75: =IFERROR(SUMIF('BD Otimix'!A:A,'BD VOLUME'!X75,'BD Otimix'!O:O)+SUMIF('BD Otimix'!A:A,'BD VOLUME'!Y75,'BD Otimix'!O:O)+SUMIF('BD Otimix'!A:A,'BD VOLUME'!Z75,'BD Otimix'!O:O)+SUMIF('BD Otimix'!A:A,'BD VOLUME'!AA75,'BD Otimix'!O:O)+SUMIF('BD Otimix'!A:A,'BD VOLUME'!AB75,'BD Otimix'!O:O)+SUMIF('BD Otimix'!A:A,'BD VOLUME'!AC75,'BD Otimix'!O:O)+SUMIF('BD Otimix'!A:A,'BD VOLUME'!W75,'BD Otimix'!O:O),0) -> 0 | AE75: =IFERROR(F75/$E$3/1000/AD75,0) -> 0 | AF75: =Preencher!$B$3&$U$8&$V$8&A75&$AF$6 -> JARINU-FRG954542MQ.GIROFREEZER | AG75: =Preencher!$B$3&$U$8&$V$8&A75&$AG$6 -> JARINU-FRG954542MQ.GIROFREEZER (1) | AH75: =Preencher!$B$3&$U$8&$V$8&A75&$AH$6 -> JARINU-FRG954542MQ.GIROFREEZER (2) | AI75: =Preencher!$B$3&$U$8&$V$8&A75&$AI$6 -> JARINU-FRG954542MQ.GIROFREEZER REV04 | AJ75: =Preencher!$B$3&$U$8&$V$8&A75&$AJ$6 -> JARINU-FRG954542MQ.GIROFREEZER (3) | AK75: =IFERROR(SUMIF('BD Otimix'!A:A,'BD VOLUME'!AG75,'BD Otimix'!O:O)+SUMIF('BD Otimix'!A:A,'BD VOLUME'!AH75,'BD Otimix'!O:O)+SUMIF('BD Otimix'!A:A,'BD VOLUME'!AI75,'BD Otimix'!O:O)+SUMIF('BD Otimix'!A:A,'BD VOLUME'!AJ75,'BD Otimix'!O:O)+SUMIF('BD Otimix'!A:A,'BD VOLUME'!AF75,'BD Otimix'!O:O),0) -> 0 | AL75: =IFERROR(F75/$E$3/1000/AK75,0) -> 0
A76: 984699 | C76: CARC C/GORD C/P PESC S/PESC C/SAMB | D76: INTEIROS | E76: BROILER MI | F76: =SUMIF('COLAR PLANO'!$A:$A,A76,'COLAR PLANO'!$D:$D) -> 0 | G76: =IFERROR(F76/($E$3*$C$3),0) -> 0 | H76: 0.7419 | I76: =IFERROR(G76/$D$3/H76,0) -> 0 | J76: =IFERROR(I76/$B$65,0) -> 0 | K76: 2.125 | L76: 8 | M76: 17 | N76: =IFERROR(G76/K76,"-") -> 0 | P76: =IFERROR(G76/M76,"-") -> 0 | U76: - | V76: FRG | W76: =Preencher!$B$3&U76&V76&A76&$W$6 -> JARINU-FRG984699MQ.TUNEL DE CG (CONTINUO) | X76: =Preencher!$B$3&U76&V76&A76&$X$6 -> JARINU-FRG984699MQ.TUNEL DE CG (CONTINUO) (1) | Y76: =Preencher!$B$3&U76&V76&A76&$Y$6 -> JARINU-FRG984699MQ.TUNEL DE CG (CONTINUO) (2) | Z76: =Preencher!$B$3&U76&V76&A76&$Z$6 -> JARINU-FRG984699MQ.TUNEL DE CG (CONTINUO) (3) | AA76: =Preencher!$B$3&U76&V76&A76&$AA$6 -> JARINU-FRG984699MQ.TUNEL DE CG (ESTATICO) | AB76: =Preencher!$B$3&U76&V76&A76&$AB$6 -> JARINU-FRG984699MQ.TUNEL DE CG (ESTATICO) (1) | AC76: =Preencher!$B$3&U76&V76&A76&$AC$6 -> JARINU-FRG984699MQ.TUNEL DE CG (ESTATICO) (2) | AD76: =IFERROR(SUMIF('BD Otimix'!A:A,'BD VOLUME'!X76,'BD Otimix'!O:O)+SUMIF('BD Otimix'!A:A,'BD VOLUME'!Y76,'BD Otimix'!O:O)+SUMIF('BD Otimix'!A:A,'BD VOLUME'!Z76,'BD Otimix'!O:O)+SUMIF('BD Otimix'!A:A,'BD VOLUME'!AA76,'BD Otimix'!O:O)+SUMIF('BD Otimix'!A:A,'BD VOLUME'!AB76,'BD Otimix'!O:O)+SUMIF('BD Otimix'!A:A,'BD VOLUME'!AC76,'BD Otimix'!O:O)+SUMIF('BD Otimix'!A:A,'BD VOLUME'!W76,'BD Otimix'!O:O),0) -> 0 | AE76: =IFERROR(F76/$E$3/1000/AD76,0) -> 0 | AF76: =Preencher!$B$3&$U$8&$V$8&A76&$AF$6 -> JARINU-FRG984699MQ.GIROFREEZER | AG76: =Preencher!$B$3&$U$8&$V$8&A76&$AG$6 -> JARINU-FRG984699MQ.GIROFREEZER (1) | AH76: =Preencher!$B$3&$U$8&$V$8&A76&$AH$6 -> JARINU-FRG984699MQ.GIROFREEZER (2) | AI76: =Preencher!$B$3&$U$8&$V$8&A76&$AI$6 -> JARINU-FRG984699MQ.GIROFREEZER REV04 | AJ76: =Preencher!$B$3&$U$8&$V$8&A76&$AJ$6 -> JARINU-FRG984699MQ.GIROFREEZER (3) | AK76: =IFERROR(SUMIF('BD Otimix'!A:A,'BD VOLUME'!AG76,'BD Otimix'!O:O)+SUMIF('BD Otimix'!A:A,'BD VOLUME'!AH76,'BD Otimix'!O:O)+SUMIF('BD Otimix'!A:A,'BD VOLUME'!AI76,'BD Otimix'!O:O)+SUMIF('BD Otimix'!A:A,'BD VOLUME'!AJ76,'BD Otimix'!O:O)+SUMIF('BD Otimix'!A:A,'BD VOLUME'!AF76,'BD Otimix'!O:O),0) -> 0 | AL76: =IFERROR(F76/$E$3/1000/AK76,0) -> 0
A77: 13854 | B77: FS-03 | C77: CARC C/GORD C/P PESC S/PESC C/SAMB | D77: INTEIROS | E77: BROILER MI | F77: =SUMIF('COLAR PLANO'!$A:$A,A77,'COLAR PLANO'!$D:$D) -> 0 | G77: =IFERROR(F77/($E$3*$C$3),0) -> 0 | H77: 0.7352 | I77: =IFERROR(G77/$D$3/H77,0) -> 0 | J77: =IFERROR(I77/$B$65,0) -> 0 | K77: 2.125 | L77: 8 | M77: 17 | N77: =IFERROR(G77/K77,"-") -> 0 | P77: =IFERROR(G77/M77,"-") -> 0 | U77: - | V77: FRG | W77: =Preencher!$B$3&U77&V77&A77&$W$6 -> JARINU-FRG13854MQ.TUNEL DE CG (CONTINUO) | X77: =Preencher!$B$3&U77&V77&A77&$X$6 -> JARINU-FRG13854MQ.TUNEL DE CG (CONTINUO) (1) | Y77: =Preencher!$B$3&U77&V77&A77&$Y$6 -> JARINU-FRG13854MQ.TUNEL DE CG (CONTINUO) (2) | Z77: =Preencher!$B$3&U77&V77&A77&$Z$6 -> JARINU-FRG13854MQ.TUNEL DE CG (CONTINUO) (3) | AA77: =Preencher!$B$3&U77&V77&A77&$AA$6 -> JARINU-FRG13854MQ.TUNEL DE CG (ESTATICO) | AB77: =Preencher!$B$3&U77&V77&A77&$AB$6 -> JARINU-FRG13854MQ.TUNEL DE CG (ESTATICO) (1) | AC77: =Preencher!$B$3&U77&V77&A77&$AC$6 -> JARINU-FRG13854MQ.TUNEL DE CG (ESTATICO) (2) | AD77: =IFERROR(SUMIF('BD Otimix'!A:A,'BD VOLUME'!X77,'BD Otimix'!O:O)+SUMIF('BD Otimix'!A:A,'BD VOLUME'!Y77,'BD Otimix'!O:O)+SUMIF('BD Otimix'!A:A,'BD VOLUME'!Z77,'BD Otimix'!O:O)+SUMIF('BD Otimix'!A:A,'BD VOLUME'!AA77,'BD Otimix'!O:O)+SUMIF('BD Otimix'!A:A,'BD VOLUME'!AB77,'BD Otimix'!O:O)+SUMIF('BD Otimix'!A:A,'BD VOLUME'!AC77,'BD Otimix'!O:O)+SUMIF('BD Otimix'!A:A,'BD VOLUME'!W77,'BD Otimix'!O:O),0) -> 0 | AE77: =IFERROR(F77/$E$3/1000/AD77,0) -> 0 | AF77: =Preencher!$B$3&$U$8&$V$8&A77&$AF$6 -> JARINU-FRG13854MQ.GIROFREEZER | AG77: =Preencher!$B$3&$U$8&$V$8&A77&$AG$6 -> JARINU-FRG13854MQ.GIROFREEZER (1) | AH77: =Preencher!$B$3&$U$8&$V$8&A77&$AH$6 -> JARINU-FRG13854MQ.GIROFREEZER (2) | AI77: =Preencher!$B$3&$U$8&$V$8&A77&$AI$6 -> JARINU-FRG13854MQ.GIROFREEZER REV04 | AJ77: =Preencher!$B$3&$U$8&$V$8&A77&$AJ$6 -> JARINU-FRG13854MQ.GIROFREEZER (3) | AK77: =IFERROR(SUMIF('BD Otimix'!A:A,'BD VOLUME'!AG77,'BD Otimix'!O:O)+SUMIF('BD Otimix'!A:A,'BD VOLUME'!AH77,'BD Otimix'!O:O)+SUMIF('BD Otimix'!A:A,'BD VOLUME'!AI77,'BD Otimix'!O:O)+SUMIF('BD Otimix'!A:A,'BD VOLUME'!AJ77,'BD Otimix'!O:O)+SUMIF('BD Otimix'!A:A,'BD VOLUME'!AF77,'BD Otimix'!O:O),0) -> 0 | AL77: =IFERROR(F77/$E$3/1000/AK77,0) -> 0
A78: 950969 | C78: CARC C/GORD C/P PESC S/PESC C/SAMB | D78: INTEIROS | E78: BROILER MI | F78: =SUMIF('COLAR PLANO'!$A:$A,A78,'COLAR PLANO'!$D:$D) -> 0 | G78: =IFERROR(F78/($E$3*$C$3),0) -> 0 | H78: 0.7838 | I78: =IFERROR(G78/$D$3/H78,0) -> 0 | J78: =IFERROR(I78/$B$65,0) -> 0 | K78: 2.125 | L78: 8 | M78: 17 | N78: =IFERROR(G78/K78,"-") -> 0 | P78: =IFERROR(G78/M78,"-") -> 0 | U78: - | V78: FRG | W78: =Preencher!$B$3&U78&V78&A78&$W$6 -> JARINU-FRG950969MQ.TUNEL DE CG (CONTINUO) | X78: =Preencher!$B$3&U78&V78&A78&$X$6 -> JARINU-FRG950969MQ.TUNEL DE CG (CONTINUO) (1) | Y78: =Preencher!$B$3&U78&V78&A78&$Y$6 -> JARINU-FRG950969MQ.TUNEL DE CG (CONTINUO) (2) | Z78: =Preencher!$B$3&U78&V78&A78&$Z$6 -> JARINU-FRG950969MQ.TUNEL DE CG (CONTINUO) (3) | AA78: =Preencher!$B$3&U78&V78&A78&$AA$6 -> JARINU-FRG950969MQ.TUNEL DE CG (ESTATICO) | AB78: =Preencher!$B$3&U78&V78&A78&$AB$6 -> JARINU-FRG950969MQ.TUNEL DE CG (ESTATICO) (1) | AC78: =Preencher!$B$3&U78&V78&A78&$AC$6 -> JARINU-FRG950969MQ.TUNEL DE CG (ESTATICO) (2) | AD78: =IFERROR(SUMIF('BD Otimix'!A:A,'BD VOLUME'!X78,'BD Otimix'!O:O)+SUMIF('BD Otimix'!A:A,'BD VOLUME'!Y78,'BD Otimix'!O:O)+SUMIF('BD Otimix'!A:A,'BD VOLUME'!Z78,'BD Otimix'!O:O)+SUMIF('BD Otimix'!A:A,'BD VOLUME'!AA78,'BD Otimix'!O:O)+SUMIF('BD Otimix'!A:A,'BD VOLUME'!AB78,'BD Otimix'!O:O)+SUMIF('BD Otimix'!A:A,'BD VOLUME'!AC78,'BD Otimix'!O:O)+SUMIF('BD Otimix'!A:A,'BD VOLUME'!W78,'BD Otimix'!O:O),0) -> 0 | AE78: =IFERROR(F78/$E$3/1000/AD78,0) -> 0 | AF78: =Preencher!$B$3&$U$8&$V$8&A78&$AF$6 -> JARINU-FRG950969MQ.GIROFREEZER | AG78: =Preencher!$B$3&$U$8&$V$8&A78&$AG$6 -> JARINU-FRG950969MQ.GIROFREEZER (1) | AH78: =Preencher!$B$3&$U$8&$V$8&A78&$AH$6 -> JARINU-FRG950969MQ.GIROFREEZER (2) | AI78: =Preencher!$B$3&$U$8&$V$8&A78&$AI$6 -> JARINU-FRG950969MQ.GIROFREEZER REV04 | AJ78: =Preencher!$B$3&$U$8&$V$8&A78&$AJ$6 -> JARINU-FRG950969MQ.GIROFREEZER (3) | AK78: =IFERROR(SUMIF('BD Otimix'!A:A,'BD VOLUME'!AG78,'BD Otimix'!O:O)+SUMIF('BD Otimix'!A:A,'BD VOLUME'!AH78,'BD Otimix'!O:O)+SUMIF('BD Otimix'!A:A,'BD VOLUME'!AI78,'BD Otimix'!O:O)+SUMIF('BD Otimix'!A:A,'BD VOLUME'!AJ78,'BD Otimix'!O:O)+SUMIF('BD Otimix'!A:A,'BD VOLUME'!AF78,'BD Otimix'!O:O),0) -> 0 | AL78: =IFERROR(F78/$E$3/1000/AK78,0) -> 0
A79: 11029 | C79: CARC C/GORD C/P PESC S/PESC C/SAMB | D79: INTEIROS | E79: BROILER MI | F79: =SUMIF('COLAR PLANO'!$A:$A,A79,'COLAR PLANO'!$D:$D) -> 0 | G79: =IFERROR(F79/($E$3*$C$3),0) -> 0 | H79: 0.7868 | I79: =IFERROR(G79/$D$3/H79,0) -> 0 | J79: =IFERROR(I79/$B$65,0) -> 0 | K79: 2.125 | L79: 8 | M79: 17 | N79: =IFERROR(G79/K79,"-") -> 0 | P79: =IFERROR(G79/M79,"-") -> 0 | U79: - | V79: FRG | W79: =Preencher!$B$3&U79&V79&A79&$W$6 -> JARINU-FRG11029MQ.TUNEL DE CG (CONTINUO) | X79: =Preencher!$B$3&U79&V79&A79&$X$6 -> JARINU-FRG11029MQ.TUNEL DE CG (CONTINUO) (1) | Y79: =Preencher!$B$3&U79&V79&A79&$Y$6 -> JARINU-FRG11029MQ.TUNEL DE CG (CONTINUO) (2) | Z79: =Preencher!$B$3&U79&V79&A79&$Z$6 -> JARINU-FRG11029MQ.TUNEL DE CG (CONTINUO) (3) | AA79: =Preencher!$B$3&U79&V79&A79&$AA$6 -> JARINU-FRG11029MQ.TUNEL DE CG (ESTATICO) | AB79: =Preencher!$B$3&U79&V79&A79&$AB$6 -> JARINU-FRG11029MQ.TUNEL DE CG (ESTATICO) (1) | AC79: =Preencher!$B$3&U79&V79&A79&$AC$6 -> JARINU-FRG11029MQ.TUNEL DE CG (ESTATICO) (2) | AD79: =IFERROR(SUMIF('BD Otimix'!A:A,'BD VOLUME'!X79,'BD Otimix'!O:O)+SUMIF('BD Otimix'!A:A,'BD VOLUME'!Y79,'BD Otimix'!O:O)+SUMIF('BD Otimix'!A:A,'BD VOLUME'!Z79,'BD Otimix'!O:O)+SUMIF('BD Otimix'!A:A,'BD VOLUME'!AA79,'BD Otimix'!O:O)+SUMIF('BD Otimix'!A:A,'BD VOLUME'!AB79,'BD Otimix'!O:O)+SUMIF('BD Otimix'!A:A,'BD VOLUME'!AC79,'BD Otimix'!O:O)+SUMIF('BD Otimix'!A:A,'BD VOLUME'!W79,'BD Otimix'!O:O),0) -> 0 | AE79: =IFERROR(F79/$E$3/1000/AD79,0) -> 0 | AF79: =Preencher!$B$3&$U$8&$V$8&A79&$AF$6 -> JARINU-FRG11029MQ.GIROFREEZER | AG79: =Preencher!$B$3&$U$8&$V$8&A79&$AG$6 -> JARINU-FRG11029MQ.GIROFREEZER (1) | AH79: =Preencher!$B$3&$U$8&$V$8&A79&$AH$6 -> JARINU-FRG11029MQ.GIROFREEZER (2) | AI79: =Preencher!$B$3&$U$8&$V$8&A79&$AI$6 -> JARINU-FRG11029MQ.GIROFREEZER REV04 | AJ79: =Preencher!$B$3&$U$8&$V$8&A79&$AJ$6 -> JARINU-FRG11029MQ.GIROFREEZER (3) | AK79: =IFERROR(SUMIF('BD Otimix'!A:A,'BD VOLUME'!AG79,'BD Otimix'!O:O)+SUMIF('BD Otimix'!A:A,'BD VOLUME'!AH79,'BD Otimix'!O:O)+SUMIF('BD Otimix'!A:A,'BD VOLUME'!AI79,'BD Otimix'!O:O)+SUMIF('BD Otimix'!A:A,'BD VOLUME'!AJ79,'BD Otimix'!O:O)+SUMIF('BD Otimix'!A:A,'BD VOLUME'!AF79,'BD Otimix'!O:O),0) -> 0 | AL79: =IFERROR(F79/$E$3/1000/AK79,0) -> 0
A80: 950191 | C80: CARC C/GORD C/P PESC S/PESC C/SAMB | D80: INTEIROS | E80: BROILER MI | F80: =SUMIF('COLAR PLANO'!$A:$A,A80,'COLAR PLANO'!$D:$D) -> 0 | G80: =IFERROR(F80/($E$3*$C$3),0) -> 0 | H80: 0.7868 | I80: =IFERROR(G80/$D$3/H80,0) -> 0 | J80: =IFERROR(I80/$B$65,0) -> 0 | K80: 2.125 | L80: 8 | M80: 17 | N80: =IFERROR(G80/K80,"-") -> 0 | P80: =IFERROR(G80/M80,"-") -> 0 | U80: - | V80: FRG | W80: =Preencher!$B$3&U80&V80&A80&$W$6 -> JARINU-FRG950191MQ.TUNEL DE CG (CONTINUO) | X80: =Preencher!$B$3&U80&V80&A80&$X$6 -> JARINU-FRG950191MQ.TUNEL DE CG (CONTINUO) (1) | Y80: =Preencher!$B$3&U80&V80&A80&$Y$6 -> JARINU-FRG950191MQ.TUNEL DE CG (CONTINUO) (2) | Z80: =Preencher!$B$3&U80&V80&A80&$Z$6 -> JARINU-FRG950191MQ.TUNEL DE CG (CONTINUO) (3) | AA80: =Preencher!$B$3&U80&V80&A80&$AA$6 -> JARINU-FRG950191MQ.TUNEL DE CG (ESTATICO) | AB80: =Preencher!$B$3&U80&V80&A80&$AB$6 -> JARINU-FRG950191MQ.TUNEL DE CG (ESTATICO) (1) | AC80: =Preencher!$B$3&U80&V80&A80&$AC$6 -> JARINU-FRG950191MQ.TUNEL DE CG (ESTATICO) (2) | AD80: =IFERROR(SUMIF('BD Otimix'!A:A,'BD VOLUME'!X80,'BD Otimix'!O:O)+SUMIF('BD Otimix'!A:A,'BD VOLUME'!Y80,'BD Otimix'!O:O)+SUMIF('BD Otimix'!A:A,'BD VOLUME'!Z80,'BD Otimix'!O:O)+SUMIF('BD Otimix'!A:A,'BD VOLUME'!AA80,'BD Otimix'!O:O)+SUMIF('BD Otimix'!A:A,'BD VOLUME'!AB80,'BD Otimix'!O:O)+SUMIF('BD Otimix'!A:A,'BD VOLUME'!AC80,'BD Otimix'!O:O)+SUMIF('BD Otimix'!A:A,'BD VOLUME'!W80,'BD Otimix'!O:O),0) -> 0 | AE80: =IFERROR(F80/$E$3/1000/AD80,0) -> 0 | AF80: =Preencher!$B$3&$U$8&$V$8&A80&$AF$6 -> JARINU-FRG950191MQ.GIROFREEZER | AG80: =Preencher!$B$3&$U$8&$V$8&A80&$AG$6 -> JARINU-FRG950191MQ.GIROFREEZER (1) | AH80: =Preencher!$B$3&$U$8&$V$8&A80&$AH$6 -> JARINU-FRG950191MQ.GIROFREEZER (2) | AI80: =Preencher!$B$3&$U$8&$V$8&A80&$AI$6 -> JARINU-FRG950191MQ.GIROFREEZER REV04 | AJ80: =Preencher!$B$3&$U$8&$V$8&A80&$AJ$6 -> JARINU-FRG950191MQ.GIROFREEZER (3) | AK80: =IFERROR(SUMIF('BD Otimix'!A:A,'BD VOLUME'!AG80,'BD Otimix'!O:O)+SUMIF('BD Otimix'!A:A,'BD VOLUME'!AH80,'BD Otimix'!O:O)+SUMIF('BD Otimix'!A:A,'BD VOLUME'!AI80,'BD Otimix'!O:O)+SUMIF('BD Otimix'!A:A,'BD VOLUME'!AJ80,'BD Otimix'!O:O)+SUMIF('BD Otimix'!A:A,'BD VOLUME'!AF80,'BD Otimix'!O:O),0) -> 0 | AL80: =IFERROR(F80/$E$3/1000/AK80,0) -> 0
A81: 727342 | C81: CARC C/GORD C/P PESC S/PESC C/SAMB | D81: INTEIROS | E81: BROILER MI | F81: =SUMIF('COLAR PLANO'!$A:$A,A81,'COLAR PLANO'!$D:$D) -> 0 | G81: =IFERROR(F81/($E$3*$C$3),0) -> 0 | H81: 0.7764 | I81: =IFERROR(G81/$D$3/H81,0) -> 0 | J81: =IFERROR(I81/$B$65,0) -> 0 | K81: 2.125 | L81: 8 | M81: 17 | N81: =IFERROR(G81/K81,"-") -> 0 | P81: =IFERROR(G81/M81,"-") -> 0 | U81: - | V81: FRG | W81: =Preencher!$B$3&U81&V81&A81&$W$6 -> JARINU-FRG727342MQ.TUNEL DE CG (CONTINUO) | X81: =Preencher!$B$3&U81&V81&A81&$X$6 -> JARINU-FRG727342MQ.TUNEL DE CG (CONTINUO) (1) | Y81: =Preencher!$B$3&U81&V81&A81&$Y$6 -> JARINU-FRG727342MQ.TUNEL DE CG (CONTINUO) (2) | Z81: =Preencher!$B$3&U81&V81&A81&$Z$6 -> JARINU-FRG727342MQ.TUNEL DE CG (CONTINUO) (3) | AA81: =Preencher!$B$3&U81&V81&A81&$AA$6 -> JARINU-FRG727342MQ.TUNEL DE CG (ESTATICO) | AB81: =Preencher!$B$3&U81&V81&A81&$AB$6 -> JARINU-FRG727342MQ.TUNEL DE CG (ESTATICO) (1) | AC81: =Preencher!$B$3&U81&V81&A81&$AC$6 -> JARINU-FRG727342MQ.TUNEL DE CG (ESTATICO) (2) | AD81: =IFERROR(SUMIF('BD Otimix'!A:A,'BD VOLUME'!X81,'BD Otimix'!O:O)+SUMIF('BD Otimix'!A:A,'BD VOLUME'!Y81,'BD Otimix'!O:O)+SUMIF('BD Otimix'!A:A,'BD VOLUME'!Z81,'BD Otimix'!O:O)+SUMIF('BD Otimix'!A:A,'BD VOLUME'!AA81,'BD Otimix'!O:O)+SUMIF('BD Otimix'!A:A,'BD VOLUME'!AB81,'BD Otimix'!O:O)+SUMIF('BD Otimix'!A:A,'BD VOLUME'!AC81,'BD Otimix'!O:O)+SUMIF('BD Otimix'!A:A,'BD VOLUME'!W81,'BD Otimix'!O:O),0) -> 0 | AE81: =IFERROR(F81/$E$3/1000/AD81,0) -> 0 | AF81: =Preencher!$B$3&$U$8&$V$8&A81&$AF$6 -> JARINU-FRG727342MQ.GIROFREEZER | AG81: =Preencher!$B$3&$U$8&$V$8&A81&$AG$6 -> JARINU-FRG727342MQ.GIROFREEZER (1) | AH81: =Preencher!$B$3&$U$8&$V$8&A81&$AH$6 -> JARINU-FRG727342MQ.GIROFREEZER (2) | AI81: =Preencher!$B$3&$U$8&$V$8&A81&$AI$6 -> JARINU-FRG727342MQ.GIROFREEZER REV04 | AJ81: =Preencher!$B$3&$U$8&$V$8&A81&$AJ$6 -> JARINU-FRG727342MQ.GIROFREEZER (3) | AK81: =IFERROR(SUMIF('BD Otimix'!A:A,'BD VOLUME'!AG81,'BD Otimix'!O:O)+SUMIF('BD Otimix'!A:A,'BD VOLUME'!AH81,'BD Otimix'!O:O)+SUMIF('BD Otimix'!A:A,'BD VOLUME'!AI81,'BD Otimix'!O:O)+SUMIF('BD Otimix'!A:A,'BD VOLUME'!AJ81,'BD Otimix'!O:O)+SUMIF('BD Otimix'!A:A,'BD VOLUME'!AF81,'BD Otimix'!O:O),0) -> 0 | AL81: =IFERROR(F81/$E$3/1000/AK81,0) -> 0
A82: 124055 | C82: CARC C/GORD C/P PESC S/PESC C/SAMB | D82: INTEIROS | E82: BROILER MI | F82: =SUMIF('COLAR PLANO'!$A:$A,A82,'COLAR PLANO'!$D:$D) -> 0 | G82: =IFERROR(F82/($E$3*$C$3),0) -> 0 | H82: 0.7861 | I82: =IFERROR(G82/$D$3/H82,0) -> 0 | J82: =IFERROR(I82/$B$65,0) -> 0 | K82: 2.125 | L82: 8 | M82: 17 | N82: =IFERROR(G82/K82,"-") -> 0 | P82: =IFERROR(G82/M82,"-") -> 0 | U82: - | V82: FRG | W82: =Preencher!$B$3&U82&V82&A82&$W$6 -> JARINU-FRG124055MQ.TUNEL DE CG (CONTINUO) | X82: =Preencher!$B$3&U82&V82&A82&$X$6 -> JARINU-FRG124055MQ.TUNEL DE CG (CONTINUO) (1) | Y82: =Preencher!$B$3&U82&V82&A82&$Y$6 -> JARINU-FRG124055MQ.TUNEL DE CG (CONTINUO) (2) | Z82: =Preencher!$B$3&U82&V82&A82&$Z$6 -> JARINU-FRG124055MQ.TUNEL DE CG (CONTINUO) (3) | AA82: =Preencher!$B$3&U82&V82&A82&$AA$6 -> JARINU-FRG124055MQ.TUNEL DE CG (ESTATICO) | AB82: =Preencher!$B$3&U82&V82&A82&$AB$6 -> JARINU-FRG124055MQ.TUNEL DE CG (ESTATICO) (1) | AC82: =Preencher!$B$3&U82&V82&A82&$AC$6 -> JARINU-FRG124055MQ.TUNEL DE CG (ESTATICO) (2) | AD82: =IFERROR(SUMIF('BD Otimix'!A:A,'BD VOLUME'!X82,'BD Otimix'!O:O)+SUMIF('BD Otimix'!A:A,'BD VOLUME'!Y82,'BD Otimix'!O:O)+SUMIF('BD Otimix'!A:A,'BD VOLUME'!Z82,'BD Otimix'!O:O)+SUMIF('BD Otimix'!A:A,'BD VOLUME'!AA82,'BD Otimix'!O:O)+SUMIF('BD Otimix'!A:A,'BD VOLUME'!AB82,'BD Otimix'!O:O)+SUMIF('BD Otimix'!A:A,'BD VOLUME'!AC82,'BD Otimix'!O:O)+SUMIF('BD Otimix'!A:A,'BD VOLUME'!W82,'BD Otimix'!O:O),0) -> 0 | AE82: =IFERROR(F82/$E$3/1000/AD82,0) -> 0 | AF82: =Preencher!$B$3&$U$8&$V$8&A82&$AF$6 -> JARINU-FRG124055MQ.GIROFREEZER | AG82: =Preencher!$B$3&$U$8&$V$8&A82&$AG$6 -> JARINU-FRG124055MQ.GIROFREEZER (1) | AH82: =Preencher!$B$3&$U$8&$V$8&A82&$AH$6 -> JARINU-FRG124055MQ.GIROFREEZER (2) | AI82: =Preencher!$B$3&$U$8&$V$8&A82&$AI$6 -> JARINU-FRG124055MQ.GIROFREEZER REV04 | AJ82: =Preencher!$B$3&$U$8&$V$8&A82&$AJ$6 -> JARINU-FRG124055MQ.GIROFREEZER (3) | AK82: =IFERROR(SUMIF('BD Otimix'!A:A,'BD VOLUME'!AG82,'BD Otimix'!O:O)+SUMIF('BD Otimix'!A:A,'BD VOLUME'!AH82,'BD Otimix'!O:O)+SUMIF('BD Otimix'!A:A,'BD VOLUME'!AI82,'BD Otimix'!O:O)+SUMIF('BD Otimix'!A:A,'BD VOLUME'!AJ82,'BD Otimix'!O:O)+SUMIF('BD Otimix'!A:A,'BD VOLUME'!AF82,'BD Otimix'!O:O),0) -> 0 | AL82: =IFERROR(F82/$E$3/1000/AK82,0) -> 0
A83: 124149 | B83: GR-265 | C83: CARC C/GORD C/P PESC S/PESC C/SAMB | D83: INTEIROS | E83: BROILER MI | F83: =SUMIF('COLAR PLANO'!$A:$A,A83,'COLAR PLANO'!$D:$D) -> 0 | G83: =IFERROR(F83/($E$3*$C$3),0) -> 0 | H83: 0.7411 | I83: =IFERROR(G83/$D$3/H83,0) -> 0 | J83: =IFERROR(I83/$B$65,0) -> 0 | K83: 2.125 | L83: 8 | M83: 17 | N83: =IFERROR(G83/K83,"-") -> 0 | P83: =IFERROR(G83/M83,"-") -> 0 | U83: - | V83: FRG | W83: =Preencher!$B$3&U83&V83&A83&$W$6 -> JARINU-FRG124149MQ.TUNEL DE CG (CONTINUO) | X83: =Preencher!$B$3&U83&V83&A83&$X$6 -> JARINU-FRG124149MQ.TUNEL DE CG (CONTINUO) (1) | Y83: =Preencher!$B$3&U83&V83&A83&$Y$6 -> JARINU-FRG124149MQ.TUNEL DE CG (CONTINUO) (2) | Z83: =Preencher!$B$3&U83&V83&A83&$Z$6 -> JARINU-FRG124149MQ.TUNEL DE CG (CONTINUO) (3) | AA83: =Preencher!$B$3&U83&V83&A83&$AA$6 -> JARINU-FRG124149MQ.TUNEL DE CG (ESTATICO) | AB83: =Preencher!$B$3&U83&V83&A83&$AB$6 -> JARINU-FRG124149MQ.TUNEL DE CG (ESTATICO) (1) | AC83: =Preencher!$B$3&U83&V83&A83&$AC$6 -> JARINU-FRG124149MQ.TUNEL DE CG (ESTATICO) (2) | AD83: =IFERROR(SUMIF('BD Otimix'!A:A,'BD VOLUME'!X83,'BD Otimix'!O:O)+SUMIF('BD Otimix'!A:A,'BD VOLUME'!Y83,'BD Otimix'!O:O)+SUMIF('BD Otimix'!A:A,'BD VOLUME'!Z83,'BD Otimix'!O:O)+SUMIF('BD Otimix'!A:A,'BD VOLUME'!AA83,'BD Otimix'!O:O)+SUMIF('BD Otimix'!A:A,'BD VOLUME'!AB83,'BD Otimix'!O:O)+SUMIF('BD Otimix'!A:A,'BD VOLUME'!AC83,'BD Otimix'!O:O)+SUMIF('BD Otimix'!A:A,'BD VOLUME'!W83,'BD Otimix'!O:O),0) -> 0 | AE83: =IFERROR(F83/$E$3/1000/AD83,0) -> 0 | AF83: =Preencher!$B$3&$U$8&$V$8&A83&$AF$6 -> JARINU-FRG124149MQ.GIROFREEZER | AG83: =Preencher!$B$3&$U$8&$V$8&A83&$AG$6 -> JARINU-FRG124149MQ.GIROFREEZER (1) | AH83: =Preencher!$B$3&$U$8&$V$8&A83&$AH$6 -> JARINU-FRG124149MQ.GIROFREEZER (2) | AI83: =Preencher!$B$3&$U$8&$V$8&A83&$AI$6 -> JARINU-FRG124149MQ.GIROFREEZER REV04 | AJ83: =Preencher!$B$3&$U$8&$V$8&A83&$AJ$6 -> JARINU-FRG124149MQ.GIROFREEZER (3) | AK83: =IFERROR(SUMIF('BD Otimix'!A:A,'BD VOLUME'!AG83,'BD Otimix'!O:O)+SUMIF('BD Otimix'!A:A,'BD VOLUME'!AH83,'BD Otimix'!O:O)+SUMIF('BD Otimix'!A:A,'BD VOLUME'!AI83,'BD Otimix'!O:O)+SUMIF('BD Otimix'!A:A,'BD VOLUME'!AJ83,'BD Otimix'!O:O)+SUMIF('BD Otimix'!A:A,'BD VOLUME'!AF83,'BD Otimix'!O:O),0) -> 0 | AL83: =IFERROR(F83/$E$3/1000/AK83,0) -> 0
A84: 124171 | B84: GR-266 | C84: CARC C/GORD C/P PESC S/PESC C/SAMB | D84: INTEIROS | E84: BROILER MI | F84: =SUMIF('COLAR PLANO'!$A:$A,A84,'COLAR PLANO'!$D:$D) -> 0 | G84: =IFERROR(F84/($E$3*$C$3),0) -> 0 | H84: 0.7411 | I84: =IFERROR(G84/$D$3/H84,0) -> 0 | J84: =IFERROR(I84/$B$65,0) -> 0 | K84: 2.125 | L84: 8 | M84: 17 | N84: =IFERROR(G84/K84,"-") -> 0 | P84: =IFERROR(G84/M84,"-") -> 0 | U84: - | V84: FRG | W84: =Preencher!$B$3&U84&V84&A84&$W$6 -> JARINU-FRG124171MQ.TUNEL DE CG (CONTINUO) | X84: =Preencher!$B$3&U84&V84&A84&$X$6 -> JARINU-FRG124171MQ.TUNEL DE CG (CONTINUO) (1) | Y84: =Preencher!$B$3&U84&V84&A84&$Y$6 -> JARINU-FRG124171MQ.TUNEL DE CG (CONTINUO) (2) | Z84: =Preencher!$B$3&U84&V84&A84&$Z$6 -> JARINU-FRG124171MQ.TUNEL DE CG (CONTINUO) (3) | AA84: =Preencher!$B$3&U84&V84&A84&$AA$6 -> JARINU-FRG124171MQ.TUNEL DE CG (ESTATICO) | AB84: =Preencher!$B$3&U84&V84&A84&$AB$6 -> JARINU-FRG124171MQ.TUNEL DE CG (ESTATICO) (1) | AC84: =Preencher!$B$3&U84&V84&A84&$AC$6 -> JARINU-FRG124171MQ.TUNEL DE CG (ESTATICO) (2) | AD84: =IFERROR(SUMIF('BD Otimix'!A:A,'BD VOLUME'!X84,'BD Otimix'!O:O)+SUMIF('BD Otimix'!A:A,'BD VOLUME'!Y84,'BD Otimix'!O:O)+SUMIF('BD Otimix'!A:A,'BD VOLUME'!Z84,'BD Otimix'!O:O)+SUMIF('BD Otimix'!A:A,'BD VOLUME'!AA84,'BD Otimix'!O:O)+SUMIF('BD Otimix'!A:A,'BD VOLUME'!AB84,'BD Otimix'!O:O)+SUMIF('BD Otimix'!A:A,'BD VOLUME'!AC84,'BD Otimix'!O:O)+SUMIF('BD Otimix'!A:A,'BD VOLUME'!W84,'BD Otimix'!O:O),0) -> 0 | AE84: =IFERROR(F84/$E$3/1000/AD84,0) -> 0 | AF84: =Preencher!$B$3&$U$8&$V$8&A84&$AF$6 -> JARINU-FRG124171MQ.GIROFREEZER | AG84: =Preencher!$B$3&$U$8&$V$8&A84&$AG$6 -> JARINU-FRG124171MQ.GIROFREEZER (1) | AH84: =Preencher!$B$3&$U$8&$V$8&A84&$AH$6 -> JARINU-FRG124171MQ.GIROFREEZER (2) | AI84: =Preencher!$B$3&$U$8&$V$8&A84&$AI$6 -> JARINU-FRG124171MQ.GIROFREEZER REV04 | AJ84: =Preencher!$B$3&$U$8&$V$8&A84&$AJ$6 -> JARINU-FRG124171MQ.GIROFREEZER (3) | AK84: =IFERROR(SUMIF('BD Otimix'!A:A,'BD VOLUME'!AG84,'BD Otimix'!O:O)+SUMIF('BD Otimix'!A:A,'BD VOLUME'!AH84,'BD Otimix'!O:O)+SUMIF('BD Otimix'!A:A,'BD VOLUME'!AI84,'BD Otimix'!O:O)+SUMIF('BD Otimix'!A:A,'BD VOLUME'!AJ84,'BD Otimix'!O:O)+SUMIF('BD Otimix'!A:A,'BD VOLUME'!AF84,'BD Otimix'!O:O),0) -> 0 | AL84: =IFERROR(F84/$E$3/1000/AK84,0) -> 0
A85: 124172 | B85: GR-267 | C85: CARC C/GORD C/P PESC S/PESC C/SAMB | D85: INTEIROS | E85: BROILER MI | F85: =SUMIF('COLAR PLANO'!$A:$A,A85,'COLAR PLANO'!$D:$D) -> 0 | G85: =IFERROR(F85/($E$3*$C$3),0) -> 0 | H85: 0.7411 | I85: =IFERROR(G85/$D$3/H85,0) -> 0 | J85: =IFERROR(I85/$B$65,0) -> 0 | K85: 2.125 | L85: 8 | M85: 17 | N85: =IFERROR(G85/K85,"-") -> 0 | P85: =IFERROR(G85/M85,"-") -> 0 | U85: - | V85: FRG | W85: =Preencher!$B$3&U85&V85&A85&$W$6 -> JARINU-FRG124172MQ.TUNEL DE CG (CONTINUO) | X85: =Preencher!$B$3&U85&V85&A85&$X$6 -> JARINU-FRG124172MQ.TUNEL DE CG (CONTINUO) (1) | Y85: =Preencher!$B$3&U85&V85&A85&$Y$6 -> JARINU-FRG124172MQ.TUNEL DE CG (CONTINUO) (2) | Z85: =Preencher!$B$3&U85&V85&A85&$Z$6 -> JARINU-FRG124172MQ.TUNEL DE CG (CONTINUO) (3) | AA85: =Preencher!$B$3&U85&V85&A85&$AA$6 -> JARINU-FRG124172MQ.TUNEL DE CG (ESTATICO) | AB85: =Preencher!$B$3&U85&V85&A85&$AB$6 -> JARINU-FRG124172MQ.TUNEL DE CG (ESTATICO) (1) | AC85: =Preencher!$B$3&U85&V85&A85&$AC$6 -> JARINU-FRG124172MQ.TUNEL DE CG (ESTATICO) (2) | AD85: =IFERROR(SUMIF('BD Otimix'!A:A,'BD VOLUME'!X85,'BD Otimix'!O:O)+SUMIF('BD Otimix'!A:A,'BD VOLUME'!Y85,'BD Otimix'!O:O)+SUMIF('BD Otimix'!A:A,'BD VOLUME'!Z85,'BD Otimix'!O:O)+SUMIF('BD Otimix'!A:A,'BD VOLUME'!AA85,'BD Otimix'!O:O)+SUMIF('BD Otimix'!A:A,'BD VOLUME'!AB85,'BD Otimix'!O:O)+SUMIF('BD Otimix'!A:A,'BD VOLUME'!AC85,'BD Otimix'!O:O)+SUMIF('BD Otimix'!A:A,'BD VOLUME'!W85,'BD Otimix'!O:O),0) -> 0 | AE85: =IFERROR(F85/$E$3/1000/AD85,0) -> 0 | AF85: =Preencher!$B$3&$U$8&$V$8&A85&$AF$6 -> JARINU-FRG124172MQ.GIROFREEZER | AG85: =Preencher!$B$3&$U$8&$V$8&A85&$AG$6 -> JARINU-FRG124172MQ.GIROFREEZER (1) | AH85: =Preencher!$B$3&$U$8&$V$8&A85&$AH$6 -> JARINU-FRG124172MQ.GIROFREEZER (2) | AI85: =Preencher!$B$3&$U$8&$V$8&A85&$AI$6 -> JARINU-FRG124172MQ.GIROFREEZER REV04 | AJ85: =Preencher!$B$3&$U$8&$V$8&A85&$AJ$6 -> JARINU-FRG124172MQ.GIROFREEZER (3) | AK85: =IFERROR(SUMIF('BD Otimix'!A:A,'BD VOLUME'!AG85,'BD Otimix'!O:O)+SUMIF('BD Otimix'!A:A,'BD VOLUME'!AH85,'BD Otimix'!O:O)+SUMIF('BD Otimix'!A:A,'BD VOLUME'!AI85,'BD Otimix'!O:O)+SUMIF('BD Otimix'!A:A,'BD VOLUME'!AJ85,'BD Otimix'!O:O)+SUMIF('BD Otimix'!A:A,'BD VOLUME'!AF85,'BD Otimix'!O:O),0) -> 0 | AL85: =IFERROR(F85/$E$3/1000/AK85,0) -> 0
A86: 124173 | B86: GR-286 | C86: CARC C/GORD C/P PESC S/PESC C/SAMB | D86: INTEIROS | E86: BROILER MI | F86: =SUMIF('COLAR PLANO'!$A:$A,A86,'COLAR PLANO'!$D:$D) -> 0 | G86: =IFERROR(F86/($E$3*$C$3),0) -> 0 | H86: 0.7411 | I86: =IFERROR(G86/$D$3/H86,0) -> 0 | J86: =IFERROR(I86/$B$65,0) -> 0 | K86: 2.125 | L86: 8 | M86: 17 | N86: =IFERROR(G86/K86,"-") -> 0 | P86: =IFERROR(G86/M86,"-") -> 0 | U86: - | V86: FRG | W86: =Preencher!$B$3&U86&V86&A86&$W$6 -> JARINU-FRG124173MQ.TUNEL DE CG (CONTINUO) | X86: =Preencher!$B$3&U86&V86&A86&$X$6 -> JARINU-FRG124173MQ.TUNEL DE CG (CONTINUO) (1) | Y86: =Preencher!$B$3&U86&V86&A86&$Y$6 -> JARINU-FRG124173MQ.TUNEL DE CG (CONTINUO) (2) | Z86: =Preencher!$B$3&U86&V86&A86&$Z$6 -> JARINU-FRG124173MQ.TUNEL DE CG (CONTINUO) (3) | AA86: =Preencher!$B$3&U86&V86&A86&$AA$6 -> JARINU-FRG124173MQ.TUNEL DE CG (ESTATICO) | AB86: =Preencher!$B$3&U86&V86&A86&$AB$6 -> JARINU-FRG124173MQ.TUNEL DE CG (ESTATICO) (1) | AC86: =Preencher!$B$3&U86&V86&A86&$AC$6 -> JARINU-FRG124173MQ.TUNEL DE CG (ESTATICO) (2) | AD86: =IFERROR(SUMIF('BD Otimix'!A:A,'BD VOLUME'!X86,'BD Otimix'!O:O)+SUMIF('BD Otimix'!A:A,'BD VOLUME'!Y86,'BD Otimix'!O:O)+SUMIF('BD Otimix'!A:A,'BD VOLUME'!Z86,'BD Otimix'!O:O)+SUMIF('BD Otimix'!A:A,'BD VOLUME'!AA86,'BD Otimix'!O:O)+SUMIF('BD Otimix'!A:A,'BD VOLUME'!AB86,'BD Otimix'!O:O)+SUMIF('BD Otimix'!A:A,'BD VOLUME'!AC86,'BD Otimix'!O:O)+SUMIF('BD Otimix'!A:A,'BD VOLUME'!W86,'BD Otimix'!O:O),0) -> 0 | AE86: =IFERROR(F86/$E$3/1000/AD86,0) -> 0 | AF86: =Preencher!$B$3&$U$8&$V$8&A86&$AF$6 -> JARINU-FRG124173MQ.GIROFREEZER | AG86: =Preencher!$B$3&$U$8&$V$8&A86&$AG$6 -> JARINU-FRG124173MQ.GIROFREEZER (1) | AH86: =Preencher!$B$3&$U$8&$V$8&A86&$AH$6 -> JARINU-FRG124173MQ.GIROFREEZER (2) | AI86: =Preencher!$B$3&$U$8&$V$8&A86&$AI$6 -> JARINU-FRG124173MQ.GIROFREEZER REV04 | AJ86: =Preencher!$B$3&$U$8&$V$8&A86&$AJ$6 -> JARINU-FRG124173MQ.GIROFREEZER (3) | AK86: =IFERROR(SUMIF('BD Otimix'!A:A,'BD VOLUME'!AG86,'BD Otimix'!O:O)+SUMIF('BD Otimix'!A:A,'BD VOLUME'!AH86,'BD Otimix'!O:O)+SUMIF('BD Otimix'!A:A,'BD VOLUME'!AI86,'BD Otimix'!O:O)+SUMIF('BD Otimix'!A:A,'BD VOLUME'!AJ86,'BD Otimix'!O:O)+SUMIF('BD Otimix'!A:A,'BD VOLUME'!AF86,'BD Otimix'!O:O),0) -> 0 | AL86: =IFERROR(F86/$E$3/1000/AK86,0) -> 0
A87: 124174 | B87: GR-287 | C87: CARC C/GORD C/P PESC S/PESC C/SAMB | D87: INTEIROS | E87: BROILER MI | F87: =SUMIF('COLAR PLANO'!$A:$A,A87,'COLAR PLANO'!$D:$D) -> 0 | G87: =IFERROR(F87/($E$3*$C$3),0) -> 0 | H87: 0.7411 | I87: =IFERROR(G87/$D$3/H87,0) -> 0 | J87: =IFERROR(I87/$B$65,0) -> 0 | K87: 2.125 | L87: 8 | M87: 17 | N87: =IFERROR(G87/K87,"-") -> 0 | P87: =IFERROR(G87/M87,"-") -> 0 | U87: - | V87: FRG | W87: =Preencher!$B$3&U87&V87&A87&$W$6 -> JARINU-FRG124174MQ.TUNEL DE CG (CONTINUO) | X87: =Preencher!$B$3&U87&V87&A87&$X$6 -> JARINU-FRG124174MQ.TUNEL DE CG (CONTINUO) (1) | Y87: =Preencher!$B$3&U87&V87&A87&$Y$6 -> JARINU-FRG124174MQ.TUNEL DE CG (CONTINUO) (2) | Z87: =Preencher!$B$3&U87&V87&A87&$Z$6 -> JARINU-FRG124174MQ.TUNEL DE CG (CONTINUO) (3) | AA87: =Preencher!$B$3&U87&V87&A87&$AA$6 -> JARINU-FRG124174MQ.TUNEL DE CG (ESTATICO) | AB87: =Preencher!$B$3&U87&V87&A87&$AB$6 -> JARINU-FRG124174MQ.TUNEL DE CG (ESTATICO) (1) | AC87: =Preencher!$B$3&U87&V87&A87&$AC$6 -> JARINU-FRG124174MQ.TUNEL DE CG (ESTATICO) (2) | AD87: =IFERROR(SUMIF('BD Otimix'!A:A,'BD VOLUME'!X87,'BD Otimix'!O:O)+SUMIF('BD Otimix'!A:A,'BD VOLUME'!Y87,'BD Otimix'!O:O)+SUMIF('BD Otimix'!A:A,'BD VOLUME'!Z87,'BD Otimix'!O:O)+SUMIF('BD Otimix'!A:A,'BD VOLUME'!AA87,'BD Otimix'!O:O)+SUMIF('BD Otimix'!A:A,'BD VOLUME'!AB87,'BD Otimix'!O:O)+SUMIF('BD Otimix'!A:A,'BD VOLUME'!AC87,'BD Otimix'!O:O)+SUMIF('BD Otimix'!A:A,'BD VOLUME'!W87,'BD Otimix'!O:O),0) -> 0 | AE87: =IFERROR(F87/$E$3/1000/AD87,0) -> 0 | AF87: =Preencher!$B$3&$U$8&$V$8&A87&$AF$6 -> JARINU-FRG124174MQ.GIROFREEZER | AG87: =Preencher!$B$3&$U$8&$V$8&A87&$AG$6 -> JARINU-FRG124174MQ.GIROFREEZER (1) | AH87: =Preencher!$B$3&$U$8&$V$8&A87&$AH$6 -> JARINU-FRG124174MQ.GIROFREEZER (2) | AI87: =Preencher!$B$3&$U$8&$V$8&A87&$AI$6 -> JARINU-FRG124174MQ.GIROFREEZER REV04 | AJ87: =Preencher!$B$3&$U$8&$V$8&A87&$AJ$6 -> JARINU-FRG124174MQ.GIROFREEZER (3) | AK87: =IFERROR(SUMIF('BD Otimix'!A:A,'BD VOLUME'!AG87,'BD Otimix'!O:O)+SUMIF('BD Otimix'!A:A,'BD VOLUME'!AH87,'BD Otimix'!O:O)+SUMIF('BD Otimix'!A:A,'BD VOLUME'!AI87,'BD Otimix'!O:O)+SUMIF('BD Otimix'!A:A,'BD VOLUME'!AJ87,'BD Otimix'!O:O)+SUMIF('BD Otimix'!A:A,'BD VOLUME'!AF87,'BD Otimix'!O:O),0) -> 0 | AL87: =IFERROR(F87/$E$3/1000/AK87,0) -> 0
A88: 124175 | B88: GR-288 | C88: CARC C/GORD C/P PESC S/PESC C/SAMB | D88: INTEIROS | E88: BROILER MI | F88: =SUMIF('COLAR PLANO'!$A:$A,A88,'COLAR PLANO'!$D:$D) -> 0 | G88: =IFERROR(F88/($E$3*$C$3),0) -> 0 | H88: 0.7411 | I88: =IFERROR(G88/$D$3/H88,0) -> 0 | J88: =IFERROR(I88/$B$65,0) -> 0 | K88: 2.125 | L88: 8 | M88: 17 | N88: =IFERROR(G88/K88,"-") -> 0 | P88: =IFERROR(G88/M88,"-") -> 0 | U88: - | V88: FRG | W88: =Preencher!$B$3&U88&V88&A88&$W$6 -> JARINU-FRG124175MQ.TUNEL DE CG (CONTINUO) | X88: =Preencher!$B$3&U88&V88&A88&$X$6 -> JARINU-FRG124175MQ.TUNEL DE CG (CONTINUO) (1) | Y88: =Preencher!$B$3&U88&V88&A88&$Y$6 -> JARINU-FRG124175MQ.TUNEL DE CG (CONTINUO) (2) | Z88: =Preencher!$B$3&U88&V88&A88&$Z$6 -> JARINU-FRG124175MQ.TUNEL DE CG (CONTINUO) (3) | AA88: =Preencher!$B$3&U88&V88&A88&$AA$6 -> JARINU-FRG124175MQ.TUNEL DE CG (ESTATICO) | AB88: =Preencher!$B$3&U88&V88&A88&$AB$6 -> JARINU-FRG124175MQ.TUNEL DE CG (ESTATICO) (1) | AC88: =Preencher!$B$3&U88&V88&A88&$AC$6 -> JARINU-FRG124175MQ.TUNEL DE CG (ESTATICO) (2) | AD88: =IFERROR(SUMIF('BD Otimix'!A:A,'BD VOLUME'!X88,'BD Otimix'!O:O)+SUMIF('BD Otimix'!A:A,'BD VOLUME'!Y88,'BD Otimix'!O:O)+SUMIF('BD Otimix'!A:A,'BD VOLUME'!Z88,'BD Otimix'!O:O)+SUMIF('BD Otimix'!A:A,'BD VOLUME'!AA88,'BD Otimix'!O:O)+SUMIF('BD Otimix'!A:A,'BD VOLUME'!AB88,'BD Otimix'!O:O)+SUMIF('BD Otimix'!A:A,'BD VOLUME'!AC88,'BD Otimix'!O:O)+SUMIF('BD Otimix'!A:A,'BD VOLUME'!W88,'BD Otimix'!O:O),0) -> 0 | AE88: =IFERROR(F88/$E$3/1000/AD88,0) -> 0 | AF88: =Preencher!$B$3&$U$8&$V$8&A88&$AF$6 -> JARINU-FRG124175MQ.GIROFREEZER | AG88: =Preencher!$B$3&$U$8&$V$8&A88&$AG$6 -> JARINU-FRG124175MQ.GIROFREEZER (1) | AH88: =Preencher!$B$3&$U$8&$V$8&A88&$AH$6 -> JARINU-FRG124175MQ.GIROFREEZER (2) | AI88: =Preencher!$B$3&$U$8&$V$8&A88&$AI$6 -> JARINU-FRG124175MQ.GIROFREEZER REV04 | AJ88: =Preencher!$B$3&$U$8&$V$8&A88&$AJ$6 -> JARINU-FRG124175MQ.GIROFREEZER (3) | AK88: =IFERROR(SUMIF('BD Otimix'!A:A,'BD VOLUME'!AG88,'BD Otimix'!O:O)+SUMIF('BD Otimix'!A:A,'BD VOLUME'!AH88,'BD Otimix'!O:O)+SUMIF('BD Otimix'!A:A,'BD VOLUME'!AI88,'BD Otimix'!O:O)+SUMIF('BD Otimix'!A:A,'BD VOLUME'!AJ88,'BD Otimix'!O:O)+SUMIF('BD Otimix'!A:A,'BD VOLUME'!AF88,'BD Otimix'!O:O),0) -> 0 | AL88: =IFERROR(F88/$E$3/1000/AK88,0) -> 0
A89: 124305 | C89: CARC C/GORD C/P PESC S/PESC C/SAMB | D89: INTEIROS | E89: BROILER MI | F89: =SUMIF('COLAR PLANO'!$A:$A,A89,'COLAR PLANO'!$D:$D) -> 0 | G89: =IFERROR(F89/($E$3*$C$3),0) -> 0 | H89: 0.7411 | I89: =IFERROR(G89/$D$3/H89,0) -> 0 | J89: =IFERROR(I89/$B$65,0) -> 0 | K89: 2.125 | L89: 8 | M89: 17 | N89: =IFERROR(G89/K89,"-") -> 0 | P89: =IFERROR(G89/M89,"-") -> 0 | U89: - | V89: FRG | W89: =Preencher!$B$3&U89&V89&A89&$W$6 -> JARINU-FRG124305MQ.TUNEL DE CG (CONTINUO) | X89: =Preencher!$B$3&U89&V89&A89&$X$6 -> JARINU-FRG124305MQ.TUNEL DE CG (CONTINUO) (1) | Y89: =Preencher!$B$3&U89&V89&A89&$Y$6 -> JARINU-FRG124305MQ.TUNEL DE CG (CONTINUO) (2) | Z89: =Preencher!$B$3&U89&V89&A89&$Z$6 -> JARINU-FRG124305MQ.TUNEL DE CG (CONTINUO) (3) | AA89: =Preencher!$B$3&U89&V89&A89&$AA$6 -> JARINU-FRG124305MQ.TUNEL DE CG (ESTATICO) | AB89: =Preencher!$B$3&U89&V89&A89&$AB$6 -> JARINU-FRG124305MQ.TUNEL DE CG (ESTATICO) (1) | AC89: =Preencher!$B$3&U89&V89&A89&$AC$6 -> JARINU-FRG124305MQ.TUNEL DE CG (ESTATICO) (2) | AD89: =IFERROR(SUMIF('BD Otimix'!A:A,'BD VOLUME'!X89,'BD Otimix'!O:O)+SUMIF('BD Otimix'!A:A,'BD VOLUME'!Y89,'BD Otimix'!O:O)+SUMIF('BD Otimix'!A:A,'BD VOLUME'!Z89,'BD Otimix'!O:O)+SUMIF('BD Otimix'!A:A,'BD VOLUME'!AA89,'BD Otimix'!O:O)+SUMIF('BD Otimix'!A:A,'BD VOLUME'!AB89,'BD Otimix'!O:O)+SUMIF('BD Otimix'!A:A,'BD VOLUME'!AC89,'BD Otimix'!O:O)+SUMIF('BD Otimix'!A:A,'BD VOLUME'!W89,'BD Otimix'!O:O),0) -> 0 | AE89: =IFERROR(F89/$E$3/1000/AD89,0) -> 0 | AF89: =Preencher!$B$3&$U$8&$V$8&A89&$AF$6 -> JARINU-FRG124305MQ.GIROFREEZER | AG89: =Preencher!$B$3&$U$8&$V$8&A89&$AG$6 -> JARINU-FRG124305MQ.GIROFREEZER (1) | AH89: =Preencher!$B$3&$U$8&$V$8&A89&$AH$6 -> JARINU-FRG124305MQ.GIROFREEZER (2) | AI89: =Preencher!$B$3&$U$8&$V$8&A89&$AI$6 -> JARINU-FRG124305MQ.GIROFREEZER REV04 | AJ89: =Preencher!$B$3&$U$8&$V$8&A89&$AJ$6 -> JARINU-FRG124305MQ.GIROFREEZER (3) | AK89: =IFERROR(SUMIF('BD Otimix'!A:A,'BD VOLUME'!AG89,'BD Otimix'!O:O)+SUMIF('BD Otimix'!A:A,'BD VOLUME'!AH89,'BD Otimix'!O:O)+SUMIF('BD Otimix'!A:A,'BD VOLUME'!AI89,'BD Otimix'!O:O)+SUMIF('BD Otimix'!A:A,'BD VOLUME'!AJ89,'BD Otimix'!O:O)+SUMIF('BD Otimix'!A:A,'BD VOLUME'!AF89,'BD Otimix'!O:O),0) -> 0 | AL89: =IFERROR(F89/$E$3/1000/AK89,0) -> 0
A90: 124307 | C90: CARC C/GORD C/P PESC S/PESC C/SAMB | D90: INTEIROS | E90: BROILER MI | F90: =SUMIF('COLAR PLANO'!$A:$A,A90,'COLAR PLANO'!$D:$D) -> 0 | G90: =IFERROR(F90/($E$3*$C$3),0) -> 0 | H90: 0.7411 | I90: =IFERROR(G90/$D$3/H90,0) -> 0 | J90: =IFERROR(I90/$B$65,0) -> 0 | K90: 2.125 | L90: 8 | M90: 17 | N90: =IFERROR(G90/K90,"-") -> 0 | P90: =IFERROR(G90/M90,"-") -> 0 | U90: - | V90: FRG | W90: =Preencher!$B$3&U90&V90&A90&$W$6 -> JARINU-FRG124307MQ.TUNEL DE CG (CONTINUO) | X90: =Preencher!$B$3&U90&V90&A90&$X$6 -> JARINU-FRG124307MQ.TUNEL DE CG (CONTINUO) (1) | Y90: =Preencher!$B$3&U90&V90&A90&$Y$6 -> JARINU-FRG124307MQ.TUNEL DE CG (CONTINUO) (2) | Z90: =Preencher!$B$3&U90&V90&A90&$Z$6 -> JARINU-FRG124307MQ.TUNEL DE CG (CONTINUO) (3) | AA90: =Preencher!$B$3&U90&V90&A90&$AA$6 -> JARINU-FRG124307MQ.TUNEL DE CG (ESTATICO) | AB90: =Preencher!$B$3&U90&V90&A90&$AB$6 -> JARINU-FRG124307MQ.TUNEL DE CG (ESTATICO) (1) | AC90: =Preencher!$B$3&U90&V90&A90&$AC$6 -> JARINU-FRG124307MQ.TUNEL DE CG (ESTATICO) (2) | AD90: =IFERROR(SUMIF('BD Otimix'!A:A,'BD VOLUME'!X90,'BD Otimix'!O:O)+SUMIF('BD Otimix'!A:A,'BD VOLUME'!Y90,'BD Otimix'!O:O)+SUMIF('BD Otimix'!A:A,'BD VOLUME'!Z90,'BD Otimix'!O:O)+SUMIF('BD Otimix'!A:A,'BD VOLUME'!AA90,'BD Otimix'!O:O)+SUMIF('BD Otimix'!A:A,'BD VOLUME'!AB90,'BD Otimix'!O:O)+SUMIF('BD Otimix'!A:A,'BD VOLUME'!AC90,'BD Otimix'!O:O)+SUMIF('BD Otimix'!A:A,'BD VOLUME'!W90,'BD Otimix'!O:O),0) -> 0 | AE90: =IFERROR(F90/$E$3/1000/AD90,0) -> 0 | AF90: =Preencher!$B$3&$U$8&$V$8&A90&$AF$6 -> JARINU-FRG124307MQ.GIROFREEZER | AG90: =Preencher!$B$3&$U$8&$V$8&A90&$AG$6 -> JARINU-FRG124307MQ.GIROFREEZER (1) | AH90: =Preencher!$B$3&$U$8&$V$8&A90&$AH$6 -> JARINU-FRG124307MQ.GIROFREEZER (2) | AI90: =Preencher!$B$3&$U$8&$V$8&A90&$AI$6 -> JARINU-FRG124307MQ.GIROFREEZER REV04 | AJ90: =Preencher!$B$3&$U$8&$V$8&A90&$AJ$6 -> JARINU-FRG124307MQ.GIROFREEZER (3) | AK90: =IFERROR(SUMIF('BD Otimix'!A:A,'BD VOLUME'!AG90,'BD Otimix'!O:O)+SUMIF('BD Otimix'!A:A,'BD VOLUME'!AH90,'BD Otimix'!O:O)+SUMIF('BD Otimix'!A:A,'BD VOLUME'!AI90,'BD Otimix'!O:O)+SUMIF('BD Otimix'!A:A,'BD VOLUME'!AJ90,'BD Otimix'!O:O)+SUMIF('BD Otimix'!A:A,'BD VOLUME'!AF90,'BD Otimix'!O:O),0) -> 0 | AL90: =IFERROR(F90/$E$3/1000/AK90,0) -> 0
A91: 956805 | B91: GR-289 | C91: CARC C/GORD C/P PESC S/PESC C/SAMB | D91: INTEIROS | E91: BROILER MI | F91: =SUMIF('COLAR PLANO'!$A:$A,A91,'COLAR PLANO'!$D:$D) -> 0 | G91: =IFERROR(F91/($E$3*$C$3),0) -> 0 | H91: 0.7411 | I91: =IFERROR(G91/$D$3/H91,0) -> 0 | J91: =IFERROR(I91/$B$65,0) -> 0 | K91: 2.125 | L91: 8 | M91: 17 | N91: =IFERROR(G91/K91,"-") -> 0 | P91: =IFERROR(G91/M91,"-") -> 0 | U91: - | V91: FRG | W91: =Preencher!$B$3&U91&V91&A91&$W$6 -> JARINU-FRG956805MQ.TUNEL DE CG (CONTINUO) | X91: =Preencher!$B$3&U91&V91&A91&$X$6 -> JARINU-FRG956805MQ.TUNEL DE CG (CONTINUO) (1) | Y91: =Preencher!$B$3&U91&V91&A91&$Y$6 -> JARINU-FRG956805MQ.TUNEL DE CG (CONTINUO) (2) | Z91: =Preencher!$B$3&U91&V91&A91&$Z$6 -> JARINU-FRG956805MQ.TUNEL DE CG (CONTINUO) (3) | AA91: =Preencher!$B$3&U91&V91&A91&$AA$6 -> JARINU-FRG956805MQ.TUNEL DE CG (ESTATICO) | AB91: =Preencher!$B$3&U91&V91&A91&$AB$6 -> JARINU-FRG956805MQ.TUNEL DE CG (ESTATICO) (1) | AC91: =Preencher!$B$3&U91&V91&A91&$AC$6 -> JARINU-FRG956805MQ.TUNEL DE CG (ESTATICO) (2) | AD91: =IFERROR(SUMIF('BD Otimix'!A:A,'BD VOLUME'!X91,'BD Otimix'!O:O)+SUMIF('BD Otimix'!A:A,'BD VOLUME'!Y91,'BD Otimix'!O:O)+SUMIF('BD Otimix'!A:A,'BD VOLUME'!Z91,'BD Otimix'!O:O)+SUMIF('BD Otimix'!A:A,'BD VOLUME'!AA91,'BD Otimix'!O:O)+SUMIF('BD Otimix'!A:A,'BD VOLUME'!AB91,'BD Otimix'!O:O)+SUMIF('BD Otimix'!A:A,'BD VOLUME'!AC91,'BD Otimix'!O:O)+SUMIF('BD Otimix'!A:A,'BD VOLUME'!W91,'BD Otimix'!O:O),0) -> 0 | AE91: =IFERROR(F91/$E$3/1000/AD91,0) -> 0 | AF91: =Preencher!$B$3&$U$8&$V$8&A91&$AF$6 -> JARINU-FRG956805MQ.GIROFREEZER | AG91: =Preencher!$B$3&$U$8&$V$8&A91&$AG$6 -> JARINU-FRG956805MQ.GIROFREEZER (1) | AH91: =Preencher!$B$3&$U$8&$V$8&A91&$AH$6 -> JARINU-FRG956805MQ.GIROFREEZER (2) | AI91: =Preencher!$B$3&$U$8&$V$8&A91&$AI$6 -> JARINU-FRG956805MQ.GIROFREEZER REV04 | AJ91: =Preencher!$B$3&$U$8&$V$8&A91&$AJ$6 -> JARINU-FRG956805MQ.GIROFREEZER (3) | AK91: =IFERROR(SUMIF('BD Otimix'!A:A,'BD VOLUME'!AG91,'BD Otimix'!O:O)+SUMIF('BD Otimix'!A:A,'BD VOLUME'!AH91,'BD Otimix'!O:O)+SUMIF('BD Otimix'!A:A,'BD VOLUME'!AI91,'BD Otimix'!O:O)+SUMIF('BD Otimix'!A:A,'BD VOLUME'!AJ91,'BD Otimix'!O:O)+SUMIF('BD Otimix'!A:A,'BD VOLUME'!AF91,'BD Otimix'!O:O),0) -> 0 | AL91: =IFERROR(F91/$E$3/1000/AK91,0) -> 0
A92: 956821 | B92: GR-290 | C92: CARC C/GORD C/P PESC S/PESC C/SAMB | D92: INTEIROS | E92: BROILER MI | F92: =SUMIF('COLAR PLANO'!$A:$A,A92,'COLAR PLANO'!$D:$D) -> 0 | G92: =IFERROR(F92/($E$3*$C$3),0) -> 0 | H92: 0.7411 | I92: =IFERROR(G92/$D$3/H92,0) -> 0 | J92: =IFERROR(I92/$B$65,0) -> 0 | K92: 2.125 | L92: 8 | M92: 17 | N92: =IFERROR(G92/K92,"-") -> 0 | P92: =IFERROR(G92/M92,"-") -> 0 | U92: - | V92: FRG | W92: =Preencher!$B$3&U92&V92&A92&$W$6 -> JARINU-FRG956821MQ.TUNEL DE CG (CONTINUO) | X92: =Preencher!$B$3&U92&V92&A92&$X$6 -> JARINU-FRG956821MQ.TUNEL DE CG (CONTINUO) (1) | Y92: =Preencher!$B$3&U92&V92&A92&$Y$6 -> JARINU-FRG956821MQ.TUNEL DE CG (CONTINUO) (2) | Z92: =Preencher!$B$3&U92&V92&A92&$Z$6 -> JARINU-FRG956821MQ.TUNEL DE CG (CONTINUO) (3) | AA92: =Preencher!$B$3&U92&V92&A92&$AA$6 -> JARINU-FRG956821MQ.TUNEL DE CG (ESTATICO) | AB92: =Preencher!$B$3&U92&V92&A92&$AB$6 -> JARINU-FRG956821MQ.TUNEL DE CG (ESTATICO) (1) | AC92: =Preencher!$B$3&U92&V92&A92&$AC$6 -> JARINU-FRG956821MQ.TUNEL DE CG (ESTATICO) (2) | AD92: =IFERROR(SUMIF('BD Otimix'!A:A,'BD VOLUME'!X92,'BD Otimix'!O:O)+SUMIF('BD Otimix'!A:A,'BD VOLUME'!Y92,'BD Otimix'!O:O)+SUMIF('BD Otimix'!A:A,'BD VOLUME'!Z92,'BD Otimix'!O:O)+SUMIF('BD Otimix'!A:A,'BD VOLUME'!AA92,'BD Otimix'!O:O)+SUMIF('BD Otimix'!A:A,'BD VOLUME'!AB92,'BD Otimix'!O:O)+SUMIF('BD Otimix'!A:A,'BD VOLUME'!AC92,'BD Otimix'!O:O)+SUMIF('BD Otimix'!A:A,'BD VOLUME'!W92,'BD Otimix'!O:O),0) -> 0 | AE92: =IFERROR(F92/$E$3/1000/AD92,0) -> 0 | AF92: =Preencher!$B$3&$U$8&$V$8&A92&$AF$6 -> JARINU-FRG956821MQ.GIROFREEZER | AG92: =Preencher!$B$3&$U$8&$V$8&A92&$AG$6 -> JARINU-FRG956821MQ.GIROFREEZER (1) | AH92: =Preencher!$B$3&$U$8&$V$8&A92&$AH$6 -> JARINU-FRG956821MQ.GIROFREEZER (2) | AI92: =Preencher!$B$3&$U$8&$V$8&A92&$AI$6 -> JARINU-FRG956821MQ.GIROFREEZER REV04 | AJ92: =Preencher!$B$3&$U$8&$V$8&A92&$AJ$6 -> JARINU-FRG956821MQ.GIROFREEZER (3) | AK92: =IFERROR(SUMIF('BD Otimix'!A:A,'BD VOLUME'!AG92,'BD Otimix'!O:O)+SUMIF('BD Otimix'!A:A,'BD VOLUME'!AH92,'BD Otimix'!O:O)+SUMIF('BD Otimix'!A:A,'BD VOLUME'!AI92,'BD Otimix'!O:O)+SUMIF('BD Otimix'!A:A,'BD VOLUME'!AJ92,'BD Otimix'!O:O)+SUMIF('BD Otimix'!A:A,'BD VOLUME'!AF92,'BD Otimix'!O:O),0) -> 0 | AL92: =IFERROR(F92/$E$3/1000/AK92,0) -> 0
A93: 925128 | B93: GR 652 | C93: CARC C/GORD C/P PESC S/PESC C/SAMB | D93: INTEIROS | E93: BROILER MI | F93: =SUMIF('COLAR PLANO'!$A:$A,A93,'COLAR PLANO'!$D:$D) -> 0 | G93: =IFERROR(F93/($E$3*$C$3),0) -> 0 | H93: 0.7401 | I93: =IFERROR(G93/$D$3/H93,0) -> 0 | J93: =IFERROR(I93/$B$65,0) -> 0 | K93: 2.125 | L93: 8 | M93: 17 | N93: =IFERROR(G93/K93,"-") -> 0 | P93: =IFERROR(G93/M93,"-") -> 0 | U93: - | V93: FRG | W93: =Preencher!$B$3&U93&V93&A93&$W$6 -> JARINU-FRG925128MQ.TUNEL DE CG (CONTINUO) | X93: =Preencher!$B$3&U93&V93&A93&$X$6 -> JARINU-FRG925128MQ.TUNEL DE CG (CONTINUO) (1) | Y93: =Preencher!$B$3&U93&V93&A93&$Y$6 -> JARINU-FRG925128MQ.TUNEL DE CG (CONTINUO) (2) | Z93: =Preencher!$B$3&U93&V93&A93&$Z$6 -> JARINU-FRG925128MQ.TUNEL DE CG (CONTINUO) (3) | AA93: =Preencher!$B$3&U93&V93&A93&$AA$6 -> JARINU-FRG925128MQ.TUNEL DE CG (ESTATICO) | AB93: =Preencher!$B$3&U93&V93&A93&$AB$6 -> JARINU-FRG925128MQ.TUNEL DE CG (ESTATICO) (1) | AC93: =Preencher!$B$3&U93&V93&A93&$AC$6 -> JARINU-FRG925128MQ.TUNEL DE CG (ESTATICO) (2) | AD93: =IFERROR(SUMIF('BD Otimix'!A:A,'BD VOLUME'!X93,'BD Otimix'!O:O)+SUMIF('BD Otimix'!A:A,'BD VOLUME'!Y93,'BD Otimix'!O:O)+SUMIF('BD Otimix'!A:A,'BD VOLUME'!Z93,'BD Otimix'!O:O)+SUMIF('BD Otimix'!A:A,'BD VOLUME'!AA93,'BD Otimix'!O:O)+SUMIF('BD Otimix'!A:A,'BD VOLUME'!AB93,'BD Otimix'!O:O)+SUMIF('BD Otimix'!A:A,'BD VOLUME'!AC93,'BD Otimix'!O:O)+SUMIF('BD Otimix'!A:A,'BD VOLUME'!W93,'BD Otimix'!O:O),0) -> 0 | AE93: =IFERROR(F93/$E$3/1000/AD93,0) -> 0 | AF93: =Preencher!$B$3&$U$8&$V$8&A93&$AF$6 -> JARINU-FRG925128MQ.GIROFREEZER | AG93: =Preencher!$B$3&$U$8&$V$8&A93&$AG$6 -> JARINU-FRG925128MQ.GIROFREEZER (1) | AH93: =Preencher!$B$3&$U$8&$V$8&A93&$AH$6 -> JARINU-FRG925128MQ.GIROFREEZER (2) | AI93: =Preencher!$B$3&$U$8&$V$8&A93&$AI$6 -> JARINU-FRG925128MQ.GIROFREEZER REV04 | AJ93: =Preencher!$B$3&$U$8&$V$8&A93&$AJ$6 -> JARINU-FRG925128MQ.GIROFREEZER (3) | AK93: =IFERROR(SUMIF('BD Otimix'!A:A,'BD VOLUME'!AG93,'BD Otimix'!O:O)+SUMIF('BD Otimix'!A:A,'BD VOLUME'!AH93,'BD Otimix'!O:O)+SUMIF('BD Otimix'!A:A,'BD VOLUME'!AI93,'BD Otimix'!O:O)+SUMIF('BD Otimix'!A:A,'BD VOLUME'!AJ93,'BD Otimix'!O:O)+SUMIF('BD Otimix'!A:A,'BD VOLUME'!AF93,'BD Otimix'!O:O),0) -> 0 | AL93: =IFERROR(F93/$E$3/1000/AK93,0) -> 0
A94: 985767 | C94: CARC C/GORD C/P PESC S/PESC C/SAMB | D94: INTEIROS | E94: BROILER MI | F94: =SUMIF('COLAR PLANO'!$A:$A,A94,'COLAR PLANO'!$D:$D) -> 0 | G94: =IFERROR(F94/($E$3*$C$3),0) -> 0 | H94: 0.7958 | I94: =IFERROR(G94/$D$3/H94,0) -> 0 | J94: =IFERROR(I94/$B$65,0) -> 0 | K94: 2.125 | L94: 8 | M94: 17 | N94: =IFERROR(G94/K94,"-") -> 0 | P94: =IFERROR(G94/M94,"-") -> 0 | U94: - | V94: FRG | W94: =Preencher!$B$3&U94&V94&A94&$W$6 -> JARINU-FRG985767MQ.TUNEL DE CG (CONTINUO) | X94: =Preencher!$B$3&U94&V94&A94&$X$6 -> JARINU-FRG985767MQ.TUNEL DE CG (CONTINUO) (1) | Y94: =Preencher!$B$3&U94&V94&A94&$Y$6 -> JARINU-FRG985767MQ.TUNEL DE CG (CONTINUO) (2) | Z94: =Preencher!$B$3&U94&V94&A94&$Z$6 -> JARINU-FRG985767MQ.TUNEL DE CG (CONTINUO) (3) | AA94: =Preencher!$B$3&U94&V94&A94&$AA$6 -> JARINU-FRG985767MQ.TUNEL DE CG (ESTATICO) | AB94: =Preencher!$B$3&U94&V94&A94&$AB$6 -> JARINU-FRG985767MQ.TUNEL DE CG (ESTATICO) (1) | AC94: =Preencher!$B$3&U94&V94&A94&$AC$6 -> JARINU-FRG985767MQ.TUNEL DE CG (ESTATICO) (2) | AD94: =IFERROR(SUMIF('BD Otimix'!A:A,'BD VOLUME'!X94,'BD Otimix'!O:O)+SUMIF('BD Otimix'!A:A,'BD VOLUME'!Y94,'BD Otimix'!O:O)+SUMIF('BD Otimix'!A:A,'BD VOLUME'!Z94,'BD Otimix'!O:O)+SUMIF('BD Otimix'!A:A,'BD VOLUME'!AA94,'BD Otimix'!O:O)+SUMIF('BD Otimix'!A:A,'BD VOLUME'!AB94,'BD Otimix'!O:O)+SUMIF('BD Otimix'!A:A,'BD VOLUME'!AC94,'BD Otimix'!O:O)+SUMIF('BD Otimix'!A:A,'BD VOLUME'!W94,'BD Otimix'!O:O),0) -> 0 | AE94: =IFERROR(F94/$E$3/1000/AD94,0) -> 0 | AF94: =Preencher!$B$3&$U$8&$V$8&A94&$AF$6 -> JARINU-FRG985767MQ.GIROFREEZER | AG94: =Preencher!$B$3&$U$8&$V$8&A94&$AG$6 -> JARINU-FRG985767MQ.GIROFREEZER (1) | AH94: =Preencher!$B$3&$U$8&$V$8&A94&$AH$6 -> JARINU-FRG985767MQ.GIROFREEZER (2) | AI94: =Preencher!$B$3&$U$8&$V$8&A94&$AI$6 -> JARINU-FRG985767MQ.GIROFREEZER REV04 | AJ94: =Preencher!$B$3&$U$8&$V$8&A94&$AJ$6 -> JARINU-FRG985767MQ.GIROFREEZER (3) | AK94: =IFERROR(SUMIF('BD Otimix'!A:A,'BD VOLUME'!AG94,'BD Otimix'!O:O)+SUMIF('BD Otimix'!A:A,'BD VOLUME'!AH94,'BD Otimix'!O:O)+SUMIF('BD Otimix'!A:A,'BD VOLUME'!AI94,'BD Otimix'!O:O)+SUMIF('BD Otimix'!A:A,'BD VOLUME'!AJ94,'BD Otimix'!O:O)+SUMIF('BD Otimix'!A:A,'BD VOLUME'!AF94,'BD Otimix'!O:O),0) -> 0 | AL94: =IFERROR(F94/$E$3/1000/AK94,0) -> 0
A95: 985996 | C95: CARC C/GORD C/P PESC S/PESC C/SAMB | D95: INTEIROS | E95: Frango s/ miudos | F95: =SUMIF('COLAR PLANO'!$A:$A,A95,'COLAR PLANO'!$D:$D) -> 0 | G95: =IFERROR(F95/($E$3*$C$3),0) -> 0 | H95: 0.7799 | I95: =IFERROR(G95/$D$3/H95,0) -> 0 | J95: =IFERROR(I95/$B$65,0) -> 0 | K95: 2.125 | L95: 8 | M95: 17 | N95: =IFERROR(G95/K95,"-") -> 0 | U95: - | V95: FRG | W95: =Preencher!$B$3&U95&V95&A95&$W$6 -> JARINU-FRG985996MQ.TUNEL DE CG (CONTINUO) | X95: =Preencher!$B$3&U95&V95&A95&$X$6 -> JARINU-FRG985996MQ.TUNEL DE CG (CONTINUO) (1) | Y95: =Preencher!$B$3&U95&V95&A95&$Y$6 -> JARINU-FRG985996MQ.TUNEL DE CG (CONTINUO) (2) | Z95: =Preencher!$B$3&U95&V95&A95&$Z$6 -> JARINU-FRG985996MQ.TUNEL DE CG (CONTINUO) (3) | AA95: =Preencher!$B$3&U95&V95&A95&$AA$6 -> JARINU-FRG985996MQ.TUNEL DE CG (ESTATICO) | AB95: =Preencher!$B$3&U95&V95&A95&$AB$6 -> JARINU-FRG985996MQ.TUNEL DE CG (ESTATICO) (1) | AC95: =Preencher!$B$3&U95&V95&A95&$AC$6 -> JARINU-FRG985996MQ.TUNEL DE CG (ESTATICO) (2) | AD95: =IFERROR(SUMIF('BD Otimix'!A:A,'BD VOLUME'!X95,'BD Otimix'!O:O)+SUMIF('BD Otimix'!A:A,'BD VOLUME'!Y95,'BD Otimix'!O:O)+SUMIF('BD Otimix'!A:A,'BD VOLUME'!Z95,'BD Otimix'!O:O)+SUMIF('BD Otimix'!A:A,'BD VOLUME'!AA95,'BD Otimix'!O:O)+SUMIF('BD Otimix'!A:A,'BD VOLUME'!AB95,'BD Otimix'!O:O)+SUMIF('BD Otimix'!A:A,'BD VOLUME'!AC95,'BD Otimix'!O:O)+SUMIF('BD Otimix'!A:A,'BD VOLUME'!W95,'BD Otimix'!O:O),0) -> 0 | AE95: =IFERROR(F95/$E$3/1000/AD95,0) -> 0 | AF95: =Preencher!$B$3&$U$8&$V$8&A95&$AF$6 -> JARINU-FRG985996MQ.GIROFREEZER | AG95: =Preencher!$B$3&$U$8&$V$8&A95&$AG$6 -> JARINU-FRG985996MQ.GIROFREEZER (1) | AH95: =Preencher!$B$3&$U$8&$V$8&A95&$AH$6 -> JARINU-FRG985996MQ.GIROFREEZER (2) | AI95: =Preencher!$B$3&$U$8&$V$8&A95&$AI$6 -> JARINU-FRG985996MQ.GIROFREEZER REV04 | AJ95: =Preencher!$B$3&$U$8&$V$8&A95&$AJ$6 -> JARINU-FRG985996MQ.GIROFREEZER (3) | AK95: =IFERROR(SUMIF('BD Otimix'!A:A,'BD VOLUME'!AG95,'BD Otimix'!O:O)+SUMIF('BD Otimix'!A:A,'BD VOLUME'!AH95,'BD Otimix'!O:O)+SUMIF('BD Otimix'!A:A,'BD VOLUME'!AI95,'BD Otimix'!O:O)+SUMIF('BD Otimix'!A:A,'BD VOLUME'!AJ95,'BD Otimix'!O:O)+SUMIF('BD Otimix'!A:A,'BD VOLUME'!AF95,'BD Otimix'!O:O),0) -> 0 | AL95: =IFERROR(F95/$E$3/1000/AK95,0) -> 0
A96: 986020 | C96: CARC C/GORD C/P PESC S/PESC C/SAMB | D96: INTEIROS | E96: BROILER MI | F96: =SUMIF('COLAR PLANO'!$A:$A,A96,'COLAR PLANO'!$D:$D) -> 0 | G96: =IFERROR(F96/($E$3*$C$3),0) -> 0 | H96: 0.7958 | I96: =IFERROR(G96/$D$3/H96,0) -> 0 | J96: =IFERROR(I96/$B$65,0) -> 0 | N96: =IFERROR(G96/K96,"-") -> - | P96: =IFERROR(G96/M96,"-") -> - | U96: - | V96: FRG | W96: =Preencher!$B$3&U96&V96&A96&$W$6 -> JARINU-FRG986020MQ.TUNEL DE CG (CONTINUO) | X96: =Preencher!$B$3&U96&V96&A96&$X$6 -> JARINU-FRG986020MQ.TUNEL DE CG (CONTINUO) (1) | Y96: =Preencher!$B$3&U96&V96&A96&$Y$6 -> JARINU-FRG986020MQ.TUNEL DE CG (CONTINUO) (2) | Z96: =Preencher!$B$3&U96&V96&A96&$Z$6 -> JARINU-FRG986020MQ.TUNEL DE CG (CONTINUO) (3) | AA96: =Preencher!$B$3&U96&V96&A96&$AA$6 -> JARINU-FRG986020MQ.TUNEL DE CG (ESTATICO) | AB96: =Preencher!$B$3&U96&V96&A96&$AB$6 -> JARINU-FRG986020MQ.TUNEL DE CG (ESTATICO) (1) | AC96: =Preencher!$B$3&U96&V96&A96&$AC$6 -> JARINU-FRG986020MQ.TUNEL DE CG (ESTATICO) (2) | AD96: =IFERROR(SUMIF('BD Otimix'!A:A,'BD VOLUME'!X96,'BD Otimix'!O:O)+SUMIF('BD Otimix'!A:A,'BD VOLUME'!Y96,'BD Otimix'!O:O)+SUMIF('BD Otimix'!A:A,'BD VOLUME'!Z96,'BD Otimix'!O:O)+SUMIF('BD Otimix'!A:A,'BD VOLUME'!AA96,'BD Otimix'!O:O)+SUMIF('BD Otimix'!A:A,'BD VOLUME'!AB96,'BD Otimix'!O:O)+SUMIF('BD Otimix'!A:A,'BD VOLUME'!AC96,'BD Otimix'!O:O)+SUMIF('BD Otimix'!A:A,'BD VOLUME'!W96,'BD Otimix'!O:O),0) -> 0 | AE96: =IFERROR(F96/$E$3/1000/AD96,0) -> 0 | AF96: =Preencher!$B$3&$U$8&$V$8&A96&$AF$6 -> JARINU-FRG986020MQ.GIROFREEZER | AG96: =Preencher!$B$3&$U$8&$V$8&A96&$AG$6 -> JARINU-FRG986020MQ.GIROFREEZER (1) | AH96: =Preencher!$B$3&$U$8&$V$8&A96&$AH$6 -> JARINU-FRG986020MQ.GIROFREEZER (2) | AI96: =Preencher!$B$3&$U$8&$V$8&A96&$AI$6 -> JARINU-FRG986020MQ.GIROFREEZER REV04 | AJ96: =Preencher!$B$3&$U$8&$V$8&A96&$AJ$6 -> JARINU-FRG986020MQ.GIROFREEZER (3) | AK96: =IFERROR(SUMIF('BD Otimix'!A:A,'BD VOLUME'!AG96,'BD Otimix'!O:O)+SUMIF('BD Otimix'!A:A,'BD VOLUME'!AH96,'BD Otimix'!O:O)+SUMIF('BD Otimix'!A:A,'BD VOLUME'!AI96,'BD Otimix'!O:O)+SUMIF('BD Otimix'!A:A,'BD VOLUME'!AJ96,'BD Otimix'!O:O)+SUMIF('BD Otimix'!A:A,'BD VOLUME'!AF96,'BD Otimix'!O:O),0) -> 0 | AL96: =IFERROR(F96/$E$3/1000/AK96,0) -> 0
A97: 986127 | C97: CARC C/GORD C/P PESC S/PESC C/SAMB | D97: INTEIROS | E97: BROILER MI | F97: =SUMIF('COLAR PLANO'!$A:$A,A97,'COLAR PLANO'!$D:$D) -> 0 | G97: =IFERROR(F97/($E$3*$C$3),0) -> 0 | H97: 0.7958 | I97: =IFERROR(G97/$D$3/H97,0) -> 0 | J97: =IFERROR(I97/$B$65,0) -> 0 | N97: =IFERROR(G97/K97,"-") -> - | P97: =IFERROR(G97/M97,"-") -> - | U97: - | V97: FRG | W97: =Preencher!$B$3&U97&V97&A97&$W$6 -> JARINU-FRG986127MQ.TUNEL DE CG (CONTINUO) | X97: =Preencher!$B$3&U97&V97&A97&$X$6 -> JARINU-FRG986127MQ.TUNEL DE CG (CONTINUO) (1) | Y97: =Preencher!$B$3&U97&V97&A97&$Y$6 -> JARINU-FRG986127MQ.TUNEL DE CG (CONTINUO) (2) | Z97: =Preencher!$B$3&U97&V97&A97&$Z$6 -> JARINU-FRG986127MQ.TUNEL DE CG (CONTINUO) (3) | AA97: =Preencher!$B$3&U97&V97&A97&$AA$6 -> JARINU-FRG986127MQ.TUNEL DE CG (ESTATICO) | AB97: =Preencher!$B$3&U97&V97&A97&$AB$6 -> JARINU-FRG986127MQ.TUNEL DE CG (ESTATICO) (1) | AC97: =Preencher!$B$3&U97&V97&A97&$AC$6 -> JARINU-FRG986127MQ.TUNEL DE CG (ESTATICO) (2) | AD97: =IFERROR(SUMIF('BD Otimix'!A:A,'BD VOLUME'!X97,'BD Otimix'!O:O)+SUMIF('BD Otimix'!A:A,'BD VOLUME'!Y97,'BD Otimix'!O:O)+SUMIF('BD Otimix'!A:A,'BD VOLUME'!Z97,'BD Otimix'!O:O)+SUMIF('BD Otimix'!A:A,'BD VOLUME'!AA97,'BD Otimix'!O:O)+SUMIF('BD Otimix'!A:A,'BD VOLUME'!AB97,'BD Otimix'!O:O)+SUMIF('BD Otimix'!A:A,'BD VOLUME'!AC97,'BD Otimix'!O:O)+SUMIF('BD Otimix'!A:A,'BD VOLUME'!W97,'BD Otimix'!O:O),0) -> 0 | AE97: =IFERROR(F97/$E$3/1000/AD97,0) -> 0 | AF97: =Preencher!$B$3&$U$8&$V$8&A97&$AF$6 -> JARINU-FRG986127MQ.GIROFREEZER | AG97: =Preencher!$B$3&$U$8&$V$8&A97&$AG$6 -> JARINU-FRG986127MQ.GIROFREEZER (1) | AH97: =Preencher!$B$3&$U$8&$V$8&A97&$AH$6 -> JARINU-FRG986127MQ.GIROFREEZER (2) | AI97: =Preencher!$B$3&$U$8&$V$8&A97&$AI$6 -> JARINU-FRG986127MQ.GIROFREEZER REV04 | AJ97: =Preencher!$B$3&$U$8&$V$8&A97&$AJ$6 -> JARINU-FRG986127MQ.GIROFREEZER (3) | AK97: =IFERROR(SUMIF('BD Otimix'!A:A,'BD VOLUME'!AG97,'BD Otimix'!O:O)+SUMIF('BD Otimix'!A:A,'BD VOLUME'!AH97,'BD Otimix'!O:O)+SUMIF('BD Otimix'!A:A,'BD VOLUME'!AI97,'BD Otimix'!O:O)+SUMIF('BD Otimix'!A:A,'BD VOLUME'!AJ97,'BD Otimix'!O:O)+SUMIF('BD Otimix'!A:A,'BD VOLUME'!AF97,'BD Otimix'!O:O),0) -> 0 | AL97: =IFERROR(F97/$E$3/1000/AK97,0) -> 0
A98: 124146 | B98: GR-262 | C98: CARC C/GORD C/P PESC S/PESC C/SAMB | D98: INTEIROS | E98: BROILER MI | F98: =SUMIF('COLAR PLANO'!$A:$A,A98,'COLAR PLANO'!$D:$D) -> 0 | G98: =IFERROR(F98/($E$3*$C$3),0) -> 0 | H98: 0.7424 | I98: =IFERROR(G98/$D$3/H98,0) -> 0 | J98: =IFERROR(I98/$B$65,0) -> 0 | K98: 1.2 | L98: 10 | M98: 12 | N98: =IFERROR(G98/K98,"-") -> 0 | P98: =IFERROR(G98/M98,"-") -> 0 | U98: - | V98: FRG | W98: =Preencher!$B$3&U98&V98&A98&$W$6 -> JARINU-FRG124146MQ.TUNEL DE CG (CONTINUO) | X98: =Preencher!$B$3&U98&V98&A98&$X$6 -> JARINU-FRG124146MQ.TUNEL DE CG (CONTINUO) (1) | Y98: =Preencher!$B$3&U98&V98&A98&$Y$6 -> JARINU-FRG124146MQ.TUNEL DE CG (CONTINUO) (2) | Z98: =Preencher!$B$3&U98&V98&A98&$Z$6 -> JARINU-FRG124146MQ.TUNEL DE CG (CONTINUO) (3) | AA98: =Preencher!$B$3&U98&V98&A98&$AA$6 -> JARINU-FRG124146MQ.TUNEL DE CG (ESTATICO) | AB98: =Preencher!$B$3&U98&V98&A98&$AB$6 -> JARINU-FRG124146MQ.TUNEL DE CG (ESTATICO) (1) | AC98: =Preencher!$B$3&U98&V98&A98&$AC$6 -> JARINU-FRG124146MQ.TUNEL DE CG (ESTATICO) (2) | AD98: =IFERROR(SUMIF('BD Otimix'!A:A,'BD VOLUME'!X98,'BD Otimix'!O:O)+SUMIF('BD Otimix'!A:A,'BD VOLUME'!Y98,'BD Otimix'!O:O)+SUMIF('BD Otimix'!A:A,'BD VOLUME'!Z98,'BD Otimix'!O:O)+SUMIF('BD Otimix'!A:A,'BD VOLUME'!AA98,'BD Otimix'!O:O)+SUMIF('BD Otimix'!A:A,'BD VOLUME'!AB98,'BD Otimix'!O:O)+SUMIF('BD Otimix'!A:A,'BD VOLUME'!AC98,'BD Otimix'!O:O)+SUMIF('BD Otimix'!A:A,'BD VOLUME'!W98,'BD Otimix'!O:O),0) -> 0 | AE98: =IFERROR(F98/$E$3/1000/AD98,0) -> 0 | AF98: =Preencher!$B$3&$U$8&$V$8&A98&$AF$6 -> JARINU-FRG124146MQ.GIROFREEZER | AG98: =Preencher!$B$3&$U$8&$V$8&A98&$AG$6 -> JARINU-FRG124146MQ.GIROFREEZER (1) | AH98: =Preencher!$B$3&$U$8&$V$8&A98&$AH$6 -> JARINU-FRG124146MQ.GIROFREEZER (2) | AI98: =Preencher!$B$3&$U$8&$V$8&A98&$AI$6 -> JARINU-FRG124146MQ.GIROFREEZER REV04 | AJ98: =Preencher!$B$3&$U$8&$V$8&A98&$AJ$6 -> JARINU-FRG124146MQ.GIROFREEZER (3) | AK98: =IFERROR(SUMIF('BD Otimix'!A:A,'BD VOLUME'!AG98,'BD Otimix'!O:O)+SUMIF('BD Otimix'!A:A,'BD VOLUME'!AH98,'BD Otimix'!O:O)+SUMIF('BD Otimix'!A:A,'BD VOLUME'!AI98,'BD Otimix'!O:O)+SUMIF('BD Otimix'!A:A,'BD VOLUME'!AJ98,'BD Otimix'!O:O)+SUMIF('BD Otimix'!A:A,'BD VOLUME'!AF98,'BD Otimix'!O:O),0) -> 0 | AL98: =IFERROR(F98/$E$3/1000/AK98,0) -> 0
A99: 124148 | B99: GR-264 | C99: CARC C/GORD C/P PESC S/PESC C/SAMB | D99: INTEIROS | E99: BROILER MI | F99: =SUMIF('COLAR PLANO'!$A:$A,A99,'COLAR PLANO'!$D:$D) -> 0 | G99: =IFERROR(F99/($E$3*$C$3),0) -> 0 | H99: 0.7424 | I99: =IFERROR(G99/$D$3/H99,0) -> 0 | J99: =IFERROR(I99/$B$65,0) -> 0 | K99: 1.4 | L99: 10 | M99: 14 | N99: =IFERROR(G99/K99,"-") -> 0 | P99: =IFERROR(G99/M99,"-") -> 0 | U99: - | V99: FRG | W99: =Preencher!$B$3&U99&V99&A99&$W$6 -> JARINU-FRG124148MQ.TUNEL DE CG (CONTINUO) | X99: =Preencher!$B$3&U99&V99&A99&$X$6 -> JARINU-FRG124148MQ.TUNEL DE CG (CONTINUO) (1) | Y99: =Preencher!$B$3&U99&V99&A99&$Y$6 -> JARINU-FRG124148MQ.TUNEL DE CG (CONTINUO) (2) | Z99: =Preencher!$B$3&U99&V99&A99&$Z$6 -> JARINU-FRG124148MQ.TUNEL DE CG (CONTINUO) (3) | AA99: =Preencher!$B$3&U99&V99&A99&$AA$6 -> JARINU-FRG124148MQ.TUNEL DE CG (ESTATICO) | AB99: =Preencher!$B$3&U99&V99&A99&$AB$6 -> JARINU-FRG124148MQ.TUNEL DE CG (ESTATICO) (1) | AC99: =Preencher!$B$3&U99&V99&A99&$AC$6 -> JARINU-FRG124148MQ.TUNEL DE CG (ESTATICO) (2) | AD99: =IFERROR(SUMIF('BD Otimix'!A:A,'BD VOLUME'!X99,'BD Otimix'!O:O)+SUMIF('BD Otimix'!A:A,'BD VOLUME'!Y99,'BD Otimix'!O:O)+SUMIF('BD Otimix'!A:A,'BD VOLUME'!Z99,'BD Otimix'!O:O)+SUMIF('BD Otimix'!A:A,'BD VOLUME'!AA99,'BD Otimix'!O:O)+SUMIF('BD Otimix'!A:A,'BD VOLUME'!AB99,'BD Otimix'!O:O)+SUMIF('BD Otimix'!A:A,'BD VOLUME'!AC99,'BD Otimix'!O:O)+SUMIF('BD Otimix'!A:A,'BD VOLUME'!W99,'BD Otimix'!O:O),0) -> 0 | AE99: =IFERROR(F99/$E$3/1000/AD99,0) -> 0 | AF99: =Preencher!$B$3&$U$8&$V$8&A99&$AF$6 -> JARINU-FRG124148MQ.GIROFREEZER | AG99: =Preencher!$B$3&$U$8&$V$8&A99&$AG$6 -> JARINU-FRG124148MQ.GIROFREEZER (1) | AH99: =Preencher!$B$3&$U$8&$V$8&A99&$AH$6 -> JARINU-FRG124148MQ.GIROFREEZER (2) | AI99: =Preencher!$B$3&$U$8&$V$8&A99&$AI$6 -> JARINU-FRG124148MQ.GIROFREEZER REV04 | AJ99: =Preencher!$B$3&$U$8&$V$8&A99&$AJ$6 -> JARINU-FRG124148MQ.GIROFREEZER (3) | AK99: =IFERROR(SUMIF('BD Otimix'!A:A,'BD VOLUME'!AG99,'BD Otimix'!O:O)+SUMIF('BD Otimix'!A:A,'BD VOLUME'!AH99,'BD Otimix'!O:O)+SUMIF('BD Otimix'!A:A,'BD VOLUME'!AI99,'BD Otimix'!O:O)+SUMIF('BD Otimix'!A:A,'BD VOLUME'!AJ99,'BD Otimix'!O:O)+SUMIF('BD Otimix'!A:A,'BD VOLUME'!AF99,'BD Otimix'!O:O),0) -> 0 | AL99: =IFERROR(F99/$E$3/1000/AK99,0) -> 0
A100: 960632 | B100: GR-694 | C100: CARC C/GORD C/P PESC S/PESC C/SAMB | D100: INTEIROS | E100: BROILER MI | F100: =SUMIF('COLAR PLANO'!$A:$A,A100,'COLAR PLANO'!$D:$D) -> 0 | G100: =IFERROR(F100/($E$3*$C$3),0) -> 0 | H100: 0.7772 | I100: =IFERROR(G100/$D$3/H100,0) -> 0 | J100: =IFERROR(I100/$B$65,0) -> 0 | N100: =IFERROR(G100/K100,"-") -> - | P100: =IFERROR(G100/M100,"-") -> - | U100: - | V100: FRG | W100: =Preencher!$B$3&U100&V100&A100&$W$6 -> JARINU-FRG960632MQ.TUNEL DE CG (CONTINUO) | X100: =Preencher!$B$3&U100&V100&A100&$X$6 -> JARINU-FRG960632MQ.TUNEL DE CG (CONTINUO) (1) | Y100: =Preencher!$B$3&U100&V100&A100&$Y$6 -> JARINU-FRG960632MQ.TUNEL DE CG (CONTINUO) (2) | Z100: =Preencher!$B$3&U100&V100&A100&$Z$6 -> JARINU-FRG960632MQ.TUNEL DE CG (CONTINUO) (3) | AA100: =Preencher!$B$3&U100&V100&A100&$AA$6 -> JARINU-FRG960632MQ.TUNEL DE CG (ESTATICO) | AB100: =Preencher!$B$3&U100&V100&A100&$AB$6 -> JARINU-FRG960632MQ.TUNEL DE CG (ESTATICO) (1) | AC100: =Preencher!$B$3&U100&V100&A100&$AC$6 -> JARINU-FRG960632MQ.TUNEL DE CG (ESTATICO) (2) | AD100: =IFERROR(SUMIF('BD Otimix'!A:A,'BD VOLUME'!X100,'BD Otimix'!O:O)+SUMIF('BD Otimix'!A:A,'BD VOLUME'!Y100,'BD Otimix'!O:O)+SUMIF('BD Otimix'!A:A,'BD VOLUME'!Z100,'BD Otimix'!O:O)+SUMIF('BD Otimix'!A:A,'BD VOLUME'!AA100,'BD Otimix'!O:O)+SUMIF('BD Otimix'!A:A,'BD VOLUME'!AB100,'BD Otimix'!O:O)+SUMIF('BD Otimix'!A:A,'BD VOLUME'!AC100,'BD Otimix'!O:O)+SUMIF('BD Otimix'!A:A,'BD VOLUME'!W100,'BD Otimix'!O:O),0) -> 0 | AE100: =IFERROR(F100/$E$3/1000/AD100,0) -> 0 | AF100: =Preencher!$B$3&$U$8&$V$8&A100&$AF$6 -> JARINU-FRG960632MQ.GIROFREEZER | AG100: =Preencher!$B$3&$U$8&$V$8&A100&$AG$6 -> JARINU-FRG960632MQ.GIROFREEZER (1) | AH100: =Preencher!$B$3&$U$8&$V$8&A100&$AH$6 -> JARINU-FRG960632MQ.GIROFREEZER (2) | AI100: =Preencher!$B$3&$U$8&$V$8&A100&$AI$6 -> JARINU-FRG960632MQ.GIROFREEZER REV04 | AJ100: =Preencher!$B$3&$U$8&$V$8&A100&$AJ$6 -> JARINU-FRG960632MQ.GIROFREEZER (3) | AK100: =IFERROR(SUMIF('BD Otimix'!A:A,'BD VOLUME'!AG100,'BD Otimix'!O:O)+SUMIF('BD Otimix'!A:A,'BD VOLUME'!AH100,'BD Otimix'!O:O)+SUMIF('BD Otimix'!A:A,'BD VOLUME'!AI100,'BD Otimix'!O:O)+SUMIF('BD Otimix'!A:A,'BD VOLUME'!AJ100,'BD Otimix'!O:O)+SUMIF('BD Otimix'!A:A,'BD VOLUME'!AF100,'BD Otimix'!O:O),0) -> 0 | AL100: =IFERROR(F100/$E$3/1000/AK100,0) -> 0
A101: 960640 | B101: GR-695 | C101: CARC C/GORD C/P PESC S/PESC C/SAMB | D101: INTEIROS | E101: BROILER MI | F101: =SUMIF('COLAR PLANO'!$A:$A,A101,'COLAR PLANO'!$D:$D) -> 0 | G101: =IFERROR(F101/($E$3*$C$3),0) -> 0 | H101: 0.7772 | I101: =IFERROR(G101/$D$3/H101,0) -> 0 | J101: =IFERROR(I101/$B$65,0) -> 0 | N101: =IFERROR(G101/K101,"-") -> - | P101: =IFERROR(G101/M101,"-") -> - | U101: - | V101: FRG | W101: =Preencher!$B$3&U101&V101&A101&$W$6 -> JARINU-FRG960640MQ.TUNEL DE CG (CONTINUO) | X101: =Preencher!$B$3&U101&V101&A101&$X$6 -> JARINU-FRG960640MQ.TUNEL DE CG (CONTINUO) (1) | Y101: =Preencher!$B$3&U101&V101&A101&$Y$6 -> JARINU-FRG960640MQ.TUNEL DE CG (CONTINUO) (2) | Z101: =Preencher!$B$3&U101&V101&A101&$Z$6 -> JARINU-FRG960640MQ.TUNEL DE CG (CONTINUO) (3) | AA101: =Preencher!$B$3&U101&V101&A101&$AA$6 -> JARINU-FRG960640MQ.TUNEL DE CG (ESTATICO) | AB101: =Preencher!$B$3&U101&V101&A101&$AB$6 -> JARINU-FRG960640MQ.TUNEL DE CG (ESTATICO) (1) | AC101: =Preencher!$B$3&U101&V101&A101&$AC$6 -> JARINU-FRG960640MQ.TUNEL DE CG (ESTATICO) (2) | AD101: =IFERROR(SUMIF('BD Otimix'!A:A,'BD VOLUME'!X101,'BD Otimix'!O:O)+SUMIF('BD Otimix'!A:A,'BD VOLUME'!Y101,'BD Otimix'!O:O)+SUMIF('BD Otimix'!A:A,'BD VOLUME'!Z101,'BD Otimix'!O:O)+SUMIF('BD Otimix'!A:A,'BD VOLUME'!AA101,'BD Otimix'!O:O)+SUMIF('BD Otimix'!A:A,'BD VOLUME'!AB101,'BD Otimix'!O:O)+SUMIF('BD Otimix'!A:A,'BD VOLUME'!AC101,'BD Otimix'!O:O)+SUMIF('BD Otimix'!A:A,'BD VOLUME'!W101,'BD Otimix'!O:O),0) -> 0 | AE101: =IFERROR(F101/$E$3/1000/AD101,0) -> 0 | AF101: =Preencher!$B$3&$U$8&$V$8&A101&$AF$6 -> JARINU-FRG960640MQ.GIROFREEZER | AG101: =Preencher!$B$3&$U$8&$V$8&A101&$AG$6 -> JARINU-FRG960640MQ.GIROFREEZER (1) | AH101: =Preencher!$B$3&$U$8&$V$8&A101&$AH$6 -> JARINU-FRG960640MQ.GIROFREEZER (2) | AI101: =Preencher!$B$3&$U$8&$V$8&A101&$AI$6 -> JARINU-FRG960640MQ.GIROFREEZER REV04 | AJ101: =Preencher!$B$3&$U$8&$V$8&A101&$AJ$6 -> JARINU-FRG960640MQ.GIROFREEZER (3) | AK101: =IFERROR(SUMIF('BD Otimix'!A:A,'BD VOLUME'!AG101,'BD Otimix'!O:O)+SUMIF('BD Otimix'!A:A,'BD VOLUME'!AH101,'BD Otimix'!O:O)+SUMIF('BD Otimix'!A:A,'BD VOLUME'!AI101,'BD Otimix'!O:O)+SUMIF('BD Otimix'!A:A,'BD VOLUME'!AJ101,'BD Otimix'!O:O)+SUMIF('BD Otimix'!A:A,'BD VOLUME'!AF101,'BD Otimix'!O:O),0) -> 0 | AL101: =IFERROR(F101/$E$3/1000/AK101,0) -> 0
